Workbook

Sheet Janeiro 
A1: Nota Fiscal | B1: Emissão | C1: Destinatário | D1: Descrição | E1: Valor Venda | F1: Mão de Obra | G1: Vencimento | H1: Data pagto | I1: OBS | J1: Em aberto Valor | L1: Soares | N1: Componarte
A2: 16412 | B2: 08.01.25 | C2: Soares | D2: Croco metal | F2: 365.03 | G2: 05.02.25 | H2: 45691 | L2: =F73 -> 28250.66
A3: 16437 | B3: 10.01.25 | C3: Soares | D3: Croco | F3: 137.17 | G3: 06.02.25 | H3: 45691
F4: 136 | G4: 13.02.25 | H4: 45698
F5: 136 | G5: 20.02.25 | H5: 45708
A6: 16488 | B6: 14.01.25 | C6: Soares | F6: 89.65 | G6: 11.02.25 | H6: 45698
F7: 88 | G7: 18.02.25 | H7: 45706
F8: 88 | G8: 25.02.25 | H8: 45713
A9: 16540 | B9: 17.01.25 | C9: Soares | D9: Crocodile | F9: 135.24 | G9: 14.02.25 | H9: 45698
A10: 16542 | B10: 17.01.25 | C10: Soares | D10: Rafia glow | F10: 267.38 | G10: 14.02.25 | H10: 45698
A11: 16541 | B11: 17.01.25 | C11: Soares | D11: Rafia glow | F11: 423.78 | G11: 14.02.25 | H11: 45698
F12: 423.78 | G12: 21.02.25 | H12: 45698
F13: 423.78 | G13: 28.02.25 | H13: 45698
A14: 16545 | B14: 20.01.25 | C14: Soares | D14: Croco | F14: 1093.78 | G14: 17.02.25 | H14: 45706
F15: 1091 | G15: 24.02.25 | H15: 45712
F16: 1091 | G16: 03.03.25 | H16: 45721
A17: 16575 | B17: 21.01.25 | C17: Soares | D17: Croco | F17: 319.93 | G17: 18.02.25 | H17: 45706
F18: 317 | G18: 25.02.25 | H18: 45713
F19: 317 | G19: 04.03.25 | H19: 45721
A20: 16600 | B20: 22.01.25 | C20: Soares | D20: Rafia | F20: 361.31 | G20: 19.02.25 | H20: 45706
F21: 361 | G21: 26.02.25 | H21: 45714
F22: 361 | G22: 05.03.25 | H22: 45721
A23: 16615 | B23: 23.01.25 | C23: Soares | D23: Croco | F23: 138 | G23: 20.02.25 | H23: 45708
A24: 16616 | B24: 23.01.25 | C24: Soares | D24: Croco | F24: 374.96 | G24: 20.02.25 | H24: 45708
F25: 373 | G25: 27.02.25 | H25: 45715
F26: 373 | G26: 06.03.25 | H26: 45722
A27: 16618 | B27: 23.01.25 | C27: Soares | D27: Lezard Metalic | F27: 472.5 | G27: 20.02.25 | H27: 45708
F28: 470 | G28: 27.02.25 | H28: 45715
F29: 470 | G29: 06.03.25 | H29: 45722
A30: 16619 | B30: 23.01.25 | C30: Soares | D30: Lezard Metalic | F30: 468.13 | G30: 20.02.25 | H30: 45708
F31: 468 | G31: 27.02.25 | H31: 45715
F32: 468 | G32: 06.03.25 | H32: 45722
A33: DL | B33: 24.01.25 | C33: DL | D33: Materiais diversos | E33: 2637 | G33: 20.02.25 | J33: =E33 -> 2637 | K33: Venda Neomir
E34: 3800 | G34: 01.03.25 | J34: =E34 -> 3800 | K34: Venda Neomir
E35: 3800 | G35: 08.03.25 | J35: =E35 -> 3800 | K35: Venda Neomir
E36: 3800 | G36: 20.03.25 | J36: =E36 -> 3800 | K36: Venda Neomir
E37: 3800 | G37: 22.03.25 | J37: =E37 -> 3800 | K37: Venda Neomir
E38: 3800 | G38: 29.03.29 | J38: =E38 -> 3800 | K38: Venda Neomir
A39: 16639 | B39: 24.01.25 | C39: Soares | D39: Croco Metal | F39: 421.74 | G39: 21.02.25 | H39: 45708
F40: 421.74 | G40: 28.02.25 | H40: 45716
F41: 421.74 | G41: 07.03.25 | H41: 45723
A42: 16638 | B42: 24.01.25 | C42: Soares | D42: Croco metal | F42: 307.64 | G42: 21.02.25 | H42: 45708
F43: 307 | G43: 28.02.25 | H43: 45716
F44: 307 | G44: 07.03.25 | H44: 45723
A45: 16654 | B45: 27.01.25 | C45: Soares | D45: Rafia glow | F45: 133.03 | G45: 24.02.25 | H45: 45712
F46: 131 | G46: 03.03.25 | H46: 45721
F47: 131 | G47: 10.03.25 | H47: 45727
A48: 16656 | B48: 27.01.25 | C48: Soares | D48: Croco verniz | F48: 1131.67 | G48: 24.02.25 | H48: 45712
F49: 1129 | G49: 03.03.25 | H49: 45721
F50: 1129 | G50: 10.03.25 | H50: 45727
A51: 16687 | B51: 29.01.25 | C51: Soares | D51: Reptil verniz | F51: 320.39 | G51: 26.02.25 | H51: 45714
A52: 16688 | B52: 29.01.25 | C52: Soares | D52: Croco metal | F52: 428.15 | G52: 26.02.25 | H52: 45714
F53: 426 | G53: 05.03.25 | H53: 45721
F54: 426 | G54: 12.03.25 | H54: 45728
A55: 16704 | B55: 30.01.25 | C55: Soares | D55: Rafia glow | F55: 1359.52 | G55: 27.02.25 | H55: 45715
F56: 1358 | G56: 06.03.25 | H56: 45722
F57: 1358 | G57: 13.03.25 | H57: 45729
A58: 16726 | B58: 31.01.25 | C58: Soares | D58: Croco | F58: 310.34 | G58: 28.02.25 | H58: 45716
F59: 308 | G59: 07.03.25 | H59: 45723
F60: 308 | G60: 14.03.25 | H60: 45730
A61: 16727 | B61: 31.01.25 | C61: Soares | D61: Croco | F61: 134.55 | G61: 28.02.25 | H61: 45716
A62: 16728 | B62: 31.01.25 | C62: Soares | D62: Croco | F62: 415.04 | G62: 28.02.25 | H62: 45716
A63: 16728 | B63: 31.01.25 | C63: Soares | D63: Rafia glow | F63: 364.89 | G63: 28.02.25 | H63: 45716
F64: 363 | G64: 07.03.25 | H64: 45723
F65: 363 | G65: 14.03.25 | H65: 45730
A66: 16511 | B66: 15.01.25 | C66: Componarte | D66: Diamantina | F66: 389.8 | G66: 22.01.25 | H66: 45698
F67: 386 | G67: 29.01.25 | H67: 45698
F68: 386 | G68: 05.02.25 | H68: 45698
F69: 386 | G69: 12.02.25 | H69: 45699
F70: 386 | G70: 19.02.25 | H70: 45707
J72: =SUM(J2:J71) -> 21637
A73: Total Faturado Mão de Obra | E73: =SUM(E2:E72) -> 21637 | F73: =SUM(F2:F72) -> 28250.66
A74: Total Faturado Venda
D75: =(F73+E73) -> 49887.66
A78: Mês | B78: Frete 2021 | C78: Frete 2022 | D78: Frete 2023 | E78: Frete 2024 | F78: Frete 2025
A79: Janeiro | B79: 19219.28 | C79: 109492.58 | D79: 126073.37 | E79: 270562.53 | F79: =D75 -> 49887.66
A80: Fevereiro | B80: 18377.75 | C80: 151228.71 | D80: 166235.96 | E80: 324984.97
A81: Março | B81: 25009.87 | C81: 119148.49 | D81: 119814.85 | E81: 256001.57
A82: Abril | B82: 34211.96 | C82: 238129.97 | D82: 112668.22 | E82: 136419.94
A83: Maio | B83: 130599.69 | C83: 150026.72 | D83: 39597.94 | E83: 57014.4
A84: Junho | B84: 97973.1 | C84: 208724.8 | D84: 77419.24 | E84: 259261.92
A85: Julho | B85: 309004.57 | C85: 130036.72 | D85: 74963.62 | E85: 191964.91
A86: Agosto | B86: 436765.8 | C86: 211762.02 | D86: 152485.66 | E86: 273158.85
A87: Setembro | B87: 355927.94 | C87: 534003.5 | D87: 171282.48 | E87: 63159.51
A88: Outubro | B88: 540038.64 | C88: 96571.01 | D88: 168433.06 | E88: 53077.38
A89: Novembro | B89: 248566.76 | C89: 33008.07 | D89: 155757.68 | E89: 15517.44
A90: Dezembro | B90: 0 | C90: 18714.12 | D90: 163379.08 | E90: 9580.01
A91: total | B91: 2215695.4 | C91: 2000846.7 | D91: 1528111.2 | E91: =SUM(E79:E90) -> 1910703.4

Sheet Fevereiro 
A1: Nota Fiscal | B1: Emissão | C1: Destinatário | D1: Descrição | E1: Valor Venda | F1: Mão de Obra | G1: Vencimento | H1: Data pagto | I1: OBS | J1: Em aberto Valor | L1: Soares | N1: Componarte
A2: 16787 | B2: 05.02.25 | C2: Soares | D2: Rafia Glow | F2: 1075.77 | G2: 05.03.25 | H2: 45722
F3: 1075 | G3: 12.03.25 | H3: 45728
F4: 1075 | G4: 19.03.25 | H4: 45735
A5: 16796 | B5: 05.02.25 | C5: Soares | D5: Croco | F5: 1033.36 | G5: 05.03.25 | H5: 45721
F6: 1031 | G6: 12.03.25 | H6: 45728
F7: 1031 | G7: 19.03.25 | H7: 45735
A8: 16826 | B8: 07.02.25 | C8: Soares | D8: Croco Metal | F8: 362.71 | G8: 07.03.25 | H8: 45723
A9: 16827 | B9: 07.02.25 | C9: Soares | D9: Croco Metal | F9: 184.61 | G9: 07.03.25 | H9: 45723
A10: 16870 | B10: 11.02.25 | C10: Soares | D10: Rafia | F10: 411.24 | G10: 11.03.24 | H10: 45727
F11: 409 | G11: 18.03.25 | H11: 45734
F12: 409 | G12: 25.03.25 | H12: 45741
A13: 16876 | B13: 11.02.25 | C13: Soares | D13: Rafia Glow | F13: 984.1 | G13: 11.03.24 | H13: 45727
F14: 983 | G14: 18.03.25 | H14: 45734
F15: 983 | G15: 25.03.25 | H15: 45741
A16: 16916 | B16: 13.02.25 | C16: Soares | D16: Croco | F16: 138 | G16: 13.03.25 | H16: 45729
A17: 16917 | B17: 13.02.25 | C17: Soares | D17: Crocodile | F17: 134.55 | G17: 13.03.25 | H17: 45729
A18: 16943 | B18: 14.02.25 | C18: Soares | D18: Rafia Glow/ Napa | F18: 583.43 | G18: 14.03.25 | H18: 45730
F19: 582 | G19: 21.03.25 | H19: 45735
F20: 582 | G20: 28.03.25 | H20: 45744
A21: 16969 | B21: 18.02.24 | C21: Soares | D21: Croco | F21: 410.38 | G21: 18.03.25 | H21: 45734
F22: 409 | G22: 25.03.25 | H22: 45741
A23: 17140 | B23: 28.02.25 | C23: Soares | D23: Rafia Napa New | F23: 542.68 | G23: 28.03.25 | H23: 45744
F24: 542 | G24: 04.04.25 | H24: 45751
F25: 542 | G25: 11.04.25 | H25: 45758
A27: Total Faturado Mão de Obra | E27: =SUM(E2:E26) -> 0 | F27: =SUM(F2:F26) -> 15513.83
A28: Total Faturado Venda
D29: =(F27+E28) -> 15513.83
A32: Mês | B32: Frete 2021 | C32: Frete 2022 | D32: Frete 2023 | E32: Frete 2024 | F32: Frete 2025
A33: Janeiro | B33: 19219.28 | C33: 109492.58 | D33: 126073.37 | E33: 270562.53 | F33: ='Janeiro '!F79 -> 49887.66
A34: Fevereiro | B34: 18377.75 | C34: 151228.71 | D34: 166235.96 | E34: 324984.97 | F34: =D29 -> 15513.83
A35: Março | B35: 25009.87 | C35: 119148.49 | D35: 119814.85 | E35: 256001.57
A36: Abril | B36: 34211.96 | C36: 238129.97 | D36: 112668.22 | E36: 136419.94
A37: Maio | B37: 130599.69 | C37: 150026.72 | D37: 39597.94 | E37: 57014.4
A38: Junho | B38: 97973.1 | C38: 208724.8 | D38: 77419.24 | E38: 259261.92
A39: Julho | B39: 309004.57 | C39: 130036.72 | D39: 74963.62 | E39: 191964.91
A40: Agosto | B40: 436765.8 | C40: 211762.02 | D40: 152485.66 | E40: 273158.85
A41: Setembro | B41: 355927.94 | C41: 534003.5 | D41: 171282.48 | E41: 63159.51
A42: Outubro | B42: 540038.64 | C42: 96571.01 | D42: 168433.06 | E42: 53077.38
A43: Novembro | B43: 248566.76 | C43: 33008.07 | D43: 155757.68 | E43: 15517.44
A44: Dezembro | B44: 0 | C44: 18714.12 | D44: 163379.08 | E44: 9580.01
A45: total | B45: 2215695.4 | C45: 2000846.7 | D45: 1528111.2 | E45: =SUM(E33:E44) -> 1910703.4

Sheet Março
A1: Nota Fiscal | B1: Emissão | C1: Destinatário | D1: Descrição | E1: Valor Venda | F1: Mão de Obra | G1: Vencimento | H1: Data pagto | I1: OBS | J1: Em aberto Valor | L1: Soares | N1: Componarte
A2: 17162 | B2: 03.02.25 | C2: Soares | D2: Rafia Glow | F2: 2359.99 | G2: 28.03.25 | H2: 45747
F3: 2358 | G3: 04.04.25 | H3: 45757
F4: 2358 | G4: 11.04.25 | H4: 45761
A5: 17174 | B5: 04.03.25 | C5: Soares | D5: Rafia Napa | F5: 361.31 | G5: 01.04.25 | H5: 45748
F6: 361 | G6: 08.04.25 | H6: 45757
F7: 361 | G7: 15.04.25 | H7: 45762
A8: 17212 | B8: 07.03.25 | C8: Soares | D8: Baby Croco | F8: 689.53 | G8: 04.04.25 | H8: 45751
F9: 688 | G9: 11.04.25 | H9: 45758
F10: 688 | G10: 18.04.25 | H10: 45764
F11: 0
F12: 0
A13: 17213 | B13: 07.03.25 | C13: Soares | D13: Baby Croco | F13: 730.69 | G13: 04.04.25 | H13: 45751
F14: 729 | G14: 11.04.25 | H14: 45758
F15: 729 | G15: 18.04.25 | H15: 45764
A16: 17283 | B16: 13.03.25 | C16: Soares | D16: Rafia Napa Natural | F16: 1003.38 | G16: 10.04.25 | H16: 45757
F17: 1002 | G17: 17.04.25 | H17: 45764
F18: 1002 | G18: 24.04.25 | H18: 45771
A19: 17290 | B19: 13.03.25 | C19: Sores | D19: Croco Branco | F19: 1071.97 | G19: 10.04.25 | H19: 45757
F20: 1070 | G20: 17.04.25 | H20: 45764
F21: 1070 | G21: 24.04.25 | H21: 45771
A22: 17312 | B22: 14.03.25 | C22: Soares | D22: Croco Metal | F22: 183.68 | G22: 11.04.25 | H22: 45758
A23: 17313 | B23: 14.03.25 | C23: Soares | D23: Croco Metal | F23: 406.95 | G23: 11.04.25 | H23: 45758
F24: 405 | G24: 18.04.25 | H24: 45764
A25: 17344 | B25: 19.03.25 | C25: Soares | D25: Rafia Napa | F25: 362.76 | G25: 16.04.25 | H25: 45762
F26: 362 | G26: 23.04.25 | H26: 45770
F27: 362 | G27: 30.04.25 | H27: 45777
A28: 17364 | B28: 20.03.25 | C28: Soares | D28: Croco | F28: 363.98 | G28: 17.04.25 | H28: 45764
A29: 17365 | B29: 20.03.25 | C29: Soares | D29: Croco | F29: 265.65 | G29: 17.04.25 | H29: 45764
A30: 17366 | B30: 20.03.25 | C30: Soares | D30: Baby Croco | F30: 369.73 | G30: 17.04.25 | H30: 45764
F31: 368 | G31: 24.04.25 | H31: 45771
F32: 368 | G32: 01.05.25 | H32: 45777
A33: 17401 | B33: 24.03.25 | C33: Soares | D33: Iguana Preto | F33: 401.13 | G33: 21.04.25 | H33: 45769
F34: 401 | G34: 28.04.25 | H34: 45777
A35: 17418 | B35: 25.03.25 | C35: Soares | D35: Iguana Rocha | F35: 101.78 | G35: 22.04.25 | H35: 45769
A36: 17423 | B36: 26.03.25 | C36: Soares | D36: Croco/Rafia | F36: 1585.88 | G36: 23.04.25 | H36: 45770
F37: 1585 | G37: 30.04.25 | H37: 45777
F38: 1585 | G38: 07.05.25 | H38: 45783
A39: 17421 | B39: 26.03.25 | C39: Soares | D39: Reptil | F39: 136.28 | G39: 23.04.25 | H39: 45770
A40: 17453 | B40: 27.03.25 | C40: Soares | D40: Rafia/Croco | F40: 1171.86 | G40: 24.04.25 | H40: 45771
F41: 1171 | G41: 01.05.25 | H41: 45777
F42: 1171 | G42: 08.05.25 | H42: 45786
A43: 17456 | B43: 28.03.25 | C43: Soares | F43: 112.13 | G43: 25.04.25 | H43: 45772
A44: 17464 | B44: 28.03.25 | C44: Soares | F44: 351.54 | G44: 25.04.25 | H44: 45772
A45: 17466 | B45: 28.03.25 | C45: Soares | F45: 186 | G45: 25.04.25 | H45: 45772
J46: =SUM(J2:J45) -> 0
A47: Total Faturado Mão de Obra | E47: =SUM(E2:E46) -> 0 | F47: =SUM(F2:F46) -> 32410.22
A48: Total Faturado Venda
D49: =(F47+E48) -> 32410.22
A52: Mês | B52: Frete 2021 | C52: Frete 2022 | D52: Frete 2023 | E52: Frete 2024 | F52: Frete 2025
A53: Janeiro | B53: 19219.28 | C53: 109492.58 | D53: 126073.37 | E53: 270562.53 | F53: ='Janeiro '!F79 -> 49887.66
A54: Fevereiro | B54: 18377.75 | C54: 151228.71 | D54: 166235.96 | E54: 324984.97 | F54: 15513.83
A55: Março | B55: 25009.87 | C55: 119148.49 | D55: 119814.85 | E55: 256001.57 | F55: =SUM(F47) -> 32410.22
A56: Abril | B56: 34211.96 | C56: 238129.97 | D56: 112668.22 | E56: 136419.94
A57: Maio | B57: 130599.69 | C57: 150026.72 | D57: 39597.94 | E57: 57014.4
A58: Junho | B58: 97973.1 | C58: 208724.8 | D58: 77419.24 | E58: 259261.92
A59: Julho | B59: 309004.57 | C59: 130036.72 | D59: 74963.62 | E59: 191964.91
A60: Agosto | B60: 436765.8 | C60: 211762.02 | D60: 152485.66 | E60: 273158.85
A61: Setembro | B61: 355927.94 | C61: 534003.5 | D61: 171282.48 | E61: 63159.51
A62: Outubro | B62: 540038.64 | C62: 96571.01 | D62: 168433.06 | E62: 53077.38
A63: Novembro | B63: 248566.76 | C63: 33008.07 | D63: 155757.68 | E63: 15517.44
A64: Dezembro | B64: 0 | C64: 18714.12 | D64: 163379.08 | E64: 9580.01
A65: total | B65: 2215695.4 | C65: 2000846.7 | D65: 1528111.2 | E65: =SUM(E53:E64) -> 1910703.4

Sheet Abril
A1: Nota Fiscal | B1: Emissão | C1: Destinatário | D1: Descrição | E1: Valor Venda | F1: Mão de Obra | G1: Vencimento | H1: Data pagto | I1: OBS | J1: Em aberto Valor
A2: 17575 | B2: 08.04.25 | C2: Soares | D2: Baby Croco | F2: 485.1 | G2: 06.05.25 | H2: 45783
F3: 483 | G3: 13.05.25 | H3: 45791
F4: 483 | G4: 20.05.25 | H4: 45797
A5: 17589 | B5: 08.04.25 | C5: Soares | D5: Croco metal/Rafia | F5: 1245.87 | G5: 06.05.25 | H5: 45783
F6: 1244 | G6: 13.05.25 | H6: 45791
F7: 1244 | G7: 20.05.25 | H7: 45797
A8: 17590 | B8: 08.04.25 | C8: Soares | D8: Rafia Napa | F8: 1185.23 | G8: 06.05.25 | H8: 45783
F9: 1185 | G9: 13.05.25 | H9: 45791
F10: 1185 | G10: 20.05.25 | H10: 45797
A11: 17591 | B11: 08.04.25 | C11: Soares | D11: Croco | F11: 368.28 | G11: 06.05.25 | H11: 45783
F12: 367 | G12: 13.05.25 | H12: 45791
F13: 367 | G13: 20.05.25 | H13: 45797
A14: 17620 | B14: 11.04.25 | C14: Soares | D14: Rafia Napa/Glow | F14: 1082.74 | G14: 09.05.25 | H14: 45786
F15: 1081 | G15: 16.05.25 | H15: 45791
F16: 1081 | G16: 23.05.25 | H16: 45798
A17: 17621 | B17: 11.04.25 | C17: Soares | D17: Croco | F17: 267.04 | G17: 09.05.25 | H17: 45786
A18: 17640 | B18: 14.04.25 | C18: Soares | D18: Croco | F18: 362.7 | G18: 12.05.25 | H18: 45791
A19: 17669 | B19: 15.04.25 | C19: Soares | D19: Reptil | F19: 274.28 | G19: 13.05.25 | H19: 45791
A20: 17750 | B20: 22.04.25 | C20: Soares | D20: Croco | F20: 1156.28 | G20: 20.05.25 | H20: 45797
F21: 1156 | G21: 27.05.25 | H21: 45804
F22: 1156 | G22: 03.06.25 | H22: 45811
A23: 17832 | B23: 29.04.25 | C23: Soares | D23: Croco | F23: 1886.01 | G23: 27.05.25 | H23: 45804
F24: 1886 | G24: 03.06.25 | H24: 45812
F25: 1886 | G25: 10.06.25 | H25: 45818
J26: =SUM(J2:J25) -> 0
A27: Total Faturado Mão de Obra | E27: =SUM(E2:E26) -> 0 | F27: =SUM(F2:F26) -> 23117.53
A28: Total Faturado Venda
D29: 0
A32: Mês | B32: Frete 2021 | C32: Frete 2022 | D32: Frete 2023 | E32: Frete 2024 | F32: Frete 2025
A33: Janeiro | B33: 19219.28 | C33: 109492.58 | D33: 126073.37 | E33: 270562.53 | F33: ='Janeiro '!F79 -> 49887.66
A34: Fevereiro | B34: 18377.75 | C34: 151228.71 | D34: 166235.96 | E34: 324984.97 | F34: 15513.83
A35: Março | B35: 25009.87 | C35: 119148.49 | D35: 119814.85 | E35: 256001.57 | F35: 32410.22
A36: Abril | B36: 34211.96 | C36: 238129.97 | D36: 112668.22 | E36: 136419.94 | F36: =SUM(F27) -> 23117.53
A37: Maio | B37: 130599.69 | C37: 150026.72 | D37: 39597.94 | E37: 57014.4
A38: Junho | B38: 97973.1 | C38: 208724.8 | D38: 77419.24 | E38: 259261.92
A39: Julho | B39: 309004.57 | C39: 130036.72 | D39: 74963.62 | E39: 191964.91
A40: Agosto | B40: 436765.8 | C40: 211762.02 | D40: 152485.66 | E40: 273158.85
A41: Setembro | B41: 355927.94 | C41: 534003.5 | D41: 171282.48 | E41: 63159.51
A42: Outubro | B42: 540038.64 | C42: 96571.01 | D42: 168433.06 | E42: 53077.38
A43: Novembro | B43: 248566.76 | C43: 33008.07 | D43: 155757.68 | E43: 15517.44
A44: Dezembro | B44: 0 | C44: 18714.12 | D44: 163379.08 | E44: 9580.01
A45: total | B45: 2215695.4 | C45: 2000846.7 | D45: 1528111.2 | E45: =SUM(E33:E44) -> 1910703.4

Sheet Maio 2025
A1: Nota Fiscal | B1: Emissão | C1: Destinatário | D1: Descrição | E1: Valor Venda | F1: Mão de Obra | G1: Vencimento | H1: Data pagto | I1: OBS | J1: Em aberto Valor
A2: 17866 | B2: 05.05.2025 | C2: Soares | F2: 774.41 | G2: 02.06.2025 | H2: 45810 | J2: 0
F3: 772 | G3: 09.06.2025 | H3: 45817 | J3: 0
F4: 772 | G4: 16.06.2025 | H4: 45824 | J4: 0
A5: 17876 | B5: 05.05.25 | C5: Soares | F5: 339.83 | G5: 02.06.2025 | H5: 45810 | J5: 0
F6: 339.82 | G6: 09.06.2025 | H6: 45817 | J6: 0
A7: 17878 | B7: 05.05.25 | C7: Soares | F7: 725.78 | G7: 02.06.2025 | H7: 45810 | J7: 0
F8: 723 | G8: 09.06.2025 | H8: 45817 | J8: 0
F9: 723 | G9: 16.06.2025 | H9: 45824 | J9: 0
A10: 17894 | B10: 06.05.25 | C10: Soares | F10: 342.83 | G10: 03.06.2025 | H10: 45811 | J10: 0
F11: 342 | G11: 10.06.2025 | H11: 45818 | J11: 0
A12: 17893 | B12: 06.05.25 | C12: Soares | F12: 369.68 | G12: 03.06.2025 | H12: 45811 | J12: 0
A13: 17892 | B13: 06.05.25 | C13: Soares | F13: 260.48 | G13: 03.06.2025 | H13: 45810 | J13: 0
A14: 17897 | B14: 06.05.25 | C14: Soares | F14: 426.76 | G14: 03.06.2025 | H14: 45811 | J14: 0
F15: 426 | G15: 10.06.2025 | H15: 45818 | J15: 0
F16: 426 | G16: 17.06.2025 | H16: 45824 | J16: 0
A17: 17921 | B17: 07.05.25 | C17: Soares | F17: 362.75 | G17: 04.06.2025 | H17: 45812 | J17: 0
F18: 362 | G18: 11.06.2025 | H18: 45818 | J18: 0
F19: 362 | G19: 18.06.2025 | H19: 45824 | J19: 0
A20: 18124 | B20: 26.05.25 | C20: Soares | F20: 725.23 | G20: 23.06.2025 | H20: 45831 | J20: 0
F21: 725 | G21: 30.06.2025 | H21: 45838 | J21: 0
F22: 725 | G22: 07.07.2025 | H22: 45845 | J22: 0
A23: 18136 | B23: 27.05.25 | C23: Soares | F23: 405.3 | G23: 24.06.2025 | H23: 45831 | J23: 0
F24: 404 | G24: 01.07.2025 | H24: 45838 | J24: 0
A25: 18193 | B25: 30.05.25 | C25: Soares | F25: 342.83 | G25: 27.06.25 | H25: 45831 | J25: 0
F26: 342 | G26: 04.07.25 | H26: 45838 | J26: 0
F27: 0 | J27: 0
J28: =SUM(J2:J27) -> 0
A29: Total Faturado Mão de Obra | E29: =SUM(E2:E28) -> 0 | F29: =SUM(F2:F27) -> 12519.7
A30: Total Faturado Venda
D31: 0
A34: Mês | B34: Frete 2021 | C34: Frete 2022 | D34: Frete 2023 | E34: Frete 2024 | F34: Frete 2025
A35: Janeiro | B35: 19219.28 | C35: 109492.58 | D35: 126073.37 | E35: 270562.53 | F35: ='Janeiro '!F79 -> 49887.66
A36: Fevereiro | B36: 18377.75 | C36: 151228.71 | D36: 166235.96 | E36: 324984.97 | F36: 15513.83
A37: Março | B37: 25009.87 | C37: 119148.49 | D37: 119814.85 | E37: 256001.57 | F37: 32410.22
A38: Abril | B38: 34211.96 | C38: 238129.97 | D38: 112668.22 | E38: 136419.94 | F38: 23117.53
A39: Maio | B39: 130599.69 | C39: 150026.72 | D39: 39597.94 | E39: 57014.4 | F39: =SUM(F29) -> 12519.7
A40: Junho | B40: 97973.1 | C40: 208724.8 | D40: 77419.24 | E40: 259261.92
A41: Julho | B41: 309004.57 | C41: 130036.72 | D41: 74963.62 | E41: 191964.91
A42: Agosto | B42: 436765.8 | C42: 211762.02 | D42: 152485.66 | E42: 273158.85
A43: Setembro | B43: 355927.94 | C43: 534003.5 | D43: 171282.48 | E43: 63159.51
A44: Outubro | B44: 540038.64 | C44: 96571.01 | D44: 168433.06 | E44: 53077.38
A45: Novembro | B45: 248566.76 | C45: 33008.07 | D45: 155757.68 | E45: 15517.44
A46: Dezembro | B46: 0 | C46: 18714.12 | D46: 163379.08 | E46: 9580.01
A47: total | B47: 2215695.4 | C47: 2000846.7 | D47: 1528111.2 | E47: =SUM(E35:E46) -> 1910703.4

Sheet Junho 2025
A1: Nota Fiscal | B1: Emissão | C1: Destinatário | D1: Descrição | E1: Valor Venda | F1: Mão de Obra | G1: Vencimento | H1: Data pagto | I1: OBS | J1: Em aberto Valor
A2: 18197 | B2: 02.06.2025 | C2: Soares | F2: 455.03 | G2: 30.06.2025 | H2: 45838 | J2: 0
F3: 453 | G3: 07.07.2025 | H3: 45845 | J3: 0
F4: 453 | G4: 14.07.2025 | H4: 45853 | J4: 0
A5: 18205 | B5: 02.06.2025 | C5: Soares | F5: 272.55 | G5: 30.06.2025 | H5: 45838 | J5: 0
A6: 18219 | B6: 03.06.2025 | C6: Soares | F6: 315.31 | G6: 01.07.2025 | H6: 45838 | J6: 0
F7: 315 | G7: 08.07.2025 | H7: 45845 | J7: 0
F8: 315 | G8: 15.07.2025 | H8: 45853 | J8: 0
A9: 18240 | B9: 04.06.2025 | C9: Soares | F9: 1442.24 | G9: 02.07.2025 | H9: 45838 | J9: 0
F10: 1442 | G10: 09.07.2025 | H10: 45847 | J10: 0
F11: 1442 | G11: 16.07.2025 | H11: 45854 | J11: 0
A12: 18289 | B12: 05.06.2025 | C12: Soares | F12: 671.08 | G12: 03.07.2025 | H12: 45838 | J12: 0
F13: 671 | G13: 10.07.2025 | H13: 45847 | J13: 0
F14: 671 | G14: 17.07.2025 | H14: 45855 | J14: 0
A15: 18340 | B15: 10.06.2025 | C15: Soares | F15: 453.85 | G15: 08.07.2025 | H15: 45845 | J15: 0
F16: 451 | G16: 15.07.2025 | H16: 45853 | J16: 0
F17: 451 | G17: 22.07.2025 | H17: 45860 | J17: 0
A18: 18341 | B18: 10.06.2025 | C18: Soares | F18: 131.1 | G18: 08.07.2025 | H18: 45845 | J18: 0
A19: 18342 | B19: 10.06.2025 | C19: Soares | F19: 263.93 | G19: 08.07.2025 | H19: 45845 | J19: 0
A20: 18343 | B20: 10.06.2025 | C20: Soares | F20: 1158.86 | G20: 08.07.2025 | H20: 45846 | J20: 0
F21: 1158 | G21: 15.07.2025 | H21: 45853 | J21: 0
F22: 1158 | G22: 22.07.2025 | H22: 45860 | J22: 0
A23: 18348 | B23: 10.06.2025 | C23: Soares | F23: 538.6 | G23: 08.07.2025 | H23: 45845 | J23: 0
F24: 538 | G24: 15.07.2025 | H24: 45853 | J24: 0
F25: 538 | G25: 22.07.2025 | H25: 45860 | J25: 0
A26: 18349 | B26: 10.06.2025 | C26: Soares | F26: 683.1 | G26: 08.07.2025 | H26: 45846 | J26: 0
A27: 18354 | B27: 11.06.2025 | C27: Soares | F27: 1134.27 | G27: 09.07.2025 | H27: 45847 | J27: 0
F28: 1132 | G28: 16.07.2025 | H28: 45854 | J28: 0
F29: 1132 | G29: 23.07.2025 | H29: 45861 | J29: 0
A30: 18356 | B30: 11.06.2025 | C30: Soares | F30: 400.2 | G30: 09.07.2025 | H30: 45847 | J30: 0
A31: 18357 | B31: 11.06.2025 | C31: Soares | F31: 403.65 | G31: 09.07.2025 | H31: 45847 | J31: 0
A32: 18358 | B32: 11.06.2025 | C32: Soares | F32: 134.55 | G32: 09.07.2025 | H32: 45847 | J32: 0
A33: 18371 | B33: 11.06.2025 | C33: Soares | F33: 414 | G33: 09.07.2025 | H33: 45847 | J33: 0
A34: 18475 | B34: 18.06.2025 | C34: Soares | F34: 323.45 | G34: 16.07.2025 | H34: 45854 | J34: 0
F35: 323 | G35: 23.07.2025 | H35: 45861 | J35: 0
F36: 323 | G36: 30.07.2025 | H36: 45868 | J36: 0
A37: 18489 | B37: 20.06.2025 | C37: Soares | F37: 1451.91 | G37: 18.07.2025 | H37: 45855 | J37: 0
F38: 1451 | G38: 25.07.2025 | H38: 45862 | J38: 0
F39: 1451 | G39: 01.08.2025 | H39: 45869 | J39: 0
A40: 18541 | B40: 25.06.2025 | C40: Soares | F40: 412.56 | G40: 23.07.025 | H40: 45861 | J40: 0
F41: 412 | G41: 30.07.2025 | H41: 45868 | J41: 0
A42: 18542 | B42: 25.06.2025 | C42: Soares | F42: 927.02 | G42: 23.07.2025 | H42: 45861 | J42: 0
F43: 927 | G43: 30.07.2025 | H43: 45868 | J43: 0
F44: 927 | G44: 06.08.2025 | H44: 45874 | J44: 0
A45: 18543 | B45: 25.06.2025 | C45: Soares | F45: 545.45 | G45: 23.07.2025 | H45: 45861 | J45: 0
A46: 18557 | B46: 26.06.2025 | C46: Soares | F46: 591.32 | G46: 24.07.2025 | H46: 45862 | J46: 0
F47: 591 | G47: 31.07.2025 | H47: 45869 | J47: 0
F48: 591 | G48: 07.08.2025 | H48: 45874 | J48: 0
A49: 18579 | B49: 27.06.2025 | C49: Soares | F49: 546.83 | G49: 25.07.2025 | H49: 45862 | J49: 0
A50: Total Faturado Mão de Obra | E50: =SUM(E2:E48) -> 0 | F50: =SUM(F2:F49) -> 32986.86
A51: Total Faturado Venda
D52: 0
A55: Mês | B55: Frete 2021 | C55: Frete 2022 | D55: Frete 2023 | E55: Frete 2024 | F55: Frete 2025
A56: Janeiro | B56: 19219.28 | C56: 109492.58 | D56: 126073.37 | E56: 270562.53 | F56: ='Janeiro '!F79 -> 49887.66
A57: Fevereiro | B57: 18377.75 | C57: 151228.71 | D57: 166235.96 | E57: 324984.97 | F57: 15513.83
A58: Março | B58: 25009.87 | C58: 119148.49 | D58: 119814.85 | E58: 256001.57 | F58: 32410.22
A59: Abril | B59: 34211.96 | C59: 238129.97 | D59: 112668.22 | E59: 136419.94 | F59: 23117.53
A60: Maio | B60: 130599.69 | C60: 150026.72 | D60: 39597.94 | E60: 57014.4 | F60: 11710.4
A61: Junho | B61: 97973.1 | C61: 208724.8 | D61: 77419.24 | E61: 259261.92 | F61: =F50 -> 32986.86
A62: Julho | B62: 309004.57 | C62: 130036.72 | D62: 74963.62 | E62: 191964.91
A63: Agosto | B63: 436765.8 | C63: 211762.02 | D63: 152485.66 | E63: 273158.85
A64: Setembro | B64: 355927.94 | C64: 534003.5 | D64: 171282.48 | E64: 63159.51
A65: Outubro | B65: 540038.64 | C65: 96571.01 | D65: 168433.06 | E65: 53077.38
A66: Novembro | B66: 248566.76 | C66: 33008.07 | D66: 155757.68 | E66: 15517.44
A67: Dezembro | B67: 0 | C67: 18714.12 | D67: 163379.08 | E67: 9580.01
A68: total | B68: 2215695.4 | C68: 2000846.7 | D68: 1528111.2 | E68: =SUM(E56:E67) -> 1910703.4

Sheet Julho 2025
A1: Nota Fiscal | B1: Emissão | C1: Destinatário | D1: Descrição | E1: Valor Venda | F1: Mão de Obra | G1: Vencimento | H1: Data pagto | I1: OBS | J1: Em aberto Valor
A2: 18656 | B2: 03.07.2025 | C2: Soares | F2: 591.85 | G2: 31.07.2025 | H2: 45869 | J2: 0
F3: 589 | G3: 07.08.2025 | H3: 45874 | J3: 0
F4: 589 | G4: 14.08.2025 | H4: 45880 | J4: 0
A5: 18666 | B5: 07.07.2025 | C5: Soares | F5: 429.4 | G5: 04.08.2025 | H5: 45874 | J5: 0
F6: 427 | G6: 11.08.2025 | H6: 45880 | J6: 0
F7: 427 | G7: 18.08.2025 | H7: 45888 | J7: 0
A8: 18720 | B8: 09.07.2025 | C8: Soares | F8: 396.75 | G8: 06.08.2025 | H8: 45874 | J8: 0
A9: 18765 | B9: 11.07.2025 | C9: Soares | F9: 127.65 | G9: 08.08.2025 | H9: 45874 | J9: 0
A10: 18838 | B10: 17.07.2025 | C10: Soares | F10: 343.55 | G10: 14.08.2025 | H10: 45901 | J10: 0
F11: 343 | G11: 21.08.2025 | H11: 45908 | J11: 0
A12: 18944 | B12: 24.07.2025 | C12: Soares | F12: 411.1 | G12: 21.08.2025 | H12: 45888 | J12: 0
F13: 410 | G13: 28.08.2025 | H13: 45898 | J13: 0
A14: 18969 | B14: 25.07.2025 | C14: Soares | F14: 408.83 | G14: 23.09.2025 | H14: 45922 | J14: 0
A15: 19052 | B15: 31.07.2025 | C15: Soares | F15: 864.68 | G15: 28.08.2025 | H15: 45898 | J15: 0
F16: 864 | G16: 04.09.2025 | H16: 45901 | J16: 0
F17: 864 | G17: 11.09.2025 | H17: 45908 | J17: 0
F18: 0 | J18: 0
F19: 0 | J19: 0
A20: Total Faturado Mão de Obra | E20: =SUM(E2:E18) -> 0 | F20: =SUM(F2:F19) -> 8086.81
A21: Total Faturado Venda
D22: 0
A25: Mês | B25: Frete 2021 | C25: Frete 2022 | D25: Frete 2023 | E25: Frete 2024 | F25: Frete 2025
A26: Janeiro | B26: 19219.28 | C26: 109492.58 | D26: 126073.37 | E26: 270562.53 | F26: ='Janeiro '!F79 -> 49887.66
A27: Fevereiro | B27: 18377.75 | C27: 151228.71 | D27: 166235.96 | E27: 324984.97 | F27: 15513.83
A28: Março | B28: 25009.87 | C28: 119148.49 | D28: 119814.85 | E28: 256001.57 | F28: 32410.22
A29: Abril | B29: 34211.96 | C29: 238129.97 | D29: 112668.22 | E29: 136419.94 | F29: 23117.53
A30: Maio | B30: 130599.69 | C30: 150026.72 | D30: 39597.94 | E30: 57014.4 | F30: 11710.4
A31: Junho | B31: 97973.1 | C31: 208724.8 | D31: 77419.24 | E31: 259261.92 | F31: 32986.86
A32: Julho | B32: 309004.57 | C32: 130036.72 | D32: 74963.62 | E32: 191964.91 | F32: =F20 -> 8086.81
A33: Agosto | B33: 436765.8 | C33: 211762.02 | D33: 152485.66 | E33: 273158.85
A34: Setembro | B34: 355927.94 | C34: 534003.5 | D34: 171282.48 | E34: 63159.51
A35: Outubro | B35: 540038.64 | C35: 96571.01 | D35: 168433.06 | E35: 53077.38
A36: Novembro | B36: 248566.76 | C36: 33008.07 | D36: 155757.68 | E36: 15517.44
A37: Dezembro | B37: 0 | C37: 18714.12 | D37: 163379.08 | E37: 9580.01
A38: total | B38: 2215695.4 | C38: 2000846.7 | D38: 1528111.2 | E38: =SUM(E26:E37) -> 1910703.4

Sheet Agosto 2025
B2: FRETES
B4: MÊS | D4: 2021 | F4: 2022 | H4: 2023 | J4: 2024 | L4: 2025
B5: JANEIRO | D5: 19219.28 | F5: 109492.58 | H5: 126073.37 | J5: 270562.53 | L5: 49887.66
B6: FEVEREIRO | D6: 18377.75 | F6: 151228.71 | H6: 166235.96 | J6: 324984.97 | L6: 15513.83
B7: MARÇO | D7: 25009.87 | F7: 119148.49 | H7: 119814.85 | J7: 256001.57 | L7: 32410.22
B8: ABRIL | D8: 34211.96 | F8: 238129.97 | H8: 112668.22 | J8: 136419.94 | L8: 23117.53
B9: MAIO | D9: 130599.69 | F9: 150026.72 | H9: 39597.94 | J9: 57014.4 | L9: 11710.4
B10: JUNHO | D10: 97973.1 | F10: 208724.8 | H10: 77419.24 | J10: 259261.92 | L10: 32986.86
B11: JULHO | D11: 309004.57 | F11: 130036.72 | H11: 74963.62 | J11: 191964.91 | L11: 8086.81
B12: AGOSTO | D12: 436765.8 | F12: 211762.02 | H12: 152485.66 | J12: 273158.85 | L12: =D45 -> 23203.36
B13: SETEMBRO | D13: 355927.94 | F13: 534003.5 | H13: 171282.48 | J13: 63159.51
B14: OUTUBRO | D14: 540038.64 | F14: 96571.01 | H14: 168433.06 | J14: 53077.38
B15: NOVEMBRO | D15: 248566.76 | F15: 33008.07 | H15: 155757.68 | J15: 15517.44
B16: DEZEMBRO | D16: 0 | F16: 18714.12 | H16: 163379.08 | J16: 9580.01
B17: TOTAL | D17: =SUM(D5:D16) -> 2215695.4 | F17: =SUM(F5:F16) -> 2000846.7 | H17: =SUM(H5:H16) -> 1528111.2 | J17: =SUM(J5:J16) -> 1910703.4 | L17: =SUM(L5:L16) -> 196916.67
B19: NOTA FISCAL | C19: PEDIDO | D19: DATA DE EMISSÃO | E19: DESTINATÁRIO | F19: REPRESENTANTE | G19: VENDA | H19: MÃO DE OBRA | I19: VENCIMENTO | J19: DATA DE PAGAMENTO | K19: OBS: | L19: VALOR EM ABERTO | M19: .
B20: 19183 | C20: 1734 | D20: 45880 | E20: SOARES | F20: Marcelo | G20: 0 | H20: 364.21 | I20: 45908 | J20: 45908
E21: SOARES | F21: Marcelo | G21: 0 | H21: 363 | I21: 45915 | J21: 45915
E22: SOARES | F22: Marcelo | G22: 0 | H22: 363 | I22: 45922 | J22: 45922
B23: 19226 | C23: 1734 | D23: 45883 | E23: SOARES | F23: Marcelo | G23: 0 | H23: 1248.98 | I23: 45911 | J23: 45908
E24: SOARES | F24: Marcelo | G24: 0 | H24: 1248 | I24: 45918 | J24: 45915
E25: SOARES | F25: Marcelo | G25: 0 | H25: 1248 | I25: 45925 | J25: 45926
B26: 19272 | C26: 1796 | D26: 45887 | E26: SOARES | F26: Marcelo | G26: 0 | H26: 633.51 | I26: 45915 | J26: 45915
E27: SOARES | F27: Marcelo | G27: 0 | H27: 632 | I27: 45922 | J27: 45922
E28: SOARES | F28: Marcelo | G28: 0 | H28: 632 | I28: 45929 | J28: 45929
B29: 19289 | C29: 1819 | D29: 45888 | E29: LC COMPONENTES | F29: Marcelo | G29: 0 | H29: 3841.53 | J29: 45923
E30: LC COMPONENTES | F30: Marcelo | G30: 0 | H30: 0
E31: LC COMPONENTES | F31: Marcelo | G31: 0 | H31: 0
B32: 19331 | C32: 1847 | D32: 45891 | E32: SOARES | F32: Marcelo | G32: 0 | H32: 1665.88 | I32: 45919 | J32: 45915
E33: SOARES | F33: Marcelo | G33: 0 | H33: 1664 | I33: 45926 | J33: 45926
E34: SOARES | F34: Marcelo | G34: 0 | H34: 1664 | I34: 45933 | J34: 45933
B35: 19353 | C35: 1849 | D35: 45894 | E35: SOARES | F35: Marcelo | G35: 0 | H35: 578.93 | I35: 45922 | J35: 45951
E36: SOARES | F36: Marcelo | G36: 0 | H36: 0
E37: SOARES | F37: Marcelo | G37: 0 | H37: 0
B38: 19441 | C38: 1934 | D38: 45897 | E38: GRIFFE SHOES | F38: Vânia | G38: 1496.1 | H38: 0 | I38: 45897 | J38: 45897
B39: 19463 | C39: 1936 | D39: 45898 | E39: GRIFFE SHOES | F39: Vânia | G39: 1227 | H39: 0 | I39: 45898 | J39: 45898
B40: 19462 | C40: 1922 | D40: 45898 | E40: SOARES | F40: Marcelo | G40: 0 | H40: 1445.22 | I40: 45926 | J40: 45926
E41: SOARES | F41: Marcelo | G41: 0 | H41: 1444 | I41: 45933 | J41: 45929
E42: SOARES | F42: Marcelo | G42: 0 | H42: 1444 | I42: 45940 | J42: 45939
B43: TOTAL VENDA | G43: =SUM(G20:G42) -> 2723.1
B44: TOTAL MÃO DE OBRA | H44: =SUM(H20:H43) -> 20480.26
B45: TOTAL | D45: =SUM(G43+H44) -> 23203.36

Sheet Setembro 2025
B2: FRETES
B4: MÊS | D4: 2021 | F4: 2022 | H4: 2023 | J4: 2024 | L4: 2025
B5: JANEIRO | D5: 19219.28 | F5: 109492.58 | H5: 126073.37 | J5: 270562.53 | L5: 49887.66
B6: FEVEREIRO | D6: 18377.75 | F6: 151228.71 | H6: 166235.96 | J6: 324984.97 | L6: 15513.83
B7: MARÇO | D7: 25009.87 | F7: 119148.49 | H7: 119814.85 | J7: 256001.57 | L7: 32410.22
B8: ABRIL | D8: 34211.96 | F8: 238129.97 | H8: 112668.22 | J8: 136419.94 | L8: 23117.53
B9: MAIO | D9: 130599.69 | F9: 150026.72 | H9: 39597.94 | J9: 57014.4 | L9: 11710.4
B10: JUNHO | D10: 97973.1 | F10: 208724.8 | H10: 77419.24 | J10: 259261.92 | L10: 32986.86
B11: JULHO | D11: 309004.57 | F11: 130036.72 | H11: 74963.62 | J11: 191964.91 | L11: 8086.81
B12: AGOSTO | D12: 436765.8 | F12: 211762.02 | H12: 152485.66 | J12: 273158.85 | L12: 22122.22
B13: SETEMBRO | D13: 355927.94 | F13: 534003.5 | H13: 171282.48 | J13: 63159.51 | L13: =D46 -> 36466.42
B14: OUTUBRO | D14: 540038.64 | F14: 96571.01 | H14: 168433.06 | J14: 53077.38 | L14: 0
B15: NOVEMBRO | D15: 248566.76 | F15: 33008.07 | H15: 155757.68 | J15: 15517.44 | L15: 0
B16: DEZEMBRO | D16: 0 | F16: 18714.12 | H16: 163379.08 | J16: 9580.01 | L16: 0
B17: TOTAL | D17: =SUM(D5:D16) -> 2215695.4 | F17: =SUM(F5:F16) -> 2000846.7 | H17: =SUM(H5:H16) -> 1528111.2 | J17: =SUM(J5:J16) -> 1910703.4 | L17: =SUM(L5:L16) -> 232301.95
B19: NOTA FISCAL | C19: PEDIDO | D19: DATA DE EMISSÃO | E19: DESTINATÁRIO | F19: REPREENTANTE | G19: VENDA | H19: MÃO DE OBRA | I19: VENCIMENTO | J19: DATA DE PAGAMENTO | K19: OBS: | L19: VALOR EM ABERTO | M19: .
B20: 19488 | C20: 1922 | D20: 45902 | E20: SOARES | F20: MARCELO | G20: 0 | H20: 365.03 | I20: 45930 | J20: 45929
B21: 19547 | C21: 1966/2000 | D21: 45905 | E21: SOARES | F21: MARCELO | G21: 0 | H21: 2571.04 | I21: 45933 | J21: 45933
E22: SOARES | F22: MARCELO | G22: 0 | H22: 2569 | I22: 45940 | J22: 45939
E23: SOARES | F23: MARCELO | G23: 0 | H23: 2569 | I23: 45947 | J23: 45945
B24: 19589 | C24: 2016 | D24: 45910 | E24: SOARES | F24: MARCELO | G24: 0 | H24: 120.75 | I24: 45938 | J24: 45971
B25: 19590 | C25: 2000 | D25: 45910 | E25: SOARES | F25: MARCELO | G25: 0 | H25: 348.75 | I25: 45938 | J25: 45939
E26: SOARES | F26: MARCELO | G26: 0 | H26: 347 | I26: 45945 | J26: 45945
E27: SOARES | F27: MARCELO | G27: 0 | H27: 347 | I27: 45952 | J27: 45951
B28: 19643 | C28: 2066 | D28: 45915 | E28: LC COMPONENTES | F28: MARCELO | G28: 0 | H28: 1400.67 | I28: 45950 | J28: 45950
B29: 19650 | C29: 2092 | D29: 45915 | E29: SOARES | F29: MARCELO | G29: 0 | H29: 407.1 | I29: 45943 | J29: 45945
B30: 19703 | C30: 2092 | D30: 45917 | E30: SOARES | F30: MARCELO | G30: 0 | H30: 917.93 | I30: 45945 | J30: 45945
E31: SOARES | F31: MARCELO | G31: 0 | H31: 915 | I31: 45952 | J31: 45951
E32: SOARES | F32: MARCELO | G32: 0 | H32: 915 | I32: 45959 | J32: 45957
B33: 19747 | C33: 2126 | D33: 45919 | E33: SOARES | F33: MARCELO | G33: 0 | H33: 408.75 | I33: 45947 | J33: 45945
E34: SOARES | F34: MARCELO | G34: 0 | H34: 408 | I34: 45954 | J34: 45951
E35: SOARES | F35: MARCELO | G35: 0 | H35: 408 | I35: 45961 | J35: 45957
B36: 19769 | C36: 2152 | D36: 45922 | E36: LC COMPONENTES | F36: MARCELO | G36: 0 | H36: 1357.29 | I36: 45957 | J36: 45957
B37: 19770 | C37: 2183 | D37: 45922 | E37: SOARES | F37: MARCELO | G37: 0 | H37: 1484.52 | I37: 45950 | J37: 45951
E38: SOARES | F38: MARCELO | G38: 0 | H38: 1483 | I38: 45957 | J38: 45957
E39: SOARES | F39: MARCELO | G39: 0 | H39: 1483 | I39: 45964 | J39: 45965
B40: 19908 | C40: 2280 | D40: 45930 | E40: SOARES | F40: MARCELO | G40: 0 | H40: 913.59 | I40: 45958 | J40: 45957
E41: SOARES | F41: MARCELO | G41: 0 | H41: 912 | I41: 45965 | J41: 45966
E42: SOARES | F42: MARCELO | G42: 0 | H42: 912 | I42: 45972 | J42: 45973
B43: 19705/06 | D43: 45918 | E43: NH TEX | F43: MAT. SEGUNDA | G43: 12903 | H43: 0
B44: TOTAL VENDA | G44: =SUM(G21:G43) -> 12903
B45: TOTAL MÃO DE OBRA | H45: =SUM(H20:H44) -> 23563.42
B46: TOTAL | D46: =SUM(G44+H45) -> 36466.42

Sheet Outubro 2025 
B2: FRETES
B4: MÊS | D4: 2021 | F4: 2022 | H4: 2023 | J4: 2024 | L4: 2025
B5: JANEIRO | D5: 19219.28 | F5: 109492.58 | H5: 126073.37 | J5: 270562.53 | L5: 49887.66
B6: FEVEREIRO | D6: 18377.75 | F6: 151228.71 | H6: 166235.96 | J6: 324984.97 | L6: 15513.83
B7: MARÇO | D7: 25009.87 | F7: 119148.49 | H7: 119814.85 | J7: 256001.57 | L7: 32410.22
B8: ABRIL | D8: 34211.96 | F8: 238129.97 | H8: 112668.22 | J8: 136419.94 | L8: 23117.53
B9: MAIO | D9: 130599.69 | F9: 150026.72 | H9: 39597.94 | J9: 57014.4 | L9: 11710.4
B10: JUNHO | D10: 97973.1 | F10: 208724.8 | H10: 77419.24 | J10: 259261.92 | L10: 32986.86
B11: JULHO | D11: 309004.57 | F11: 130036.72 | H11: 74963.62 | J11: 191964.91 | L11: 8086.81
B12: AGOSTO | D12: 436765.8 | F12: 211762.02 | H12: 152485.66 | J12: 273158.85 | L12: 22122.22
B13: SETEMBRO | D13: 355927.94 | F13: 534003.5 | H13: 171282.48 | J13: 63159.51 | L13: 36466.42
B14: OUTUBRO | D14: 540038.64 | F14: 96571.01 | H14: 168433.06 | J14: 53077.38 | L14: =D67 -> 101839.17
B15: NOVEMBRO | D15: 248566.76 | F15: 33008.07 | H15: 155757.68 | J15: 15517.44 | L15: 0
B16: DEZEMBRO | D16: 0 | F16: 18714.12 | H16: 163379.08 | J16: 9580.01 | L16: 0
B17: TOTAL | D17: =SUM(D5:D16) -> 2215695.4 | F17: =SUM(F5:F16) -> 2000846.7 | H17: =SUM(H5:H16) -> 1528111.2 | J17: =SUM(J5:J16) -> 1910703.4 | L17: =SUM(L5:L16) -> 334141.12
B19: NOTA FISCAL | C19: PEDIDO | D19: DATA DE EMISSÃO | E19: DESTINATÁRIO | F19: REPRESENTANTE | G19: VENDA | H19: MÃO DE OBRA | I19: VENCIMENTO | J19: DATA DE PAGAMENTO | K19: OBS: | L19: VALOR EM ABERTO | M19: VALOR PAGO
B20: 19970 | C20: 2280 | D20: 45933 | E20: SOARES | F20: MARCELO | G20: 0 | H20: 400.89 | I20: 45961 | J20: 45957 | L20: =Tabela224[[#This Row],[VENDA]]+Tabela224[[#This Row],[MÃO DE OBRA]]-M20 -> 400.89
E21: SOARES | F21: MARCELO | G21: 0 | H21: 399 | I21: 45968 | J21: 45966 | L21: =Tabela224[[#This Row],[VENDA]]+Tabela224[[#This Row],[MÃO DE OBRA]]-M21 -> 399
E22: SOARES | F22: MARCELO | G22: 0 | H22: 399 | I22: 45975 | J22: 45973 | L22: =Tabela224[[#This Row],[VENDA]]+Tabela224[[#This Row],[MÃO DE OBRA]]-M22 -> 399
B23: 19997 | C23: 2404 | D23: 45935 | E23: RM | F23: MARCIANO | G23: 1554 | H23: 0 | I23: 45939 | J23: 45939 | L23: =Tabela224[[#This Row],[VENDA]]+Tabela224[[#This Row],[MÃO DE OBRA]]-M23 -> 1554
B24: 19999 | C24: 2349 | D24: 45936 | E24: SOARES | F24: MARCELO | G24: 0 | H24: 2241.37 | I24: 45964 | J24: 45965 | L24: =Tabela224[[#This Row],[VENDA]]+Tabela224[[#This Row],[MÃO DE OBRA]]-M24 -> 2241.37
E25: SOARES | F25: MARCELO | G25: 0 | H25: 2241 | I25: 45971 | J25: 45971 | L25: =Tabela224[[#This Row],[VENDA]]+Tabela224[[#This Row],[MÃO DE OBRA]]-M25 -> 2241
E26: SOARES | F26: MARCELO | G26: 0 | H26: 2241 | I26: 45978 | J26: 45978 | L26: =Tabela224[[#This Row],[VENDA]]+Tabela224[[#This Row],[MÃO DE OBRA]]-M26 -> -0.11 | M26: 2241.11
B27: 20001 | C27: 2349 | D27: 45936 | E27: SOARES | F27: MARCELO | G27: 0 | H27: 576.73 | I27: 45964 | J27: 45965 | L27: =Tabela224[[#This Row],[VENDA]]+Tabela224[[#This Row],[MÃO DE OBRA]]-M27 -> 576.73
E28: SOARES | F28: MARCELO | G28: 0 | H28: 576 | I28: 45971 | J28: 45971 | L28: =Tabela224[[#This Row],[VENDA]]+Tabela224[[#This Row],[MÃO DE OBRA]]-M28 -> 576
E29: SOARES | F29: MARCELO | G29: 0 | H29: 576 | I29: 45978 | J29: 45978 | L29: =Tabela224[[#This Row],[VENDA]]+Tabela224[[#This Row],[MÃO DE OBRA]]-M29 -> -0.24 | M29: 576.24
B30: 20019 | C30: 2349 | D30: 45937 | E30: SOARES | F30: MARCELO | G30: 0 | H30: 487.79 | I30: 45965 | J30: 45966 | L30: =Tabela224[[#This Row],[VENDA]]+Tabela224[[#This Row],[MÃO DE OBRA]]-M30 -> 487.79
E31: SOARES | F31: MARCELO | G31: 0 | H31: 485 | I31: 45972 | J31: 45973 | L31: =Tabela224[[#This Row],[VENDA]]+Tabela224[[#This Row],[MÃO DE OBRA]]-M31 -> 485
E32: SOARES | F32: MARCELO | G32: 0 | H32: 485 | I32: 45979 | J32: 45980 | L32: =Tabela224[[#This Row],[VENDA]]+Tabela224[[#This Row],[MÃO DE OBRA]]-M32 -> -0.92 | M32: 485.92
B33: 20103 | C33: 2412 | D33: 45940 | E33: SOARES | F33: MARCELO | G33: 0 | H33: 404.31 | I33: 45968 | J33: 45966 | L33: =Tabela224[[#This Row],[VENDA]]+Tabela224[[#This Row],[MÃO DE OBRA]]-M33 -> 404.31
E34: SOARES | F34: MARCELO | G34: 0 | H34: 403 | I34: 45975 | J34: 45973 | L34: =Tabela224[[#This Row],[VENDA]]+Tabela224[[#This Row],[MÃO DE OBRA]]-M34 -> 403
B35: 20104 | C35: 2435 | D35: 45940 | E35: SOARES | F35: MARCELO | G35: 0 | H35: 132.83 | I35: 45968 | J35: 45971 | L35: =Tabela224[[#This Row],[VENDA]]+Tabela224[[#This Row],[MÃO DE OBRA]]-M35 -> 132.83
B36: 20105 | C36: 2435 | D36: 45940 | E36: SOARES | F36: MARCELO | G36: 0 | H36: 270.83 | I36: 45968 | J36: 45971 | L36: =Tabela224[[#This Row],[VENDA]]+Tabela224[[#This Row],[MÃO DE OBRA]]-M36 -> 270.83
B37: 20122 | C37: 2428 | D37: 45943 | E37: SOARES | F37: MARCELO | G37: 0 | H37: 369.68 | I37: 45971 | J37: 45973 | L37: =Tabela224[[#This Row],[VENDA]]+Tabela224[[#This Row],[MÃO DE OBRA]]-M37 -> 369.68
B38: 378 | C38: 338 | D38: 45943 | E38: RM | F38: MARCIANO | G38: 518 | H38: 0 | I38: 45940 | J38: 45940 | L38: =Tabela224[[#This Row],[VENDA]]+Tabela224[[#This Row],[MÃO DE OBRA]]-M38 -> 518
B39: 20164 | C39: 2428 | D39: 45945 | E39: SOARES | F39: MARCELO | G39: 0 | H39: 679.23 | I39: 45973 | J39: 45973 | L39: =Tabela224[[#This Row],[VENDA]]+Tabela224[[#This Row],[MÃO DE OBRA]]-M39 -> 679.23
E40: SOARES | F40: MARCELO | G40: 0 | H40: 679 | I40: 45980 | J40: 45980 | L40: =Tabela224[[#This Row],[VENDA]]+Tabela224[[#This Row],[MÃO DE OBRA]]-M40 -> -0.07 | M40: 679.07
E41: SOARES | F41: MARCELO | G41: 0 | H41: 679 | I41: 45987 | J41: 45989 | L41: =Tabela224[[#This Row],[VENDA]]+Tabela224[[#This Row],[MÃO DE OBRA]]-M41 -> -0.08 | M41: 679.08
B42: 388 | C42: 349 | D42: 45946 | E42: VR | F42: CLEMILSON | G42: 1077.6 | H42: 0 | I42: 45945 | J42: 45945 | L42: =Tabela224[[#This Row],[VENDA]]+Tabela224[[#This Row],[MÃO DE OBRA]]-M42 -> 1077.6
B43: 20244 | C43: 2515 | D43: 45950 | E43: SOARES | F43: MARCELO | G43: 0 | H43: 908.07 | I43: 45978 | J43: 45978 | L43: =Tabela224[[#This Row],[VENDA]]+Tabela224[[#This Row],[MÃO DE OBRA]]-M43 -> 0.73 | M43: 907.34
E44: SOARES | F44: MARCELO | G44: 0 | H44: 907 | I44: 45985 | J44: 45989 | L44: =Tabela224[[#This Row],[VENDA]]+Tabela224[[#This Row],[MÃO DE OBRA]]-M44 -> -0.34 | M44: 907.34
E45: SOARES | F45: MARCELO | G45: 0 | H45: 907 | I45: 45992 | J45: 45996 | L45: =Tabela224[[#This Row],[VENDA]]+Tabela224[[#This Row],[MÃO DE OBRA]]-M45 -> -0.35 | M45: 907.35
B46: 20245 | C46: 2516 | D46: 45950 | E46: SOARES | F46: MARCELO | G46: 0 | H46: 591.31 | I46: 45978 | J46: 45978 | L46: =Tabela224[[#This Row],[VENDA]]+Tabela224[[#This Row],[MÃO DE OBRA]]-M46 -> 0.21 | M46: 591.1
E47: SOARES | F47: MARCELO | G47: 0 | H47: 591 | I47: 45985 | J47: 45989 | L47: =Tabela224[[#This Row],[VENDA]]+Tabela224[[#This Row],[MÃO DE OBRA]]-M47 -> -0.1 | M47: 591.1
E48: SOARES | F48: MARCELO | G48: 0 | H48: 591 | I48: 45992 | J48: 45996 | L48: =Tabela224[[#This Row],[VENDA]]+Tabela224[[#This Row],[MÃO DE OBRA]]-M48 -> -0.09 | M48: 591.09
B49: 20301 | C49: 2392 | D49: 45953 | E49: LC COMPONENTES | F49: MARCELO | G49: 0 | H49: 1336.68 | I49: 45988 | J49: 45994 | L49: =Tabela224[[#This Row],[VENDA]]+Tabela224[[#This Row],[MÃO DE OBRA]]-M49 -> 0 | M49: 1336.68
B50: 20332 | C50: 2619 | D50: 45952 | E50: MARIOTTA | F50: SILVANO | G50: 3900 | H50: 0 | I50: 45952 | J50: 45952 | L50: =Tabela224[[#This Row],[VENDA]]+Tabela224[[#This Row],[MÃO DE OBRA]]-M50 -> 3900
B51: 20347 | C51: 2585 | D51: 45954 | E51: SOARES | F51: MARCELO | G51: 0 | H51: 1324.27 | I51: 45982 | J51: 45980 | L51: =Tabela224[[#This Row],[VENDA]]+Tabela224[[#This Row],[MÃO DE OBRA]]-M51 -> 0.85 | M51: 1323.42
E52: SOARES | F52: MARCELO | G52: 0 | H52: 1323 | I52: 45989 | J52: 45989 | L52: =Tabela224[[#This Row],[VENDA]]+Tabela224[[#This Row],[MÃO DE OBRA]]-M52 -> -0.42 | M52: 1323.42
E53: SOARES | F53: MARCELO | G53: 0 | H53: 1323 | I53: 45996 | J53: 45996 | L53: =Tabela224[[#This Row],[VENDA]]+Tabela224[[#This Row],[MÃO DE OBRA]]-M53 -> -0.41 | M53: 1323.41
B54: 20389 | C54: 2642 | D54: 45958 | E54: SOARES | F54: MARCELO | G54: 0 | H54: 453.85 | I54: 45986 | J54: 45989 | L54: =Tabela224[[#This Row],[VENDA]]+Tabela224[[#This Row],[MÃO DE OBRA]]-M54 -> 1.9 | M54: 451.95
E55: SOARES | F55: MARCELO | G55: 0 | H55: 451 | I55: 45993 | J55: 45996 | L55: =Tabela224[[#This Row],[VENDA]]+Tabela224[[#This Row],[MÃO DE OBRA]]-M55 -> -0.95 | M55: 451.95
E56: SOARES | F56: MARCELO | G56: 0 | H56: 451 | I56: 46000 | J56: 46003 | L56: =Tabela224[[#This Row],[VENDA]]+Tabela224[[#This Row],[MÃO DE OBRA]]-M56 -> -0.95 | M56: 451.95
B57: 20394 | C57: 2656 | D57: 45954 | E57: GLAUCIA | F57: SILVANO | G57: 3600 | H57: 0 | I57: 45955 | J57: 45955 | L57: =Tabela224[[#This Row],[VENDA]]+Tabela224[[#This Row],[MÃO DE OBRA]]-M57 -> 3600
B58: 20401 | C58: 2667 | D58: 45957 | E58: NS DEVIDES | F58: SILVANO | G58: 4087.2 | H58: 0 | I58: 45958 | J58: 45958 | L58: =Tabela224[[#This Row],[VENDA]]+Tabela224[[#This Row],[MÃO DE OBRA]]-M58 -> 4087.2
B59: 20421 | C59: 2724 | D59: 45960 | E59: SOARES | F59: MARCELO | G59: 17233.333 | H59: 0 | I59: 45988 | J59: 45989 | L59: =Tabela224[[#This Row],[VENDA]]+Tabela224[[#This Row],[MÃO DE OBRA]]-M59 -> 0.0033333333 | M59: 17233.33
E60: SOARES | F60: MARCELO | G60: 17233.333 | H60: 0 | I60: 45995 | J60: 45996 | L60: =Tabela224[[#This Row],[VENDA]]+Tabela224[[#This Row],[MÃO DE OBRA]]-M60 -> 0.0033333333 | M60: 17233.33
E61: SOARES | F61: MARCELO | G61: 17233.333 | H61: 0 | I61: 46002 | J61: 46003 | L61: =Tabela224[[#This Row],[VENDA]]+Tabela224[[#This Row],[MÃO DE OBRA]]-M61 -> -0.0066666667 | M61: 17233.34
B62: 20451 | C62: 2699 | D62: 45961 | E62: SOARES | F62: MARCELO | G62: 0 | H62: 3173.53 | I62: 45989 | J62: 45989 | L62: =Tabela224[[#This Row],[VENDA]]+Tabela224[[#This Row],[MÃO DE OBRA]]-M62 -> 1.03 | M62: 3172.5
E63: SOARES | F63: MARCELO | G63: 0 | H63: 3172 | I63: 45996 | J63: 45996 | L63: =Tabela224[[#This Row],[VENDA]]+Tabela224[[#This Row],[MÃO DE OBRA]]-M63 -> -0.5 | M63: 3172.5
E64: SOARES | F64: MARCELO | G64: 0 | H64: 3172 | I64: 46003 | J64: 46003 | L64: =Tabela224[[#This Row],[VENDA]]+Tabela224[[#This Row],[MÃO DE OBRA]]-M64 -> -0.5 | M64: 3172.5
B65: TOTAL VENDA | G65: =SUM(G21:G64) -> 66436.8
B66: TOTAL MÃO DE OBRA | H66: =SUM(H20:H65) -> 35402.37
B67: TOTAL | D67: =SUM(G65+H66) -> 101839.17

Sheet Novembro 2025 
B2: FRETES
B4: MÊS | C4: SMART | H4: STK
C5: 2023 | D5: 2024 | E5: 2025 | F5: 2026 | G5: 2027 | H5: 2025 | I5: 2026 | J5: 2027 | K5: 2028 | L5: 2029 | M5: 2030
B6: JANEIRO | C6: 126073.37 | D6: 270562.53 | E6: 49887.66 | F6: 0 | G6: 0 | H6: 0 | I6: 0 | J6: 0 | K6: 0 | L6: 0 | M6: 0
B7: FEVEREIRO | C7: 166235.96 | D7: 324984.97 | E7: 15513.83 | F7: 0 | G7: 0 | H7: 0 | I7: 0 | J7: 0 | K7: 0 | L7: 0 | M7: 0
B8: MARÇO | C8: 119814.85 | D8: 256001.57 | E8: 32410.22 | F8: 0 | G8: 0 | H8: 0 | I8: 0 | J8: 0 | K8: 0 | L8: 0 | M8: 0
B9: ABRIL | C9: 112668.22 | D9: 136419.94 | E9: 23117.53 | F9: 0 | G9: 0 | H9: 0 | I9: 0 | J9: 0 | K9: 0 | L9: 0 | M9: 0
B10: MAIO | C10: 39597.94 | D10: 57014.4 | E10: 11710.4 | F10: 0 | G10: 0 | H10: 0 | I10: 0 | J10: 0 | K10: 0 | L10: 0 | M10: 0
B11: JUNHO | C11: 77419.24 | D11: 259261.92 | E11: 32986.86 | F11: 0 | G11: 0 | H11: 0 | I11: 0 | J11: 0 | K11: 0 | L11: 0 | M11: 0
B12: JULHO | C12: 74963.62 | D12: 191964.91 | E12: 8086.81 | F12: 0 | G12: 0 | H12: 0 | I12: 0 | J12: 0 | K12: 0 | L12: 0 | M12: 0
B13: AGOSTO | C13: 152485.66 | D13: 273158.85 | E13: 22122.22 | F13: 0 | G13: 0 | H13: 0 | I13: 0 | J13: 0 | K13: 0 | L13: 0 | M13: 0
B14: SETEMBRO | C14: 171282.48 | D14: 63159.51 | E14: 36466.42 | F14: 0 | G14: 0 | H14: 0 | I14: 0 | J14: 0 | K14: 0 | L14: 0 | M14: 0
B15: OUTUBRO | C15: 168433.06 | D15: 53077.38 | E15: 99828 | F15: 0 | G15: 0 | H15: 1595.6 | I15: 0 | J15: 0 | K15: 0 | L15: 0 | M15: 0
B16: NOVEMBRO | C16: 155757.68 | D16: 15517.44 | E16: 0 | F16: 0 | G16: 0 | H16: 0 | I16: 0 | J16: 0 | K16: 0 | L16: 0 | M16: 0
B17: DEZEMBRO | C17: 163379.08 | D17: 9580.01 | E17: 0 | F17: 0 | G17: 0 | H17: 0 | I17: 0 | J17: 0 | K17: 0 | L17: 0 | M17: 0
B18: TOTAL | C18: =SUM(C6:C17) -> 1528111.2 | D18: =SUM(D6:D17) -> 1910703.4 | E18: =SUM(E6:E17) -> 332129.95 | F18: =SUM(F6:F17) -> 0 | G18: 0 | H18: =SUM(H6:H17) -> 1595.6 | I18: 0 | J18: =SUM(J6:J17) -> 0 | K18: 0 | L18: =SUM(L6:L17) -> 0 | M18: 0
B19: TOTAL CONSOLIDADO 2025: | D19: =SUM(H18+E18) -> 333725.55
B20: EMPRESA | C20: NOTA FISCAL | D20: PEDIDO | E20: DATA DE EMISSÃO | F20: DESTINATÁRIO | G20: REPRESENTANTE | H20: VENDA | I20: MÃO DE OBRA | J20: VENCIMENTO | K20: DATA DE PAGAMENTO | L20: VALOR PAGO | M20: VALOR EM ABERTO
B21: STK | C21: 448 | D21: 408 | E21: 45971 | F21: MARIOTA | G21: SILVANO | H21: 3000 | I21: 0 | J21: 45971 | K21: 45967 | L21: 3000 | M21: =Tabela2246[[#This Row],[VENDA]]+Tabela2246[[#This Row],[MÃO DE OBRA]]-Tabela2246[[#This Row],[VALOR PAGO]] -> 0
B22: STK | C22: 458 | D22: 409 | E22: 45974 | F22: GLAUCIA | G22: SILVANO | H22: 4500 | I22: 0 | J22: 45974 | K22: 45973 | L22: 4500 | M22: =Tabela2246[[#This Row],[VENDA]]+Tabela2246[[#This Row],[MÃO DE OBRA]]-Tabela2246[[#This Row],[VALOR PAGO]] -> 0
B23: SMART | C23: 20590 | D23: 2783 | E23: 45971 | F23: SOARES | G23: MARCELO | H23: 0 | I23: 522.59 | J23: 45999 | K23: 46003 | L23: 521.52 | M23: =Tabela2246[[#This Row],[VENDA]]+Tabela2246[[#This Row],[MÃO DE OBRA]]-Tabela2246[[#This Row],[VALOR PAGO]] -> 1.07
F24: SOARES | G24: MARCELO | H24: 0 | I24: 521 | J24: 46006 | K24: 46010 | L24: 521.52 | M24: =Tabela2246[[#This Row],[VENDA]]+Tabela2246[[#This Row],[MÃO DE OBRA]]-Tabela2246[[#This Row],[VALOR PAGO]] -> -0.52
F25: SOARES | G25: MARCELO | H25: 0 | I25: 521 | J25: 46013 | K25: 46017 | L25: 521.52 | M25: =Tabela2246[[#This Row],[VENDA]]+Tabela2246[[#This Row],[MÃO DE OBRA]]-Tabela2246[[#This Row],[VALOR PAGO]] -> -0.52
B26: SMART | C26: 20591 | D26: 2801 | E26: 45971 | F26: SOARES | G26: MARCELO | H26: 0 | I26: 364.48 | J26: 45999 | K26: 46003 | L26: 362.82 | M26: =Tabela2246[[#This Row],[VENDA]]+Tabela2246[[#This Row],[MÃO DE OBRA]]-Tabela2246[[#This Row],[VALOR PAGO]] -> 1.66
F27: SOARES | G27: MARCELO | H27: 0 | I27: 362 | J27: 46006 | K27: 46010 | L27: 362.82 | M27: =Tabela2246[[#This Row],[VENDA]]+Tabela2246[[#This Row],[MÃO DE OBRA]]-Tabela2246[[#This Row],[VALOR PAGO]] -> -0.82
F28: SOARES | G28: MARCELO | H28: 0 | I28: 362 | J28: 46013 | K28: 45997 | L28: 362.83 | M28: =Tabela2246[[#This Row],[VENDA]]+Tabela2246[[#This Row],[MÃO DE OBRA]]-Tabela2246[[#This Row],[VALOR PAGO]] -> -0.83
B29: SMART | C29: 20644 | D29: 2838 | E29: 45974 | F29: SOARES | G29: MARCELO | H29: 0 | I29: 490.26 | J29: 46002 | K29: 46003 | L29: 488.75 | M29: =Tabela2246[[#This Row],[VENDA]]+Tabela2246[[#This Row],[MÃO DE OBRA]]-Tabela2246[[#This Row],[VALOR PAGO]] -> 1.51
F30: SOARES | G30: MARCELO | H30: 0 | I30: 488 | J30: 46009 | K30: 46010 | L30: 488.75 | M30: =Tabela2246[[#This Row],[VENDA]]+Tabela2246[[#This Row],[MÃO DE OBRA]]-Tabela2246[[#This Row],[VALOR PAGO]] -> -0.75
F31: SOARES | G31: MARCELO | H31: 0 | I31: 488 | J31: 46016 | K31: 46017 | L31: 488.74 | M31: =Tabela2246[[#This Row],[VENDA]]+Tabela2246[[#This Row],[MÃO DE OBRA]]-Tabela2246[[#This Row],[VALOR PAGO]] -> -0.74
B32: SMART | C32: 20656 | D32: 2888 | E32: 45974 | F32: LEANDRENSE | G32: MARCIANO | H32: 1036 | I32: 0 | J32: 45988 | K32: 45988 | L32: 1036 | M32: =Tabela2246[[#This Row],[VENDA]]+Tabela2246[[#This Row],[MÃO DE OBRA]]-Tabela2246[[#This Row],[VALOR PAGO]] -> 0
B33: STK | C33: 20671 | D33: 2898 | E33: 45975 | F33: SOARES | G33: DIRETO | H33: =26852.98/3 -> 8950.9933 | I33: 0 | J33: 46003 | K33: 46010 | L33: 8950.99 | M33: =Tabela2246[[#This Row],[VENDA]]+Tabela2246[[#This Row],[MÃO DE OBRA]]-Tabela2246[[#This Row],[VALOR PAGO]] -> 0.0033333333
F34: SOARES | G34: DIRETO | H34: 8950.9933 | I34: 0 | J34: 46010 | K34: 46017 | L34: 8950.99 | M34: =Tabela2246[[#This Row],[VENDA]]+Tabela2246[[#This Row],[MÃO DE OBRA]]-Tabela2246[[#This Row],[VALOR PAGO]] -> 0.0033333333
F35: SOARES | G35: DIRETO | H35: 8950.9933 | I35: 0 | J35: 46017 | K35: 46041 | L35: 8951 | M35: =Tabela2246[[#This Row],[VENDA]]+Tabela2246[[#This Row],[MÃO DE OBRA]]-Tabela2246[[#This Row],[VALOR PAGO]] -> -0.0066666667
B36: STK | C36: 20678 | D36: 2850 | E36: 45975 | F36: SOARES | G36: DIRETO | H36: =68611.8/3 -> 22870.6 | I36: 0 | J36: 46003 | K36: 46010 | L36: 22870.6 | M36: =Tabela2246[[#This Row],[VENDA]]+Tabela2246[[#This Row],[MÃO DE OBRA]]-Tabela2246[[#This Row],[VALOR PAGO]] -> 0
F37: SOARES | G37: DIRETO | H37: 22870.6 | I37: 0 | J37: 46010 | K37: 46017 | L37: 22870.6 | M37: =Tabela2246[[#This Row],[VENDA]]+Tabela2246[[#This Row],[MÃO DE OBRA]]-Tabela2246[[#This Row],[VALOR PAGO]] -> 0
F38: SOARES | G38: DIRETO | H38: 22870.6 | I38: 0 | J38: 46017 | K38: 46035 | L38: 22870.6 | M38: =Tabela2246[[#This Row],[VENDA]]+Tabela2246[[#This Row],[MÃO DE OBRA]]-Tabela2246[[#This Row],[VALOR PAGO]] -> 0
B39: STK | C39: 20679 | D39: 2906 | E39: 45975 | F39: SOARES | G39: DIRETO | H39: 8411.59 | I39: 0 | J39: 46003 | K39: 46010 | L39: 8411.59 | M39: =Tabela2246[[#This Row],[VENDA]]+Tabela2246[[#This Row],[MÃO DE OBRA]]-Tabela2246[[#This Row],[VALOR PAGO]] -> 0
F40: SOARES | G40: DIRETO | H40: 8411.59 | I40: 0 | J40: 46010 | K40: 46017 | L40: 8411.59 | M40: =Tabela2246[[#This Row],[VENDA]]+Tabela2246[[#This Row],[MÃO DE OBRA]]-Tabela2246[[#This Row],[VALOR PAGO]] -> 0
F41: SOARES | G41: DIRETO | H41: 8411.59 | I41: 0 | J41: 46017 | K41: 46041 | L41: 8411.59 | M41: =Tabela2246[[#This Row],[VENDA]]+Tabela2246[[#This Row],[MÃO DE OBRA]]-Tabela2246[[#This Row],[VALOR PAGO]] -> 0
B42: SMART | C42: 20707 | D42: 2880 | E42: 45979 | F42: SOARES | G42: MARCELO | H42: 0 | I42: 332.93 | J42: 46007 | K42: 46010 | L42: 332.92 | M42: =Tabela2246[[#This Row],[VENDA]]+Tabela2246[[#This Row],[MÃO DE OBRA]]-Tabela2246[[#This Row],[VALOR PAGO]] -> 0.01
F43: SOARES | G43: MARCELO | H43: 0 | I43: 332.92 | J43: 46014 | K43: 46017 | L43: 332.93 | M43: =Tabela2246[[#This Row],[VENDA]]+Tabela2246[[#This Row],[MÃO DE OBRA]]-Tabela2246[[#This Row],[VALOR PAGO]] -> -0.01
B44: SMART | C44: 20728 | D44: 2924 | E44: 45981 | F44: SOARES | G44: MARCELO | H44: 0 | I44: 408.83 | J44: 46009 | K44: 46055 | L44: 408.82 | M44: =Tabela2246[[#This Row],[VENDA]]+Tabela2246[[#This Row],[MÃO DE OBRA]]-Tabela2246[[#This Row],[VALOR PAGO]] -> 0.01
B45: SMART | C45: 20768 | D45: 2924 | E45: 45985 | F45: SOARES | G45: MARCELO | H45: 0 | I45: 411.42 | J45: 46013 | K45: 46007 | L45: 411.41 | M45: =Tabela2246[[#This Row],[VENDA]]+Tabela2246[[#This Row],[MÃO DE OBRA]]-Tabela2246[[#This Row],[VALOR PAGO]] -> 0.01
F46: SOARES | G46: MARCELO | H46: 0 | I46: 411.41 | J46: 46020 | K46: 46043 | L46: 411.41 | M46: =Tabela2246[[#This Row],[VENDA]]+Tabela2246[[#This Row],[MÃO DE OBRA]]-Tabela2246[[#This Row],[VALOR PAGO]] -> 0
F47: SOARES | G47: MARCELO | H47: 0 | I47: 0 | L47: 0 | M47: =Tabela2246[[#This Row],[VENDA]]+Tabela2246[[#This Row],[MÃO DE OBRA]]-Tabela2246[[#This Row],[VALOR PAGO]] -> 0
B48: SMART | C48: 20789 | D48: 2940 | E48: 45986 | F48: SOARES | G48: MARCELO | H48: 0 | I48: 339.83 | J48: 46014 | K48: 46017 | L48: 339.82 | M48: =Tabela2246[[#This Row],[VENDA]]+Tabela2246[[#This Row],[MÃO DE OBRA]]-Tabela2246[[#This Row],[VALOR PAGO]] -> 0.01
F49: SOARES | G49: MARCELO | H49: 0 | I49: 339.82 | J49: 46021 | K49: 46043 | L49: 339.83 | M49: =Tabela2246[[#This Row],[VENDA]]+Tabela2246[[#This Row],[MÃO DE OBRA]]-Tabela2246[[#This Row],[VALOR PAGO]] -> -0.01
B50: SMART | C50: 20792 | D50: 2940 | E50: 45987 | F50: SOARES | G50: MARCELO | H50: 0 | I50: 526.13 | J50: 46015 | K50: 46017 | L50: 526.12 | M50: =Tabela2246[[#This Row],[VENDA]]+Tabela2246[[#This Row],[MÃO DE OBRA]]-Tabela2246[[#This Row],[VALOR PAGO]] -> 0.01
B51: SMART | C51: 20797 | D51: 2963 | E51: 45987 | F51: SOARES | G51: MARCELO | H51: 0 | I51: 270.83 | J51: 46015 | K51: 46017 | L51: 270.82 | M51: =Tabela2246[[#This Row],[VENDA]]+Tabela2246[[#This Row],[MÃO DE OBRA]]-Tabela2246[[#This Row],[VALOR PAGO]] -> 0.01
B52: STK | C52: 20809 | D52: 2965 | E52: 45988 | F52: SOARES | G52: DIRETO | H52: 17519.133 | I52: 0 | J52: 46016 | K52: 46036 | L52: 17519.13 | M52: =Tabela2246[[#This Row],[VENDA]]+Tabela2246[[#This Row],[MÃO DE OBRA]]-Tabela2246[[#This Row],[VALOR PAGO]] -> 0.0033333333
F53: SOARES | G53: DIRETO | H53: 17519.133 | I53: 0 | J53: 45658 | K53: 46043 | L53: 17519.13 | M53: =Tabela2246[[#This Row],[VENDA]]+Tabela2246[[#This Row],[MÃO DE OBRA]]-Tabela2246[[#This Row],[VALOR PAGO]] -> 0.0033333333
F54: SOARES | G54: DIRETO | H54: 17519.133 | I54: 0 | J54: 45665 | K54: 46050 | L54: 17519.13 | M54: =Tabela2246[[#This Row],[VENDA]]+Tabela2246[[#This Row],[MÃO DE OBRA]]-Tabela2246[[#This Row],[VALOR PAGO]] -> 0.0033333333
B55: STK | C55: 498 | D55: 452 | E55: 45988 | F55: RM | G55: MARCIANO | H55: 11156.25 | I55: 0 | J55: 46066 | K55: 46066 | L55: 11156.25 | M55: =Tabela2246[[#This Row],[VENDA]]+Tabela2246[[#This Row],[MÃO DE OBRA]]-Tabela2246[[#This Row],[VALOR PAGO]] -> 0
F56: RM | G56: MARCIANO | H56: 11153 | I56: 0 | J56: 45708 | K56: 46077 | L56: 11153 | M56: =Tabela2246[[#This Row],[VENDA]]+Tabela2246[[#This Row],[MÃO DE OBRA]]-Tabela2246[[#This Row],[VALOR PAGO]] -> 0
D57: ATENÇÃO: COMISSÃO 1% | F57: RM | G57: MARCIANO | H57: 11153 | I57: 0 | J57: 45715 | K57: 46084 | L57: 11153 | M57: =Tabela2246[[#This Row],[VENDA]]+Tabela2246[[#This Row],[MÃO DE OBRA]]-Tabela2246[[#This Row],[VALOR PAGO]] -> 0
F58: RM | G58: MARCIANO | H58: 11153 | I58: 0 | J58: 45722 | K58: 46093 | L58: 11153 | M58: =Tabela2246[[#This Row],[VENDA]]+Tabela2246[[#This Row],[MÃO DE OBRA]]-Tabela2246[[#This Row],[VALOR PAGO]] -> 0
F59: RM | G59: MARCIANO | H59: 11153 | I59: 0 | J59: 45729 | K59: 46098 | L59: 11153 | M59: =Tabela2246[[#This Row],[VENDA]]+Tabela2246[[#This Row],[MÃO DE OBRA]]-Tabela2246[[#This Row],[VALOR PAGO]] -> 0
F60: RM | G60: MARCIANO | H60: 11153 | I60: 0 | J60: 45736 | K60: 46106 | L60: 11153 | M60: =Tabela2246[[#This Row],[VENDA]]+Tabela2246[[#This Row],[MÃO DE OBRA]]-Tabela2246[[#This Row],[VALOR PAGO]] -> 0
B61: STK | C61: 499 | D61: 467 | E61: 45988 | F61: RM | G61: MARCIANO | H61: 5040 | I61: 0 | J61: 46066 | K61: 46066 | L61: 5040 | M61: =Tabela2246[[#This Row],[VENDA]]+Tabela2246[[#This Row],[MÃO DE OBRA]]-Tabela2246[[#This Row],[VALOR PAGO]] -> 0
F62: RM | G62: MARCIANO | H62: 5037 | I62: 0 | J62: 45708 | K62: 46077 | L62: 5037 | M62: =Tabela2246[[#This Row],[VENDA]]+Tabela2246[[#This Row],[MÃO DE OBRA]]-Tabela2246[[#This Row],[VALOR PAGO]] -> 0
D63: ATENÇÃO: COMISSÃO 1% | F63: RM | G63: MARCIANO | H63: 5037 | I63: 0 | J63: 45715 | K63: 46084 | L63: 5037 | M63: =Tabela2246[[#This Row],[VENDA]]+Tabela2246[[#This Row],[MÃO DE OBRA]]-Tabela2246[[#This Row],[VALOR PAGO]] -> 0
F64: RM | G64: MARCIANO | H64: 5037 | I64: 0 | J64: 45722 | K64: 46093 | L64: 5037 | M64: =Tabela2246[[#This Row],[VENDA]]+Tabela2246[[#This Row],[MÃO DE OBRA]]-Tabela2246[[#This Row],[VALOR PAGO]] -> 0
F65: RM | G65: MARCIANO | H65: 5037 | I65: 0 | J65: 45729 | K65: 46098 | L65: 5037 | M65: =Tabela2246[[#This Row],[VENDA]]+Tabela2246[[#This Row],[MÃO DE OBRA]]-Tabela2246[[#This Row],[VALOR PAGO]] -> 0
F66: RM | G66: MARCIANO | H66: 5037 | I66: 0 | J66: 45736 | K66: 46106 | L66: 5037 | M66: =Tabela2246[[#This Row],[VENDA]]+Tabela2246[[#This Row],[MÃO DE OBRA]]-Tabela2246[[#This Row],[VALOR PAGO]] -> 0
B67: STK | C67: 500 | D67: 468 | E67: 45988 | F67: RM | G67: MARCIANO | H67: 14845.25 | I67: 0 | J67: 46066 | K67: 46066 | L67: 14845.25 | M67: =Tabela2246[[#This Row],[VENDA]]+Tabela2246[[#This Row],[MÃO DE OBRA]]-Tabela2246[[#This Row],[VALOR PAGO]] -> 0
F68: RM | G68: MARCIANO | H68: 14842 | I68: 0 | J68: 45708 | K68: 46077 | L68: 14842 | M68: =Tabela2246[[#This Row],[VENDA]]+Tabela2246[[#This Row],[MÃO DE OBRA]]-Tabela2246[[#This Row],[VALOR PAGO]] -> 0
D69: ATENÇÃO: COMISSÃO 1% | F69: RM | G69: MARCIANO | H69: 14842 | I69: 0 | J69: 45715 | K69: 46084 | L69: 14842 | M69: =Tabela2246[[#This Row],[VENDA]]+Tabela2246[[#This Row],[MÃO DE OBRA]]-Tabela2246[[#This Row],[VALOR PAGO]] -> 0
F70: RM | G70: MARCIANO | H70: 14842 | I70: 0 | J70: 45722 | K70: 46093 | L70: 14842 | M70: =Tabela2246[[#This Row],[VENDA]]+Tabela2246[[#This Row],[MÃO DE OBRA]]-Tabela2246[[#This Row],[VALOR PAGO]] -> 0
F71: RM | G71: MARCIANO | H71: 14842 | I71: 0 | J71: 45729 | K71: 46098 | L71: 14842 | M71: =Tabela2246[[#This Row],[VENDA]]+Tabela2246[[#This Row],[MÃO DE OBRA]]-Tabela2246[[#This Row],[VALOR PAGO]] -> 0
F72: RM | G72: MARCIANO | H72: 14842 | I72: 0 | J72: 45736 | K72: 46106 | L72: 14842 | M72: =Tabela2246[[#This Row],[VENDA]]+Tabela2246[[#This Row],[MÃO DE OBRA]]-Tabela2246[[#This Row],[VALOR PAGO]] -> 0
B73: STK | C73: 20788 | D73: 2993 | E73: 45986 | F73: GLAUCIA | G73: SILVANO | H73: =154*11.97 -> 1843.38 | I73: 0 | J73: 45986 | K73: 45993 | L73: 1843.38 | M73: =Tabela2246[[#This Row],[VENDA]]+Tabela2246[[#This Row],[MÃO DE OBRA]]-Tabela2246[[#This Row],[VALOR PAGO]] -> 0
B74: SMART | C74: 20843 | D74: 3002 | E74: 45989 | F74: SOARES | G74: MARCELO | H74: 0 | I74: 1453.03 | J74: 46017 | K74: 46043 | L74: 1453.02 | M74: =Tabela2246[[#This Row],[VENDA]]+Tabela2246[[#This Row],[MÃO DE OBRA]]-Tabela2246[[#This Row],[VALOR PAGO]] -> 0.01
F75: SOARES | G75: MARCELO | H75: 0 | I75: 1453.03 | J75: 45659 | K75: 46043 | L75: 1453.02 | M75: =Tabela2246[[#This Row],[VENDA]]+Tabela2246[[#This Row],[MÃO DE OBRA]]-Tabela2246[[#This Row],[VALOR PAGO]] -> 0.01
F76: SOARES | G76: MARCELO | H76: 0 | I76: 1453.02 | J76: 45666 | K76: 46050 | L76: 1453.03 | M76: =Tabela2246[[#This Row],[VENDA]]+Tabela2246[[#This Row],[MÃO DE OBRA]]-Tabela2246[[#This Row],[VALOR PAGO]] -> -0.01
C77: Total | H77: =SUM(H21:H76) -> 369837.83 | I77: =SUM(I21:I76) -> 11852.53 | L77: =SUM(L21:L76) -> 381690.24 | M77: =SUM(M21:M76) -> 0.12
B78: TOTAL VENDA: | D78: =Tabela2246[[#Totals],[VENDA]] -> 369837.83
B79: TOTAL MÃO DE OBRA: | D79: =Tabela2246[[#Totals],[MÃO DE OBRA]] -> 11852.53
B80: TOTAL: | C80: =SUM(D78+D79) -> 381690.36 | F80: TOTAL RECEBIDO: | H80: =Tabela2246[[#Totals],[VALOR PAGO]] -> 381690.24 | J80: TOTAL À RECEBER: | L80: =Tabela2246[[#Totals],[VALOR EM ABERTO]] -> 0.12

Sheet Dezembro 2025
B2: FRETES
B4: MÊS | C4: SMART | H4: STK
C5: 2023 | D5: 2024 | E5: 2025 | F5: 2026 | G5: 2027 | H5: 2025 | I5: 2026 | J5: 2027 | K5: 2028 | L5: 2029 | M5: 2030
B6: JANEIRO | C6: 126073.37 | D6: 270562.53 | E6: 49887.66 | F6: 0 | G6: 0 | H6: 0 | I6: 0 | J6: 0 | K6: 0 | L6: 0 | M6: 0
B7: FEVEREIRO | C7: 166235.96 | D7: 324984.97 | E7: 15513.83 | F7: 0 | G7: 0 | H7: 0 | I7: 0 | J7: 0 | K7: 0 | L7: 0 | M7: 0
B8: MARÇO | C8: 119814.85 | D8: 256001.57 | E8: 32410.22 | F8: 0 | G8: 0 | H8: 0 | I8: 0 | J8: 0 | K8: 0 | L8: 0 | M8: 0
B9: ABRIL | C9: 112668.22 | D9: 136419.94 | E9: 23117.53 | F9: 0 | G9: 0 | H9: 0 | I9: 0 | J9: 0 | K9: 0 | L9: 0 | M9: 0
B10: MAIO | C10: 39597.94 | D10: 57014.4 | E10: 11710.4 | F10: 0 | G10: 0 | H10: 0 | I10: 0 | J10: 0 | K10: 0 | L10: 0 | M10: 0
B11: JUNHO | C11: 77419.24 | D11: 259261.92 | E11: 32986.86 | F11: 0 | G11: 0 | H11: 0 | I11: 0 | J11: 0 | K11: 0 | L11: 0 | M11: 0
B12: JULHO | C12: 74963.62 | D12: 191964.91 | E12: 8086.81 | F12: 0 | G12: 0 | H12: 0 | I12: 0 | J12: 0 | K12: 0 | L12: 0 | M12: 0
B13: AGOSTO | C13: 152485.66 | D13: 273158.85 | E13: 22122.22 | F13: 0 | G13: 0 | H13: 0 | I13: 0 | J13: 0 | K13: 0 | L13: 0 | M13: 0
B14: SETEMBRO | C14: 171282.48 | D14: 63159.51 | E14: 36466.42 | F14: 0 | G14: 0 | H14: 0 | I14: 0 | J14: 0 | K14: 0 | L14: 0 | M14: 0
B15: OUTUBRO | C15: 168433.06 | D15: 53077.38 | E15: 99828 | F15: 0 | G15: 0 | H15: 1595.6 | I15: 0 | J15: 0 | K15: 0 | L15: 0 | M15: 0
B16: NOVEMBRO | C16: 155757.68 | D16: 15517.44 | E16: =Tabela2246[[#Totals],[VENDA]]+Tabela2246[[#Totals],[MÃO DE OBRA]] -> 381690.36 | F16: 0 | G16: 0 | H16: 0 | I16: 0 | J16: 0 | K16: 0 | L16: 0 | M16: 0
B17: DEZEMBRO | C17: 163379.08 | D17: 9580.01 | E17: =Tabela22465[[#Totals],[VENDA]]+Tabela22465[[#Totals],[MÃO DE OBRA]] -> 148680.26 | F17: 0 | G17: 0 | H17: 0 | I17: 0 | J17: 0 | K17: 0 | L17: 0 | M17: 0
B18: TOTAL | C18: =SUM(C6:C17) -> 1528111.2 | D18: =SUM(D6:D17) -> 1910703.4 | E18: =SUM(E6:E17) -> 862500.57 | F18: =SUM(F6:F17) -> 0 | G18: 0 | H18: =SUM(H6:H17) -> 1595.6 | I18: 0 | J18: =SUM(J6:J17) -> 0 | K18: 0 | L18: =SUM(L6:L17) -> 0 | M18: 0
B19: TOTAL CONSOLIDADO 2025: | D19: =SUM(H18+E18) -> 864096.17
B20: EMPRESA | C20: NOTA FISCAL | D20: PEDIDO | E20: DATA DE EMISSÃO | F20: DESTINATÁRIO | G20: REPRESENTANTE | H20: VENDA | I20: MÃO DE OBRA | J20: VENCIMENTO | K20: DATA DE PAGAMENTO | L20: VALOR PAGO | M20: VALOR EM ABERTO | N20: Coluna1
B21: STK | C21: 507 | D21: 428 | E21: 45992 | F21: GLAUCIA | G21: SILVANO | H21: =901*7.5 -> 6757.5 | I21: 0 | J21: 45992 | K21: 46006 | L21: 6757.5 | M21: =Tabela22465[[#This Row],[VENDA]]+Tabela22465[[#This Row],[MÃO DE OBRA]]-Tabela22465[[#This Row],[VALOR PAGO]] -> 0
B22: STK | C22: 20882 | D22: 2993 | E22: 45993 | F22: GLAUCIA | G22: SILVANO | H22: =160*11.97 -> 1915.2 | I22: 0 | J22: 45993 | K22: 45993 | L22: 1915.2 | M22: =Tabela22465[[#This Row],[VENDA]]+Tabela22465[[#This Row],[MÃO DE OBRA]]-Tabela22465[[#This Row],[VALOR PAGO]] -> 0
B23: STK | C23: 20883 | D23: 3050 | E23: 45993 | F23: GLAUCIA | G23: SILVANO | H23: =520*11.97 -> 6224.4 | I23: 0 | J23: 45993 | K23: 45993 | L23: 6224.4 | M23: =Tabela22465[[#This Row],[VENDA]]+Tabela22465[[#This Row],[MÃO DE OBRA]]-Tabela22465[[#This Row],[VALOR PAGO]] -> 0
B24: STK | C24: 525 | D24: 1019 | E24: 46360 | F24: RM CALÇADOS | G24: MARCIANO | H24: 18956.25 | I24: 0 | J24: 46112 | K24: 46122 | L24: 18956.25 | M24: =Tabela22465[[#This Row],[VENDA]]+Tabela22465[[#This Row],[MÃO DE OBRA]]-Tabela22465[[#This Row],[VALOR PAGO]] -> 0
B25: STK | C25: 525 | D25: 1019 | E25: 46360 | F25: RM CALÇADOS | G25: MARCIANO | H25: 18954 | I25: 0 | J25: 46119 | K25: 46150 | L25: 18954 | M25: =Tabela22465[[#This Row],[VENDA]]+Tabela22465[[#This Row],[MÃO DE OBRA]]-Tabela22465[[#This Row],[VALOR PAGO]] -> 0
B26: STK | C26: 525 | D26: 1019 | E26: 46360 | F26: RM CALÇADOS | G26: MARCIANO | H26: 18954 | I26: 0 | J26: 46126 | K26: 46160 | L26: 18954 | M26: =Tabela22465[[#This Row],[VENDA]]+Tabela22465[[#This Row],[MÃO DE OBRA]]-Tabela22465[[#This Row],[VALOR PAGO]] -> 0
B27: STK | C27: 525 | D27: 1019 | E27: 46360 | F27: RM CALÇADOS | G27: MARCIANO | H27: 18954 | I27: 0 | J27: 46133 | K27: 46176 | L27: 18954 | M27: =Tabela22465[[#This Row],[VENDA]]+Tabela22465[[#This Row],[MÃO DE OBRA]]-Tabela22465[[#This Row],[VALOR PAGO]] -> 0
B28: SMART | C28: 20958 | D28: 3078 | E28: 45996 | F28: LC COMPONENTES | G28: MARCELO | H28: 0 | I28: 1404.23 | J28: 45666 | K28: 46035 | L28: 1404.23 | M28: =Tabela22465[[#This Row],[VENDA]]+Tabela22465[[#This Row],[MÃO DE OBRA]]-Tabela22465[[#This Row],[VALOR PAGO]] -> 0
B29: SMART | C29: 20959 | D29: 3106 | E29: 46361 | F29: LC COMPONENTES | G29: MARCELO | I29: 1411.33 | J29: 46031 | K29: 46035 | L29: 1411.33 | M29: =Tabela22465[[#This Row],[VENDA]]+Tabela22465[[#This Row],[MÃO DE OBRA]]-Tabela22465[[#This Row],[VALOR PAGO]] -> 0
B30: SMART | C30: 21045 | D30: 3192 | E30: 46002 | F30: LC COMPONENTES | G30: MARCELO | H30: 0 | I30: =198*7.11 -> 1407.78 | J30: 45672 | K30: 46037 | L30: 1407.78 | M30: =Tabela22465[[#This Row],[VENDA]]+Tabela22465[[#This Row],[MÃO DE OBRA]]-Tabela22465[[#This Row],[VALOR PAGO]] -> 0
B31: SMART | C31: 20905 | D31: 3042 | E31: 45994 | F31: SOARES | G31: MARCELO | H31: 0 | I31: 458.85 | J31: 46022 | K31: 46043 | L31: 458.85 | M31: =Tabela22465[[#This Row],[VENDA]]+Tabela22465[[#This Row],[MÃO DE OBRA]]-Tabela22465[[#This Row],[VALOR PAGO]] -> 0
H32: 0 | I32: 458.85 | J32: 45664 | K32: 46044 | L32: 458.85 | M32: =Tabela22465[[#This Row],[VENDA]]+Tabela22465[[#This Row],[MÃO DE OBRA]]-Tabela22465[[#This Row],[VALOR PAGO]] -> 0
H33: 0 | I33: 458.95 | J33: 45671 | K33: 46055 | L33: 458.85 | M33: =Tabela22465[[#This Row],[VENDA]]+Tabela22465[[#This Row],[MÃO DE OBRA]]-Tabela22465[[#This Row],[VALOR PAGO]] -> 0.1
B34: SMART | C34: 20910 | D34: 3042 | E34: 45994 | F34: SOARES | G34: MARCELO | H34: 0 | I34: =2998.05/3 -> 999.35 | J34: 46022 | K34: 46043 | L34: 999.34 | M34: =Tabela22465[[#This Row],[VENDA]]+Tabela22465[[#This Row],[MÃO DE OBRA]]-Tabela22465[[#This Row],[VALOR PAGO]] -> 0.01
H35: 0 | I35: =2998.05/3 -> 999.35 | J35: 45664 | K35: 46044 | L35: 999.34 | M35: =Tabela22465[[#This Row],[VENDA]]+Tabela22465[[#This Row],[MÃO DE OBRA]]-Tabela22465[[#This Row],[VALOR PAGO]] -> 0.01
H36: 0 | I36: =2998.05/3 -> 999.35 | J36: 45671 | K36: 46055 | L36: 999.35 | M36: =Tabela22465[[#This Row],[VENDA]]+Tabela22465[[#This Row],[MÃO DE OBRA]]-Tabela22465[[#This Row],[VALOR PAGO]] -> 0
B37: SMART | C37: 20995 | D37: 3115 | E37: 46000 | F37: SOARES | G37: MARCELO | H37: 0 | I37: =3437.93/3 -> 1145.9767 | J37: 45663 | K37: 46044 | L37: 1145.97 | M37: =Tabela22465[[#This Row],[VENDA]]+Tabela22465[[#This Row],[MÃO DE OBRA]]-Tabela22465[[#This Row],[VALOR PAGO]] -> 0.0066666667
H38: 0 | I38: =3437.93/3 -> 1145.9767 | J38: 45670 | K38: 46055 | L38: 1145.97 | M38: =Tabela22465[[#This Row],[VENDA]]+Tabela22465[[#This Row],[MÃO DE OBRA]]-Tabela22465[[#This Row],[VALOR PAGO]] -> 0.0066666667
H39: 0 | I39: =3437.93/3 -> 1145.9767 | J39: 45677 | K39: 02/002/26 | L39: 1145.97 | M39: =Tabela22465[[#This Row],[VENDA]]+Tabela22465[[#This Row],[MÃO DE OBRA]]-Tabela22465[[#This Row],[VALOR PAGO]] -> 0.0066666667
B40: SMART | C40: 21058 | D40: 3165 | E40: 46368 | F40: SOARES | G40: MARCELO | H40: 0 | I40: 1030.4 | J40: 46031 | K40: 46055 | L40: 1030.4 | M40: =Tabela22465[[#This Row],[VENDA]]+Tabela22465[[#This Row],[MÃO DE OBRA]]-Tabela22465[[#This Row],[VALOR PAGO]] -> 0
H41: 0 | I41: 1030.4 | J41: 46038 | K41: 46055 | L41: 1030.39 | M41: =Tabela22465[[#This Row],[VENDA]]+Tabela22465[[#This Row],[MÃO DE OBRA]]-Tabela22465[[#This Row],[VALOR PAGO]] -> 0.01
H42: 0 | I42: 1030.41 | J42: 46045 | K42: 46055 | L42: 1030.4 | M42: =Tabela22465[[#This Row],[VENDA]]+Tabela22465[[#This Row],[MÃO DE OBRA]]-Tabela22465[[#This Row],[VALOR PAGO]] -> 0.01
B43: SMART | C43: 21059 | D43: 3182 | E43: 46368 | F43: SOARES | G43: MARCELO | H43: 0 | I43: 810.18 | J43: 46031 | K43: 46050 | L43: 810.17 | M43: =Tabela22465[[#This Row],[VENDA]]+Tabela22465[[#This Row],[MÃO DE OBRA]]-Tabela22465[[#This Row],[VALOR PAGO]] -> 0.01
H44: 0 | I44: 810.18 | J44: 46038 | K44: 46055 | L44: 810.17 | M44: =Tabela22465[[#This Row],[VENDA]]+Tabela22465[[#This Row],[MÃO DE OBRA]]-Tabela22465[[#This Row],[VALOR PAGO]] -> 0.01
H45: 0 | I45: 810.17 | J45: 46045 | K45: 46055 | L45: 810.18 | M45: =Tabela22465[[#This Row],[VENDA]]+Tabela22465[[#This Row],[MÃO DE OBRA]]-Tabela22465[[#This Row],[VALOR PAGO]] -> -0.01
B46: SMART | C46: 21057 | D46: s/pedido | E46: 46368 | F46: VIASCARPA | G46: MARCELO | H46: 0 | I46: =7528 -> 7528 | J46: =Tabela22465[[#This Row],[DATA DE EMISSÃO]]+14 -> 46382 | K46: ACERTO | L46: 0 | M46: 0
B47: SMART | C47: 21070 | D47: s/pedido | E47: 46372 | F47: VIASCARPA | G47: MARCELO | H47: 0 | I47: 12675.6 | J47: =Tabela22465[[#This Row],[DATA DE EMISSÃO]]+14 -> 46386 | K47: ACERTO | L47: 0 | M47: 0
B48: SMART | C48: 21057 | D48: Sem pedido | E48: 46368 | F48: VIASCARPA | G48: MARCELO | I48: =470.5*8 -> 3764 | J48: - | M48: 0 | N48: Benef em cima de Napa Like Aveia que veio errado via Importação. Transformado em Napa Like Mocca
B49: SMART | C49: 21057 | D49: Sem pedido | E49: 46368 | F49: VIASCARPA | G49: MARCELO | I49: =470.5*8 -> 3764 | J49: - | M49: 0 | N49: Benef em cima de Napa Like Aveia que veio errado via Importação. Transformado em Napa Like Capuccino
B50: SMART | C50: 21070 | D50: Sem pedido | E50: 46372 | F50: VIASCARPA | G50: MARCELO | I50: =1006*12.6 -> 12675.6 | J50: - | M50: 0 | N50: Benef em cima de Napa Like Aveia que veio errado via Importação. Transformado em Napa Metal Lyon O. Light
C51: Total | H51: =SUM(H21:H50) -> 90715.35 | I51: =SUM(I21:I50) -> 57964.91 | L51: =SUM(L21:L50) -> 108272.89 | M51: =SUM(M21:M50) -> 0.17
B52: TOTAL VENDA: | D52: =Tabela22465[[#Totals],[VENDA]] -> 90715.35
B53: TOTAL MÃO DE OBRA: | D53: =Tabela22465[[#Totals],[MÃO DE OBRA]] -> 57964.91
B54: TOTAL: | C54: =SUM(D52+D53) -> 148680.26 | F54: TOTAL RECEBIDO: | H54: =Tabela22465[[#Totals],[VALOR PAGO]] -> 108272.89 | J54: TOTAL À RECEBER: | L54: =Tabela22465[[#Totals],[VALOR EM ABERTO]] -> 0.17

Sheet Janeiro 2026
B2: FRETES
B4: MÊS | C4: SMART | H4: STK
C5: 2023 | D5: 2024 | E5: 2025 | F5: 2026 | G5: 2027 | H5: 2025 | I5: 2026 | J5: 2027 | K5: 2028 | L5: 2029 | M5: 2030
B6: JANEIRO | C6: 126073.37 | D6: 270562.53 | E6: 49887.66 | F6: 0 | G6: 0 | H6: 0 | I6: 0 | J6: 0 | K6: 0 | L6: 0 | M6: 0
B7: FEVEREIRO | C7: 166235.96 | D7: 324984.97 | E7: 15513.83 | F7: 0 | G7: 0 | H7: 0 | I7: 0 | J7: 0 | K7: 0 | L7: 0 | M7: 0
B8: MARÇO | C8: 119814.85 | D8: 256001.57 | E8: 32410.22 | F8: 0 | G8: 0 | H8: 0 | I8: 0 | J8: 0 | K8: 0 | L8: 0 | M8: 0
B9: ABRIL | C9: 112668.22 | D9: 136419.94 | E9: 23117.53 | F9: 0 | G9: 0 | H9: 0 | I9: 0 | J9: 0 | K9: 0 | L9: 0 | M9: 0
B10: MAIO | C10: 39597.94 | D10: 57014.4 | E10: 11710.4 | F10: 0 | G10: 0 | H10: 0 | I10: 0 | J10: 0 | K10: 0 | L10: 0 | M10: 0
B11: JUNHO | C11: 77419.24 | D11: 259261.92 | E11: 32986.86 | F11: 0 | G11: 0 | H11: 0 | I11: 0 | J11: 0 | K11: 0 | L11: 0 | M11: 0
B12: JULHO | C12: 74963.62 | D12: 191964.91 | E12: 8086.81 | F12: 0 | G12: 0 | H12: 0 | I12: 0 | J12: 0 | K12: 0 | L12: 0 | M12: 0
B13: AGOSTO | C13: 152485.66 | D13: 273158.85 | E13: 22122.22 | F13: 0 | G13: 0 | H13: 0 | I13: 0 | J13: 0 | K13: 0 | L13: 0 | M13: 0
B14: SETEMBRO | C14: 171282.48 | D14: 63159.51 | E14: 36466.42 | F14: 0 | G14: 0 | H14: 0 | I14: 0 | J14: 0 | K14: 0 | L14: 0 | M14: 0
B15: OUTUBRO | C15: 168433.06 | D15: 53077.38 | E15: 99828 | F15: 0 | G15: 0 | I15: 0 | J15: 0 | K15: 0 | L15: 0 | M15: 0
B16: NOVEMBRO | C16: 155757.68 | D16: 15517.44 | E16: 0 | F16: 0 | G16: 0 | H16: 0 | I16: 0 | J16: 0 | K16: 0 | L16: 0 | M16: 0
B17: DEZEMBRO | C17: 163379.08 | D17: 9580.01 | E17: 0 | F17: 0 | G17: 0 | H17: 0 | I17: 0 | J17: 0 | K17: 0 | L17: 0 | M17: 0
B18: TOTAL | C18: =SUM(C6:C17) -> 1528111.2 | D18: =SUM(D6:D17) -> 1910703.4 | E18: =SUM(E6:E17) -> 332129.95 | F18: =SUM(F6:F17) -> 0 | G18: 0 | H18: =SUM(H6:H17) -> 0 | I18: 0 | J18: =SUM(J6:J17) -> 0 | K18: 0 | L18: =SUM(L6:L17) -> 0 | M18: 0
B19: TOTAL CONSOLIDADO 2026: | D19: =SUM(I18+F18) -> 0
B20: EMPRESA | C20: NOTA FISCAL | D20: PEDIDO | E20: DATA DE EMISSÃO | F20: DESTINATÁRIO | G20: REPRESENTANTE | H20: VENDA | I20: MÃO DE OBRA | J20: VENCIMENTO | K20: DATA DE PAGAMENTO | L20: VALOR PAGO | M20: VALOR EM ABERTO
B21: STK | C21: 21098 | D21: 3229 | E21: 46030 | F21: GLAUCIA | G21: SILVANO | H21: 3704.72 | J21: 46030 | K21: 46030 | L21: 3704.72 | M21: =Tabela224657[[#This Row],[VENDA]]+Tabela224657[[#This Row],[MÃO DE OBRA]]-Tabela224657[[#This Row],[VALOR PAGO]] -> 0
B22: SMART | C22: 21087 | D22: 3202 | E22: 46029 | F22: SOARES | G22: MARCELO | I22: 960.25 | J22: 46057 | K22: 46055 | L22: 960.24 | M22: =Tabela224657[[#This Row],[VENDA]]+Tabela224657[[#This Row],[MÃO DE OBRA]]-Tabela224657[[#This Row],[VALOR PAGO]] -> 0.01
B23: SMART | C23: 21087 | D23: 3202 | E23: 46029 | F23: SOARES | G23: MARCELO | I23: 960.25 | J23: 46064 | K23: 46055 | L23: 960.25 | M23: =Tabela224657[[#This Row],[VENDA]]+Tabela224657[[#This Row],[MÃO DE OBRA]]-Tabela224657[[#This Row],[VALOR PAGO]] -> 0
B24: SMART | C24: 21087 | D24: 3202 | E24: 46029 | F24: SOARES | G24: MARCELO | I24: 960.25 | J24: 46071 | K24: 46055 | L24: 960.25 | M24: =Tabela224657[[#This Row],[VENDA]]+Tabela224657[[#This Row],[MÃO DE OBRA]]-Tabela224657[[#This Row],[VALOR PAGO]] -> 0
B25: SMART | C25: 21147 | D25: 3225 | E25: 46035 | F25: LC COMPONENTES | G25: MARCELO | I25: 280.85 | J25: 46056 | K25: 46056 | L25: 280.84 | M25: =Tabela224657[[#This Row],[VENDA]]+Tabela224657[[#This Row],[MÃO DE OBRA]]-Tabela224657[[#This Row],[VALOR PAGO]] -> 0.01
B26: STK | C26: 21203 | D26: 3322 | E26: 46038 | F26: GLAUCIA | G26: SILVANO | H26: =(608.2*0.01)+17623.77 -> 17629.852 | J26: 46038 | K26: 46037 | L26: 18008.65 | M26: =Tabela224657[[#This Row],[VENDA]]+Tabela224657[[#This Row],[MÃO DE OBRA]]-Tabela224657[[#This Row],[VALOR PAGO]] -> -378.798
B27: SMART | C27: 21156 | D27: 3265 | E27: 46036 | F27: LC COMPONENTES | G27: MARCELO | I27: =(76.5+75.5+74.5+75.5+77.5+76.5+76.5)*8.91 -> 4744.575 | J27: 46057 | K27: 46058 | L27: 4744.58 | M27: =Tabela224657[[#This Row],[VENDA]]+Tabela224657[[#This Row],[MÃO DE OBRA]]-Tabela224657[[#This Row],[VALOR PAGO]] -> -0.005
B28: SMART | C28: 21177 | D28: 3240 | E28: 46037 | F28: SOARES | G28: MARCELO | I28: =(39.5+39)*3.45 -> 270.825 | J28: 46065 | K28: 46055 | L28: 270.82 | M28: =Tabela224657[[#This Row],[VENDA]]+Tabela224657[[#This Row],[MÃO DE OBRA]]-Tabela224657[[#This Row],[VALOR PAGO]] -> 0.005
B29: SMART | C29: 21181 | D29: 3239 | E29: 46038 | F29: SOARES | G29: MARCELO | I29: 718.75 | J29: 46066 | K29: 46055 | L29: 718.75 | M29: =Tabela224657[[#This Row],[VENDA]]+Tabela224657[[#This Row],[MÃO DE OBRA]]-Tabela224657[[#This Row],[VALOR PAGO]] -> 0
B30: SMART | C30: 21181 | D30: 3239 | E30: 46038 | F30: SOARES | G30: MARCELO | I30: 718.75 | J30: 46073 | K30: 46055 | L30: 718.75 | M30: =Tabela224657[[#This Row],[VENDA]]+Tabela224657[[#This Row],[MÃO DE OBRA]]-Tabela224657[[#This Row],[VALOR PAGO]] -> 0
B31: SMART | C31: 21181 | D31: 3239 | E31: 46038 | F31: SOARES | G31: MARCELO | I31: 718.75 | J31: 46080 | K31: 46055 | L31: 718.74 | M31: =Tabela224657[[#This Row],[VENDA]]+Tabela224657[[#This Row],[MÃO DE OBRA]]-Tabela224657[[#This Row],[VALOR PAGO]] -> 0.01
B32: SMART | C32: 21182 | D32: 3241 | E32: 46038 | F32: SOARES | G32: MARCELO | I32: =(198.5+319.5+315+175)*3.45/3 -> 1159.2 | J32: 46066 | K32: 46055 | L32: 1159.2 | M32: =Tabela224657[[#This Row],[VENDA]]+Tabela224657[[#This Row],[MÃO DE OBRA]]-Tabela224657[[#This Row],[VALOR PAGO]] -> 0
B33: SMART | C33: 21182 | D33: 3241 | E33: 46038 | F33: SOARES | G33: MARCELO | I33: 1159.2 | J33: 46073 | K33: 46055 | L33: 1159.2 | M33: =Tabela224657[[#This Row],[VENDA]]+Tabela224657[[#This Row],[MÃO DE OBRA]]-Tabela224657[[#This Row],[VALOR PAGO]] -> 0
B34: SMART | C34: 21182 | D34: 3241 | E34: 46038 | F34: SOARES | G34: MARCELO | I34: 1159.2 | J34: 46080 | K34: 46055 | L34: 1159.19 | M34: =Tabela224657[[#This Row],[VENDA]]+Tabela224657[[#This Row],[MÃO DE OBRA]]-Tabela224657[[#This Row],[VALOR PAGO]] -> 0.01
B35: SMART | C35: 21258 | D35: 3324 | E35: 46043 | F35: SOARES | G35: MARCELO | I35: 590.53 | J35: 46071 | K35: 46055 | L35: 590.52 | M35: =Tabela224657[[#This Row],[VENDA]]+Tabela224657[[#This Row],[MÃO DE OBRA]]-Tabela224657[[#This Row],[VALOR PAGO]] -> 0.01
B36: STK | C36: 21206 | D36: 3325 | E36: 46038 | F36: NOSSA SRA DE FAT | G36: MARCIANO | H36: 1346.76 | J36: 46038 | K36: 46038 | L36: 1346.76 | M36: =Tabela224657[[#This Row],[VENDA]]+Tabela224657[[#This Row],[MÃO DE OBRA]]-Tabela224657[[#This Row],[VALOR PAGO]] -> 0
B37: SMART | C37: 21263 | D37: 3347 | E37: 46043 | F37: LC COMPONENTES | G37: MARCELO | I37: 949.19 | J37: 46078 | K37: 46078 | L37: 949.19 | M37: =Tabela224657[[#This Row],[VENDA]]+Tabela224657[[#This Row],[MÃO DE OBRA]]-Tabela224657[[#This Row],[VALOR PAGO]] -> 0
B38: STK | C38: 21280 | D38: 3363 | E38: 46044 | F38: GLAUCIA | G38: SILVANO | H38: 3530.14 | K38: 46042 | L38: 3628.56 | M38: =Tabela224657[[#This Row],[VENDA]]+Tabela224657[[#This Row],[MÃO DE OBRA]]-Tabela224657[[#This Row],[VALOR PAGO]] -> -98.42
B39: SMART | C39: 21277 | D39: 3361 | E39: 46044 | F39: SOARES | G39: MARCELO | I39: 116.8 | J39: 46072 | K39: 46055 | L39: 116.8 | M39: =Tabela224657[[#This Row],[VENDA]]+Tabela224657[[#This Row],[MÃO DE OBRA]]-Tabela224657[[#This Row],[VALOR PAGO]] -> 0
B40: SMART | C40: 21395 | D40: 3390 | E40: 46052 | F40: SOARES | G40: MARCELO | I40: 91.43 | J40: 46080 | K40: 46071 | L40: 91.42 | M40: =Tabela224657[[#This Row],[VENDA]]+Tabela224657[[#This Row],[MÃO DE OBRA]]-Tabela224657[[#This Row],[VALOR PAGO]] -> 0.01
B41: SMART | C41: 21395 | D41: 3390 | E41: 46052 | F41: SOARES | G41: MARCELO | I41: 91.43 | J41: 46087 | K41: 46071 | L41: 91.42 | M41: =Tabela224657[[#This Row],[VENDA]]+Tabela224657[[#This Row],[MÃO DE OBRA]]-Tabela224657[[#This Row],[VALOR PAGO]] -> 0.01
B42: SMART | C42: 21395 | D42: 3390 | E42: 46052 | F42: SOARES | G42: MARCELO | I42: 91.42 | J42: 46094 | K42: 46072 | L42: 91.43 | M42: =Tabela224657[[#This Row],[VENDA]]+Tabela224657[[#This Row],[MÃO DE OBRA]]-Tabela224657[[#This Row],[VALOR PAGO]] -> -0.01
B43: SMART | C43: 21396 | D43: 3389 | E43: 46052 | F43: SOARES | G43: MARCELO | I43: 2854.31 | J43: 46049 | K43: 46071 | L43: 2854.29 | M43: =Tabela224657[[#This Row],[VENDA]]+Tabela224657[[#This Row],[MÃO DE OBRA]]-Tabela224657[[#This Row],[VALOR PAGO]] -> 0.02
B44: SMART | C44: 21396 | D44: 3389 | E44: 46052 | F44: SOARES | G44: MARCELO | I44: 2854.31 | J44: 46087 | K44: 46071 | L44: 2854.29 | M44: =Tabela224657[[#This Row],[VENDA]]+Tabela224657[[#This Row],[MÃO DE OBRA]]-Tabela224657[[#This Row],[VALOR PAGO]] -> 0.02
B45: SMART | C45: 21396 | D45: 3389 | E45: 46052 | F45: SOARES | G45: MARCELO | I45: 2854.3 | J45: 46094 | K45: 46076 | L45: 2854.3 | M45: =Tabela224657[[#This Row],[VENDA]]+Tabela224657[[#This Row],[MÃO DE OBRA]]-Tabela224657[[#This Row],[VALOR PAGO]] -> 0
M46: =Tabela224657[[#This Row],[VENDA]]+Tabela224657[[#This Row],[MÃO DE OBRA]]-Tabela224657[[#This Row],[VALOR PAGO]] -> 0
M47: =Tabela224657[[#This Row],[VENDA]]+Tabela224657[[#This Row],[MÃO DE OBRA]]-Tabela224657[[#This Row],[VALOR PAGO]] -> 0
M48: =Tabela224657[[#This Row],[VENDA]]+Tabela224657[[#This Row],[MÃO DE OBRA]]-Tabela224657[[#This Row],[VALOR PAGO]] -> 0
M49: =Tabela224657[[#This Row],[VENDA]]+Tabela224657[[#This Row],[MÃO DE OBRA]]-Tabela224657[[#This Row],[VALOR PAGO]] -> 0
M50: =Tabela224657[[#This Row],[VENDA]]+Tabela224657[[#This Row],[MÃO DE OBRA]]-Tabela224657[[#This Row],[VALOR PAGO]] -> 0
M51: =Tabela224657[[#This Row],[VENDA]]+Tabela224657[[#This Row],[MÃO DE OBRA]]-Tabela224657[[#This Row],[VALOR PAGO]] -> 0
M52: =Tabela224657[[#This Row],[VENDA]]+Tabela224657[[#This Row],[MÃO DE OBRA]]-Tabela224657[[#This Row],[VALOR PAGO]] -> 0
C53: Total | H53: =SUM(H21:H52) -> 26211.472 | I53: =SUM(I21:I52) -> 24304.57 | L53: =SUM(L21:L52) -> 50993.16 | M53: =SUM(M21:M52) -> -477.118
B54: TOTAL VENDA: | D54: =Tabela224657[[#Totals],[VENDA]] -> 26211.472
B55: TOTAL MÃO DE OBRA: | D55: =Tabela224657[[#Totals],[MÃO DE OBRA]] -> 24304.57
B56: TOTAL: | C56: =SUM(D54+D55) -> 50516.042 | F56: TOTAL RECEBIDO: | H56: =Tabela224657[[#Totals],[VALOR PAGO]] -> 50993.16 | J56: TOTAL À RECEBER: | L56: =Tabela224657[[#Totals],[VALOR EM ABERTO]] -> -477.118

Sheet Fevereiro 2026
B2: FRETES
B4: MÊS | C4: SMART | H4: STK
C5: 2023 | D5: 2024 | E5: 2025 | F5: 2026 | G5: 2027 | H5: 2025 | I5: 2026 | J5: 2027 | K5: 2028 | L5: 2029 | M5: 2030
B6: JANEIRO | C6: 126073.37 | D6: 270562.53 | E6: 49887.66 | F6: 0 | G6: 0 | H6: 0 | I6: 0 | J6: 0 | K6: 0 | L6: 0 | M6: 0
B7: FEVEREIRO | C7: 166235.96 | D7: 324984.97 | E7: 15513.83 | F7: 0 | G7: 0 | H7: 0 | I7: 0 | J7: 0 | K7: 0 | L7: 0 | M7: 0
B8: MARÇO | C8: 119814.85 | D8: 256001.57 | E8: 32410.22 | F8: 0 | G8: 0 | H8: 0 | I8: 0 | J8: 0 | K8: 0 | L8: 0 | M8: 0
B9: ABRIL | C9: 112668.22 | D9: 136419.94 | E9: 23117.53 | F9: 0 | G9: 0 | H9: 0 | I9: 0 | J9: 0 | K9: 0 | L9: 0 | M9: 0
B10: MAIO | C10: 39597.94 | D10: 57014.4 | E10: 11710.4 | F10: 0 | G10: 0 | H10: 0 | I10: 0 | J10: 0 | K10: 0 | L10: 0 | M10: 0
B11: JUNHO | C11: 77419.24 | D11: 259261.92 | E11: 32986.86 | F11: 0 | G11: 0 | H11: 0 | I11: 0 | J11: 0 | K11: 0 | L11: 0 | M11: 0
B12: JULHO | C12: 74963.62 | D12: 191964.91 | E12: 8086.81 | F12: 0 | G12: 0 | H12: 0 | I12: 0 | J12: 0 | K12: 0 | L12: 0 | M12: 0
B13: AGOSTO | C13: 152485.66 | D13: 273158.85 | E13: 22122.22 | F13: 0 | G13: 0 | H13: 0 | I13: 0 | J13: 0 | K13: 0 | L13: 0 | M13: 0
B14: SETEMBRO | C14: 171282.48 | D14: 63159.51 | E14: 36466.42 | F14: 0 | G14: 0 | H14: 0 | I14: 0 | J14: 0 | K14: 0 | L14: 0 | M14: 0
B15: OUTUBRO | C15: 168433.06 | D15: 53077.38 | E15: 99828 | F15: 0 | G15: 0 | I15: 0 | J15: 0 | K15: 0 | L15: 0 | M15: 0
B16: NOVEMBRO | C16: 155757.68 | D16: 15517.44 | E16: 0 | F16: 0 | G16: 0 | H16: 0 | I16: 0 | J16: 0 | K16: 0 | L16: 0 | M16: 0
B17: DEZEMBRO | C17: 163379.08 | D17: 9580.01 | E17: 0 | F17: 0 | G17: 0 | H17: 0 | I17: 0 | J17: 0 | K17: 0 | L17: 0 | M17: 0
B18: TOTAL | C18: =SUM(C6:C17) -> 1528111.2 | D18: =SUM(D6:D17) -> 1910703.4 | E18: =SUM(E6:E17) -> 332129.95 | F18: =SUM(F6:F17) -> 0 | G18: 0 | H18: =SUM(H6:H17) -> 0 | I18: 0 | J18: =SUM(J6:J17) -> 0 | K18: 0 | L18: =SUM(L6:L17) -> 0 | M18: 0
B19: TOTAL CONSOLIDADO 2026: | D19: =SUM(I18+F18) -> 0
B20: EMPRESA | C20: NOTA FISCAL | D20: PEDIDO | E20: DATA DE EMISSÃO | F20: DESTINATÁRIO | G20: REPRESENTANTE | H20: VENDA | I20: MÃO DE OBRA | J20: VENCIMENTO | K20: DATA DE PAGAMENTO | L20: VALOR PAGO | M20: VALOR EM ABERTO | N20: Coluna1
B21: STK | C21: 21626 | D21: 3369 | E21: 46066 | F21: GLAUCIA | G21: SILVANO | H21: 2875.2 | J21: 46066 | K21: 46066 | L21: 2875.2 | M21: =Tabela2246578[[#This Row],[VENDA]]+Tabela2246578[[#This Row],[MÃO DE OBRA]]-Tabela2246578[[#This Row],[VALOR PAGO]] -> 0
B22: SMART | C22: 21440 | D22: 3389 | E22: 46056 | F22: SOARES | G22: MARCELO | I22: 119.35 | J22: 46084 | K22: 46071 | L22: 119.35 | M22: =Tabela2246578[[#This Row],[VENDA]]+Tabela2246578[[#This Row],[MÃO DE OBRA]]-Tabela2246578[[#This Row],[VALOR PAGO]] -> 0
B23: SMART | C23: 21440 | D23: 3389 | E23: 46056 | F23: SOARES | G23: MARCELO | I23: 119.35 | J23: 46091 | K23: 46071 | L23: 119.35 | M23: =Tabela2246578[[#This Row],[VENDA]]+Tabela2246578[[#This Row],[MÃO DE OBRA]]-Tabela2246578[[#This Row],[VALOR PAGO]] -> 0
B24: SMART | C24: 21440 | D24: 3389 | E24: 46056 | F24: SOARES | G24: MARCELO | I24: 119.35 | J24: 46098 | K24: 46076 | L24: 119.35 | M24: =Tabela2246578[[#This Row],[VENDA]]+Tabela2246578[[#This Row],[MÃO DE OBRA]]-Tabela2246578[[#This Row],[VALOR PAGO]] -> 0
B25: SMART | C25: 21521 | D25: 3522 | E25: 46059 | F25: SOARES | G25: MARCELO | I25: 134.55 | J25: 46087 | K25: 46071 | L25: 134.55 | M25: =Tabela2246578[[#This Row],[VENDA]]+Tabela2246578[[#This Row],[MÃO DE OBRA]]-Tabela2246578[[#This Row],[VALOR PAGO]] -> 0
B26: STK | C26: 662 | D26: 624 | E26: 46059 | F26: NHTEX | G26: DIRETO | H26: 1932 | J26: 46089 | K26: 46093 | L26: 1288.88 | M26: =Tabela2246578[[#This Row],[VENDA]]+Tabela2246578[[#This Row],[MÃO DE OBRA]]-Tabela2246578[[#This Row],[VALOR PAGO]] -> 643.12
B27: STK | C27: 662 | D27: 624 | E27: 46059 | F27: NHTEX | G27: DIRETO | H27: 1932 | J27: 46104 | K27: 46101 | L27: 2577.76 | M27: =Tabela2246578[[#This Row],[VENDA]]+Tabela2246578[[#This Row],[MÃO DE OBRA]]-Tabela2246578[[#This Row],[VALOR PAGO]] -> -645.76
B28: STK | C28: 21607 | D28: 3643 | E28: 46065 | F28: VIA BELLA | G28: MARCIANO | H28: 2666.77 | J28: 46095 | K28: 46097 | L28: 2666.77 | M28: =Tabela2246578[[#This Row],[VENDA]]+Tabela2246578[[#This Row],[MÃO DE OBRA]]-Tabela2246578[[#This Row],[VALOR PAGO]] -> 0
B29: STK | C29: 21607 | D29: 3643 | E29: 46065 | F29: VIA BELLA | G29: MARCIANO | H29: 2666.77 | J29: 46110 | K29: 46099 | L29: 2666.77 | M29: =Tabela2246578[[#This Row],[VENDA]]+Tabela2246578[[#This Row],[MÃO DE OBRA]]-Tabela2246578[[#This Row],[VALOR PAGO]] -> 0
B30: STK | C30: 21607 | D30: 3643 | E30: 46065 | F30: VIA BELLA | G30: MARCIANO | H30: 2666.77 | J30: 46125 | K30: 46099 | L30: 2661.79 | M30: =Tabela2246578[[#This Row],[VENDA]]+Tabela2246578[[#This Row],[MÃO DE OBRA]]-Tabela2246578[[#This Row],[VALOR PAGO]] -> 4.98
B31: SMART | C31: 21590 | D31: 3524 | E31: 46065 | F31: SOARES | G31: MARCELO | I31: 901.33 | J31: 46093 | K31: 46071 | L31: 901.32 | M31: =Tabela2246578[[#This Row],[VENDA]]+Tabela2246578[[#This Row],[MÃO DE OBRA]]-Tabela2246578[[#This Row],[VALOR PAGO]] -> 0.01
B32: SMART | C32: 21590 | D32: 3524 | E32: 46065 | F32: SOARES | G32: MARCELO | I32: 901.33 | J32: 46100 | K32: 46078 | L32: 901.32 | M32: =Tabela2246578[[#This Row],[VENDA]]+Tabela2246578[[#This Row],[MÃO DE OBRA]]-Tabela2246578[[#This Row],[VALOR PAGO]] -> 0.01
B33: SMART | C33: 21590 | D33: 3524 | E33: 46065 | F33: SOARES | G33: MARCELO | I33: 901.34 | J33: 46107 | K33: 46098 | L33: 901.31 | M33: =Tabela2246578[[#This Row],[VENDA]]+Tabela2246578[[#This Row],[MÃO DE OBRA]]-Tabela2246578[[#This Row],[VALOR PAGO]] -> 0.03
B34: SMART | C34: 21598 | D34: 3524 | E34: 46065 | F34: SOARES | G34: MARCELO | I34: 2295.41 | J34: 46093 | K34: 46072 | L34: 2295.39 | M34: =Tabela2246578[[#This Row],[VENDA]]+Tabela2246578[[#This Row],[MÃO DE OBRA]]-Tabela2246578[[#This Row],[VALOR PAGO]] -> 0.02
B35: SMART | C35: 21598 | D35: 3524 | E35: 46065 | F35: SOARES | G35: MARCELO | I35: 2295.41 | J35: 46100 | K35: 46078 | L35: 1737.7 | M35: =Tabela2246578[[#This Row],[VENDA]]+Tabela2246578[[#This Row],[MÃO DE OBRA]]-Tabela2246578[[#This Row],[VALOR PAGO]] -> 557.71
B36: SMART | C36: 21598 | D36: 3524 | E36: 46065 | F36: SOARES | G36: MARCELO | I36: 2295.4 | J36: 46107 | K36: 46098 | L36: 2853.09 | M36: =Tabela2246578[[#This Row],[VENDA]]+Tabela2246578[[#This Row],[MÃO DE OBRA]]-Tabela2246578[[#This Row],[VALOR PAGO]] -> -557.69
B37: SMART | C37: 21608 | D37: 3524 | E37: 46065 | F37: SOARES | G37: MARCELO | I37: 131.1 | J37: 46093 | K37: 46076 | L37: 131.1 | M37: =Tabela2246578[[#This Row],[VENDA]]+Tabela2246578[[#This Row],[MÃO DE OBRA]]-Tabela2246578[[#This Row],[VALOR PAGO]] -> 0
B38: SMART | C38: 21554 | D38: 3459 | E38: 46063 | F38: SOARES | G38: MARCELO | I38: 3026.8 | J38: 46091 | K38: 46071 | L38: 3026.8 | M38: =Tabela2246578[[#This Row],[VENDA]]+Tabela2246578[[#This Row],[MÃO DE OBRA]]-Tabela2246578[[#This Row],[VALOR PAGO]] -> 0
B39: SMART | C39: 21554 | D39: 3459 | E39: 46063 | F39: SOARES | G39: MARCELO | I39: 3026.8 | J39: 46098 | K39: 46078 | L39: 3026.8 | M39: =Tabela2246578[[#This Row],[VENDA]]+Tabela2246578[[#This Row],[MÃO DE OBRA]]-Tabela2246578[[#This Row],[VALOR PAGO]] -> 0
B40: SMART | C40: 21554 | D40: 3459 | E40: 46063 | F40: SOARES | G40: MARCELO | I40: 3026.81 | J40: 46105 | K40: 46098 | L40: 3026.79 | M40: =Tabela2246578[[#This Row],[VENDA]]+Tabela2246578[[#This Row],[MÃO DE OBRA]]-Tabela2246578[[#This Row],[VALOR PAGO]] -> 0.02
B41: SMART | C41: 21669 | D41: 3658 | E41: 46070 | F41: SOARES | G41: MARCELO | I41: 408.83 | J41: 46098 | K41: 46078 | L41: 408.82 | M41: =Tabela2246578[[#This Row],[VENDA]]+Tabela2246578[[#This Row],[MÃO DE OBRA]]-Tabela2246578[[#This Row],[VALOR PAGO]] -> 0.01
B42: SMART | C42: 21669 | D42: 3658 | E42: 46070 | F42: SOARES | G42: MARCELO | I42: 408.83 | J42: 46105 | K42: 46098 | L42: 408.82 | M42: =Tabela2246578[[#This Row],[VENDA]]+Tabela2246578[[#This Row],[MÃO DE OBRA]]-Tabela2246578[[#This Row],[VALOR PAGO]] -> 0.01
B43: SMART | C43: 21670 | D43: 3522 | E43: 46070 | F43: SOARES | G43: MARCELO | I43: 136.28 | J43: 46098 | K43: 46094 | L43: 136.27 | M43: =Tabela2246578[[#This Row],[VENDA]]+Tabela2246578[[#This Row],[MÃO DE OBRA]]-Tabela2246578[[#This Row],[VALOR PAGO]] -> 0.01
B44: SMART | C44: 21671 | D44: 3565 | E44: 46070 | F44: LC COMPONENTES | G44: MARCELO | I44: 568.8 | J44: 46105 | K44: 46105 | L44: 568.8 | M44: 0
B45: SMART | C45: 21673 | D45: 3560 | E45: 46070 | F45: LC COMPONENTES | G45: MARCELO | I45: 1404.23 | J45: 46105 | K45: 46105 | L45: 1404.23 | M45: =Tabela2246578[[#This Row],[VENDA]]+Tabela2246578[[#This Row],[MÃO DE OBRA]]-Tabela2246578[[#This Row],[VALOR PAGO]] -> 0
B46: STK | C46: 21723 | D46: 3637 | E46: 46072 | F46: GLAUCIA | G46: SILVANO | H46: 2809.31 | J46: 46093 | K46: 46129 | L46: 2809.31 | M46: =Tabela2246578[[#This Row],[VENDA]]+Tabela2246578[[#This Row],[MÃO DE OBRA]]-Tabela2246578[[#This Row],[VALOR PAGO]] -> 0
B47: SMART | C47: 21746 | D47: 3524 | E47: 46073 | F47: SOARES | G47: MARCELO | I47: 369.73 | J47: 46101 | K47: 46094 | L47: 369.72 | M47: =Tabela2246578[[#This Row],[VENDA]]+Tabela2246578[[#This Row],[MÃO DE OBRA]]-Tabela2246578[[#This Row],[VALOR PAGO]] -> 0.01
B48: SMART | C48: 21746 | D48: 3524 | E48: 46073 | F48: SOARES | G48: MARCELO | I48: 369.73 | J48: 46108 | K48: 46105 | L48: 369.72 | M48: =Tabela2246578[[#This Row],[VENDA]]+Tabela2246578[[#This Row],[MÃO DE OBRA]]-Tabela2246578[[#This Row],[VALOR PAGO]] -> 0.01
B49: SMART | C49: 21746 | D49: 3524 | E49: 46073 | F49: SOARES | G49: MARCELO | I49: 369.72 | J49: 46115 | K49: 46108 | L49: 369.73 | M49: =Tabela2246578[[#This Row],[VENDA]]+Tabela2246578[[#This Row],[MÃO DE OBRA]]-Tabela2246578[[#This Row],[VALOR PAGO]] -> -0.01
B50: SMART | C50: 21747 | D50: 3697 | E50: 46073 | F50: SOARES | G50: MARCELO | I50: 439.88 | J50: 46101 | K50: 46094 | L50: 439.87 | M50: =Tabela2246578[[#This Row],[VENDA]]+Tabela2246578[[#This Row],[MÃO DE OBRA]]-Tabela2246578[[#This Row],[VALOR PAGO]] -> 0.01
B51: SMART | C51: 21747 | D51: 3697 | E51: 46073 | F51: SOARES | G51: MARCELO | I51: 439.88 | J51: 46108 | K51: 46105 | L51: 439.87 | M51: =Tabela2246578[[#This Row],[VENDA]]+Tabela2246578[[#This Row],[MÃO DE OBRA]]-Tabela2246578[[#This Row],[VALOR PAGO]] -> 0.01
B52: SMART | C52: 21747 | D52: 3697 | E52: 46073 | F52: SOARES | G52: MARCELO | I52: 439.87 | J52: 46115 | K52: 46105 | L52: 439.88 | M52: =Tabela2246578[[#This Row],[VENDA]]+Tabela2246578[[#This Row],[MÃO DE OBRA]]-Tabela2246578[[#This Row],[VALOR PAGO]] -> -0.01
B53: SMART | C53: 21753 | D53: 3697 | E53: 46073 | F53: SOARES | G53: MARCELO | I53: 226.55 | J53: 46101 | K53: 46094 | L53: 226.55 | M53: =Tabela2246578[[#This Row],[VENDA]]+Tabela2246578[[#This Row],[MÃO DE OBRA]]-Tabela2246578[[#This Row],[VALOR PAGO]] -> 0
B54: SMART | C54: 21753 | D54: 3697 | E54: 46073 | F54: SOARES | G54: MARCELO | I54: 226.55 | J54: 46108 | K54: 46105 | L54: 226.55 | M54: =Tabela2246578[[#This Row],[VENDA]]+Tabela2246578[[#This Row],[MÃO DE OBRA]]-Tabela2246578[[#This Row],[VALOR PAGO]] -> 0
B55: SMART | C55: 21753 | D55: 3697 | E55: 46073 | F55: SOARES | G55: MARCELO | I55: 226.55 | J55: 46115 | K55: 46106 | L55: 226.55 | M55: =Tabela2246578[[#This Row],[VENDA]]+Tabela2246578[[#This Row],[MÃO DE OBRA]]-Tabela2246578[[#This Row],[VALOR PAGO]] -> 0
B56: SMART | C56: 21758 | D56: 3700 | E56: 46076 | F56: SOARES | G56: MARCELO | I56: 265.66 | J56: 46104 | K56: 46098 | L56: 265.64 | M56: =Tabela2246578[[#This Row],[VENDA]]+Tabela2246578[[#This Row],[MÃO DE OBRA]]-Tabela2246578[[#This Row],[VALOR PAGO]] -> 0.02
B57: SMART | C57: 21759 | D57: 3697 | E57: 46076 | F57: SOARES | G57: MARCELO | I57: 410.55 | J57: 46104 | K57: 46098 | L57: 410.55 | M57: =Tabela2246578[[#This Row],[VENDA]]+Tabela2246578[[#This Row],[MÃO DE OBRA]]-Tabela2246578[[#This Row],[VALOR PAGO]] -> 0
B58: STK | C58: 21795 | D58: 3804 | E58: 46077 | F58: VIA BELLA | G58: MARCIANO | H58: 1753.2 | J58: 46107 | K58: 46097 | L58: 1753.2 | M58: =Tabela2246578[[#This Row],[VENDA]]+Tabela2246578[[#This Row],[MÃO DE OBRA]]-Tabela2246578[[#This Row],[VALOR PAGO]] -> 0
B59: SMART | C59: 21416 | D59: Sem pedido | E59: 46055 | F59: VIASCARPA | G59: MARCELO | I59: =475*12.6 -> 5985 | J59: - | K59: Acerto | M59: =Tabela2246578[[#This Row],[VENDA]]+Tabela2246578[[#This Row],[MÃO DE OBRA]]-Tabela2246578[[#This Row],[VALOR PAGO]] -> 5985 | N59: Benef em cima de Napa Like Aveia que veio errado via Importação. Transformado em Napa Metal Lyon O. Light
B60: SMART | C60: 21636 | D60: Sem pedido | E60: 46069 | F60: VIASCARPA | G60: MARCELO | I60: =636*12.6 -> 8013.6 | J60: - | K60: Acerto | M60: =Tabela2246578[[#This Row],[VENDA]]+Tabela2246578[[#This Row],[MÃO DE OBRA]]-Tabela2246578[[#This Row],[VALOR PAGO]] -> 8013.6 | N60: Benef em cima de Napa Like Aveia que veio errado via Importação. Transformado em Napa Metal Lyon O. Light
B61: STK | C61: 21853 | D61: 3714 | E61: 46079 | F61: GLAUCIA | G61: SILVANO | H61: 2899.16 | J61: 46093 | K61: 46129 | L61: =2190.69+708.47 -> 2899.16 | M61: =Tabela2246578[[#This Row],[VENDA]]-Tabela2246578[[#This Row],[VALOR PAGO]] -> 0
B62: STK | C62: 21883 | D62: 3868 | E62: 46080 | F62: NOSSA SRA DE FAT | G62: MARCIANO | H62: 1417.95 | J62: 46125 | K62: 46080 | L62: 1417.95 | M62: =Tabela2246578[[#This Row],[VENDA]]+Tabela2246578[[#This Row],[MÃO DE OBRA]]-Tabela2246578[[#This Row],[VALOR PAGO]] -> 0
B63: SMART | C63: 21888 | D63: 3795 | E63: 46080 | F63: SOARES | G63: MARCELO | I63: 588.8 | J63: 46108 | K63: 46105 | L63: 588.8 | M63: =Tabela2246578[[#This Row],[VENDA]]+Tabela2246578[[#This Row],[MÃO DE OBRA]]-Tabela2246578[[#This Row],[VALOR PAGO]] -> 0
B64: SMART | C64: 21888 | D64: 3795 | E64: 46080 | F64: SOARES | G64: MARCELO | I64: 588.8 | J64: 46115 | K64: 46108 | L64: 588.79 | M64: =Tabela2246578[[#This Row],[VENDA]]+Tabela2246578[[#This Row],[MÃO DE OBRA]]-Tabela2246578[[#This Row],[VALOR PAGO]] -> 0.01
B65: SMART | C65: 21888 | D65: 3795 | E65: 46080 | F65: SOARES | G65: MARCELO | I65: 588.81 | J65: 46122 | K65: 46108 | L65: 588.8 | M65: =Tabela2246578[[#This Row],[VENDA]]+Tabela2246578[[#This Row],[MÃO DE OBRA]]-Tabela2246578[[#This Row],[VALOR PAGO]] -> 0.01
M66: =Tabela2246578[[#This Row],[VENDA]]+Tabela2246578[[#This Row],[MÃO DE OBRA]]-Tabela2246578[[#This Row],[VALOR PAGO]] -> 0
C67: Total | H67: =SUM(H21:H66) -> 23619.13 | I67: =SUM(I21:I66) -> 41770.98 | L67: =SUM(L21:L66) -> 51388.97 | M67: =SUM(M21:M66) -> 14001.14
B68: TOTAL VENDA: | D68: =Tabela2246578[[#Totals],[VENDA]] -> 23619.13
B69: TOTAL MÃO DE OBRA: | D69: =Tabela2246578[[#Totals],[MÃO DE OBRA]] -> 41770.98
B70: TOTAL: | C70: =SUM(D68+D69) -> 65390.11 | F70: TOTAL RECEBIDO: | H70: =Tabela2246578[[#Totals],[VALOR PAGO]] -> 51388.97 | J70: TOTAL À RECEBER: | L70: =Tabela2246578[[#Totals],[VALOR EM ABERTO]] -> 14001.14
K73: Dep Glaucia 17/04 | L73: 5000
L74: 2809.31
L75: 2190.69
L76: =L73-L74-L75 -> 0
K77: Dep Glaucia 23/04 | L77: 2000
L78: 708.47
L79: =L77-L78 -> 1291.53

Sheet Março 2026
B2: FRETES
B4: MÊS | C4: SMART | H4: STK
C5: 2023 | D5: 2024 | E5: 2025 | F5: 2026 | G5: 2027 | H5: 2025 | I5: 2026 | J5: 2027 | K5: 2028 | L5: 2029 | M5: 2030
B6: JANEIRO | C6: 126073.37 | D6: 270562.53 | E6: 49887.66 | F6: 0 | G6: 0 | H6: 0 | I6: 0 | J6: 0 | K6: 0 | L6: 0 | M6: 0
B7: FEVEREIRO | C7: 166235.96 | D7: 324984.97 | E7: 15513.83 | F7: 0 | G7: 0 | H7: 0 | I7: 0 | J7: 0 | K7: 0 | L7: 0 | M7: 0
B8: MARÇO | C8: 119814.85 | D8: 256001.57 | E8: 32410.22 | F8: 0 | G8: 0 | H8: 0 | I8: 0 | J8: 0 | K8: 0 | L8: 0 | M8: 0
B9: ABRIL | C9: 112668.22 | D9: 136419.94 | E9: 23117.53 | F9: 0 | G9: 0 | H9: 0 | I9: 0 | J9: 0 | K9: 0 | L9: 0 | M9: 0
B10: MAIO | C10: 39597.94 | D10: 57014.4 | E10: 11710.4 | F10: 0 | G10: 0 | H10: 0 | I10: 0 | J10: 0 | K10: 0 | L10: 0 | M10: 0
B11: JUNHO | C11: 77419.24 | D11: 259261.92 | E11: 32986.86 | F11: 0 | G11: 0 | H11: 0 | I11: 0 | J11: 0 | K11: 0 | L11: 0 | M11: 0
B12: JULHO | C12: 74963.62 | D12: 191964.91 | E12: 8086.81 | F12: 0 | G12: 0 | H12: 0 | I12: 0 | J12: 0 | K12: 0 | L12: 0 | M12: 0
B13: AGOSTO | C13: 152485.66 | D13: 273158.85 | E13: 22122.22 | F13: 0 | G13: 0 | H13: 0 | I13: 0 | J13: 0 | K13: 0 | L13: 0 | M13: 0
B14: SETEMBRO | C14: 171282.48 | D14: 63159.51 | E14: 36466.42 | F14: 0 | G14: 0 | H14: 0 | I14: 0 | J14: 0 | K14: 0 | L14: 0 | M14: 0
B15: OUTUBRO | C15: 168433.06 | D15: 53077.38 | E15: 99828 | F15: 0 | G15: 0 | I15: 0 | J15: 0 | K15: 0 | L15: 0 | M15: 0
B16: NOVEMBRO | C16: 155757.68 | D16: 15517.44 | E16: 0 | F16: 0 | G16: 0 | H16: 0 | I16: 0 | J16: 0 | K16: 0 | L16: 0 | M16: 0
B17: DEZEMBRO | C17: 163379.08 | D17: 9580.01 | E17: 0 | F17: 0 | G17: 0 | H17: 0 | I17: 0 | J17: 0 | K17: 0 | L17: 0 | M17: 0
B18: TOTAL | C18: =SUM(C6:C17) -> 1528111.2 | D18: =SUM(D6:D17) -> 1910703.4 | E18: =SUM(E6:E17) -> 332129.95 | F18: =SUM(F6:F17) -> 0 | G18: 0 | H18: =SUM(H6:H17) -> 0 | I18: 0 | J18: =SUM(J6:J17) -> 0 | K18: 0 | L18: =SUM(L6:L17) -> 0 | M18: 0
B19: TOTAL CONSOLIDADO 2026: | D19: =SUM(I18+F18) -> 0
B20: EMPRESA | C20: NOTA FISCAL | D20: PEDIDO | E20: DATA DE EMISSÃO | F20: DESTINATÁRIO | G20: REPRESENTANTE | H20: VENDA | I20: MÃO DE OBRA | J20: VENCIMENTO | K20: DATA DE PAGAMENTO | L20: VALOR PAGO | M20: VALOR EM ABERTO | N20: Coluna1
B21: SMART | C21: 21939 | D21: 3842 | E21: 46084 | F21: SOARES | G21: MARCELO | I21: 504.85 | J21: 46112 | K21: 46105 | L21: 504.85 | M21: =Tabela22465789[[#This Row],[VENDA]]+Tabela22465789[[#This Row],[MÃO DE OBRA]]-Tabela22465789[[#This Row],[VALOR PAGO]] -> 0
B22: SMART | C22: 21939 | D22: 3842 | E22: 46084 | F22: SOARES | G22: MARCELO | I22: 504.85 | J22: 46119 | K22: 46108 | L22: 504.85 | M22: =Tabela22465789[[#This Row],[VENDA]]+Tabela22465789[[#This Row],[MÃO DE OBRA]]-Tabela22465789[[#This Row],[VALOR PAGO]] -> 0
B23: SMART | C23: 21939 | D23: 3842 | E23: 46084 | F23: SOARES | G23: MARCELO | I23: 504.86 | J23: 46126 | K23: 46108 | L23: 504.84 | M23: =Tabela22465789[[#This Row],[VENDA]]+Tabela22465789[[#This Row],[MÃO DE OBRA]]-Tabela22465789[[#This Row],[VALOR PAGO]] -> 0.02
B24: STK | C24: 21938 | D24: 3818 | E24: 46084 | F24: GLAUCIA | G24: SILVANO | H24: 9515.57 | J24: 46114 | K24: 46164 | L24: =1291.53+8224.04 -> 9515.57 | M24: =Tabela22465789[[#This Row],[VENDA]]+Tabela22465789[[#This Row],[MÃO DE OBRA]]-Tabela22465789[[#This Row],[VALOR PAGO]] -> 0 | N24: Pagou 1.291,53 dia 23/04 e saldo dia 22/05
B25: STK | C25: 21938 | D25: 3818 | E25: 46084 | F25: GLAUCIA | G25: SILVANO | H25: 9515.56 | J25: 46144 | K25: 46164 | L25: =(9000-8224.04)+5000 -> 5775.96 | M25: =Tabela22465789[[#This Row],[VENDA]]+Tabela22465789[[#This Row],[MÃO DE OBRA]]-Tabela22465789[[#This Row],[VALOR PAGO]] -> 3739.6 | N25: Saldo de 9000,00 depositado dia 22/05 foi abatido nessa duplicata
B26: SMART | C26: 22025 | D26: 3907 | E26: 46084 | F26: LC COMPONENTES | G26: MARCELO | I26: 686.12 | J26: 46125 | K26: 46125 | L26: 686.12 | M26: =Tabela22465789[[#This Row],[VENDA]]+Tabela22465789[[#This Row],[MÃO DE OBRA]]-Tabela22465789[[#This Row],[VALOR PAGO]] -> 0
B27: STK | C27: 755 | D27: 707 | E27: 46091 | F27: Rosa D'alva | G27: HENRIQUE | H27: =1800*14.4 -> 25920 | J27: A VISTA | K27: 46090 | L27: 25920 | M27: =Tabela22465789[[#This Row],[VENDA]]+Tabela22465789[[#This Row],[MÃO DE OBRA]]-Tabela22465789[[#This Row],[VALOR PAGO]] -> 0
B28: STK | C28: 22053 | D28: 3959 | E28: 46091 | F28: REI COLAS | G28: FERNANDO | H28: 2268 | J28: 46105 | K28: 46105 | L28: 2268 | M28: =Tabela22465789[[#This Row],[VENDA]]+Tabela22465789[[#This Row],[MÃO DE OBRA]]-Tabela22465789[[#This Row],[VALOR PAGO]] -> 0
B29: STK | C29: 22053 | D29: 3959 | E29: 46091 | F29: REI COLAS | G29: FERNANDO | H29: 2268 | J29: 46112 | K29: 46112 | L29: 2268 | M29: =Tabela22465789[[#This Row],[VENDA]]+Tabela22465789[[#This Row],[MÃO DE OBRA]]-Tabela22465789[[#This Row],[VALOR PAGO]] -> 0
B30: STK | C30: 22053 | D30: 3959 | E30: 46091 | F30: REI COLAS | G30: FERNANDO | H30: 2268 | J30: 46119 | K30: 46129 | L30: 2268 | M30: =Tabela22465789[[#This Row],[VENDA]]+Tabela22465789[[#This Row],[MÃO DE OBRA]]-Tabela22465789[[#This Row],[VALOR PAGO]] -> 0
B31: STK | C31: 22053 | D31: 3959 | E31: 46091 | F31: REI COLAS | G31: FERNANDO | H31: 2268 | J31: 46133 | K31: 46134 | L31: 2268 | M31: =Tabela22465789[[#This Row],[VENDA]]+Tabela22465789[[#This Row],[MÃO DE OBRA]]-Tabela22465789[[#This Row],[VALOR PAGO]] -> 0
B32: STK | C32: 22053 | D32: 3959 | E32: 46091 | F32: REI COLAS | G32: FERNANDO | H32: 2268 | J32: 46140 | K32: 46140 | L32: 2268 | M32: =Tabela22465789[[#This Row],[VENDA]]+Tabela22465789[[#This Row],[MÃO DE OBRA]]-Tabela22465789[[#This Row],[VALOR PAGO]] -> 0
B33: STK | C33: 22053 | D33: 3959 | E33: 46091 | F33: REI COLAS | G33: FERNANDO | H33: 2268 | J33: 46147 | K33: 46147 | L33: 2268 | M33: =Tabela22465789[[#This Row],[VENDA]]+Tabela22465789[[#This Row],[MÃO DE OBRA]]-Tabela22465789[[#This Row],[VALOR PAGO]] -> 0
B34: STK | C34: 22064 | D34: 3961 | E34: 46091 | F34: NOSSA SRA DE FAT | G34: MARCIANO | H34: 662.4 | J34: 46136 | K34: 46163 | L34: 662.4 | M34: =Tabela22465789[[#This Row],[VENDA]]+Tabela22465789[[#This Row],[MÃO DE OBRA]]-Tabela22465789[[#This Row],[VALOR PAGO]] -> 0
C35: 22072 | E35: 46092 | F35: P&G | H35: 594.3 | J35: 46092 | K35: 46092 | L35: 594.3 | M35: =Tabela22465789[[#This Row],[VENDA]]+Tabela22465789[[#This Row],[MÃO DE OBRA]]-Tabela22465789[[#This Row],[VALOR PAGO]] -> 0
B36: STK | C36: 22115 | D36: 4018 | E36: 46093 | F36: VIA BELLA | G36: MARCIANO | H36: 3098.62 | J36: 46114 | K36: 46132 | L36: 3098.62 | M36: =Tabela22465789[[#This Row],[VENDA]]+Tabela22465789[[#This Row],[MÃO DE OBRA]]-Tabela22465789[[#This Row],[VALOR PAGO]] -> 0
B37: STK | C37: 759 | D37: 709 | E37: 46092 | F37: YPORA | G37: MARCIANO | H37: 8785 | J37: 46113 | K37: 46122 | L37: 8785 | M37: =Tabela22465789[[#This Row],[VENDA]]+Tabela22465789[[#This Row],[MÃO DE OBRA]]-Tabela22465789[[#This Row],[VALOR PAGO]] -> 0
B38: STK | C38: 759 | D38: 709 | E38: 46092 | F38: YPORA | G38: MARCIANO | H38: 8783 | J38: 46120 | K38: 46150 | L38: 8783 | M38: =Tabela22465789[[#This Row],[VENDA]]+Tabela22465789[[#This Row],[MÃO DE OBRA]]-Tabela22465789[[#This Row],[VALOR PAGO]] -> 0
B39: STK | C39: 759 | D39: 709 | E39: 46092 | F39: YPORA | G39: MARCIANO | H39: 8783 | J39: 46127 | K39: 46160 | L39: 8783 | M39: =Tabela22465789[[#This Row],[VENDA]]+Tabela22465789[[#This Row],[MÃO DE OBRA]]-Tabela22465789[[#This Row],[VALOR PAGO]] -> 0
B40: STK | C40: 759 | D40: 709 | E40: 46092 | F40: YPORA | G40: MARCIANO | H40: 8783 | J40: 46134 | K40: 46176 | L40: 8783 | M40: =Tabela22465789[[#This Row],[VENDA]]+Tabela22465789[[#This Row],[MÃO DE OBRA]]-Tabela22465789[[#This Row],[VALOR PAGO]] -> 0
B41: STK | C41: 759 | D41: 709 | E41: 46092 | F41: YPORA | G41: MARCIANO | H41: 8783 | J41: 46141 | K41: 46176 | L41: 8783 | M41: =Tabela22465789[[#This Row],[VENDA]]+Tabela22465789[[#This Row],[MÃO DE OBRA]]-Tabela22465789[[#This Row],[VALOR PAGO]] -> 0
B42: STK | C42: 759 | D42: 709 | E42: 46092 | F42: YPORA | G42: MARCIANO | H42: 8783 | J42: 46148 | K42: 46189 | L42: 8783 | M42: =Tabela22465789[[#This Row],[VENDA]]+Tabela22465789[[#This Row],[MÃO DE OBRA]]-Tabela22465789[[#This Row],[VALOR PAGO]] -> 0
B43: STK | C43: 760 | D43: 711 | E43: 46092 | F43: SANTOS | G43: MARCIANO | H43: 6100 | J43: 46113 | K43: 46150 | L43: 6100 | M43: =Tabela22465789[[#This Row],[VENDA]]+Tabela22465789[[#This Row],[MÃO DE OBRA]]-Tabela22465789[[#This Row],[VALOR PAGO]] -> 0
B44: STK | C44: 760 | D44: 711 | E44: 46092 | F44: SANTOS | G44: MARCIANO | H44: 6096 | J44: 46120 | K44: 46150 | L44: 6096 | M44: =Tabela22465789[[#This Row],[VENDA]]+Tabela22465789[[#This Row],[MÃO DE OBRA]]-Tabela22465789[[#This Row],[VALOR PAGO]] -> 0
B45: STK | C45: 760 | D45: 711 | E45: 46092 | F45: SANTOS | G45: MARCIANO | H45: 6096 | J45: 46127 | K45: 46160 | L45: 6096 | M45: =Tabela22465789[[#This Row],[VENDA]]+Tabela22465789[[#This Row],[MÃO DE OBRA]]-Tabela22465789[[#This Row],[VALOR PAGO]] -> 0
B46: STK | C46: 760 | D46: 711 | E46: 46092 | F46: SANTOS | G46: MARCIANO | H46: 6096 | J46: 46134 | K46: 46160 | L46: 6096.01 | M46: =Tabela22465789[[#This Row],[VENDA]]+Tabela22465789[[#This Row],[MÃO DE OBRA]]-Tabela22465789[[#This Row],[VALOR PAGO]] -> -0.01
B47: STK | C47: 760 | D47: 711 | E47: 46092 | F47: SANTOS | G47: MARCIANO | H47: 6096 | J47: 46141 | K47: 46176 | L47: 6096 | M47: =Tabela22465789[[#This Row],[VENDA]]+Tabela22465789[[#This Row],[MÃO DE OBRA]]-Tabela22465789[[#This Row],[VALOR PAGO]] -> 0
... B60: STK | C60: 762 | D60: 713 | E60: 46092 | F60: FELIPE NANUQUE | G60: MARCIANO | H60: 7762 | J60: 46148 | K60: 46190 | L60: 7762 | M60: =Tabela22465789[[#This Row],[VENDA]]+Tabela22465789[[#This Row],[MÃO DE OBRA]]-Tabela22465789[[#This Row],[VALOR PAGO]] -> 0
B61: SMART | C61: 22138 | D61: 4017 | E61: 46094 | F61: SOARES | G61: MARCELO | I61: 411.93 | J61: 46122 | K61: 46108 | L61: 411.93 | M61: =Tabela22465789[[#This Row],[VENDA]]+Tabela22465789[[#This Row],[MÃO DE OBRA]]-Tabela22465789[[#This Row],[VALOR PAGO]] -> 0
B62: SMART | C62: 22138 | D62: 4017 | E62: 46094 | F62: SOARES | G62: MARCELO | I62: 411.93 | J62: 46129 | K62: 46108 | L62: 411.93 | M62: =Tabela22465789[[#This Row],[VENDA]]+Tabela22465789[[#This Row],[MÃO DE OBRA]]-Tabela22465789[[#This Row],[VALOR PAGO]] -> 0
B63: SMART | C63: 22140 | D63: 3949 | E63: 46094 | F63: SOARES | G63: MARCELO | I63: 686.78 | J63: 46122 | K63: 46108 | L63: 686.78 | M63: =Tabela22465789[[#This Row],[VENDA]]+Tabela22465789[[#This Row],[MÃO DE OBRA]]-Tabela22465789[[#This Row],[VALOR PAGO]] -> 0
B64: SMART | C64: 22140 | D64: 3949 | E64: 46094 | F64: SOARES | G64: MARCELO | I64: 686.78 | J64: 46129 | K64: 46108 | L64: 686.78 | M64: =Tabela22465789[[#This Row],[VENDA]]+Tabela22465789[[#This Row],[MÃO DE OBRA]]-Tabela22465789[[#This Row],[VALOR PAGO]] -> 0
B65: SMART | C65: 22140 | D65: 3949 | E65: 46094 | F65: SOARES | G65: MARCELO | I65: 686.77 | J65: 46136 | K65: 46136 | L65: 686.79 | M65: =Tabela22465789[[#This Row],[VENDA]]+Tabela22465789[[#This Row],[MÃO DE OBRA]]-Tabela22465789[[#This Row],[VALOR PAGO]] -> -0.02
B66: STK | C66: 775 | D66: 730 | E66: 46097 | F66: MARIOTTA | G66: HENRIQUE | H66: 12866.4 | J66: 46111 | K66: 46111 | L66: 12866.4 | M66: =Tabela22465789[[#This Row],[VENDA]]+Tabela22465789[[#This Row],[MÃO DE OBRA]]-Tabela22465789[[#This Row],[VALOR PAGO]] -> 0
B67: STK | C67: 22158 | D67: 4059 | E67: 46097 | F67: NHTEX | G67: HENRIQUE | H67: 1113 | J67: 46127 | K67: 46127 | L67: 1113 | M67: =Tabela22465789[[#This Row],[VENDA]]+Tabela22465789[[#This Row],[MÃO DE OBRA]]-Tabela22465789[[#This Row],[VALOR PAGO]] -> 0
B68: STK | C68: 22158 | D68: 4059 | E68: 46097 | F68: NHTEX | G68: HENRIQUE | H68: 1113 | J68: 46142 | K68: 46142 | L68: 1113 | M68: =Tabela22465789[[#This Row],[VENDA]]+Tabela22465789[[#This Row],[MÃO DE OBRA]]-Tabela22465789[[#This Row],[VALOR PAGO]] -> 0
B69: STK | C69: 22158 | D69: 4059 | E69: 46097 | F69: NHTEX | G69: HENRIQUE | H69: 1124.13 | J69: 46157 | K69: 46157 | L69: 1113 | M69: =Tabela22465789[[#This Row],[VENDA]]+Tabela22465789[[#This Row],[MÃO DE OBRA]]-Tabela22465789[[#This Row],[VALOR PAGO]] -> 11.13
C70: 22157 | E70: 46097 | F70: MATOS IND | G70: HENRIQUE | H70: =8281.75 -> 8281.75 | J70: 46127 | K70: 46134 | L70: 8281.75 | M70: =Tabela22465789[[#This Row],[VENDA]]+Tabela22465789[[#This Row],[MÃO DE OBRA]]-Tabela22465789[[#This Row],[VALOR PAGO]] -> 0
C71: 22157 | E71: 46097 | F71: MATOS IND | G71: HENRIQUE | H71: =H70 -> 8281.75 | J71: 46146 | K71: 46155 | L71: 8281.75 | M71: =Tabela22465789[[#This Row],[VENDA]]+Tabela22465789[[#This Row],[MÃO DE OBRA]]-Tabela22465789[[#This Row],[VALOR PAGO]] -> 0
B72: S/ COMISSÃO | C72: 22157 | E72: 46097 | F72: MATOS IND | G72: HENRIQUE | H72: =H71 -> 8281.75 | J72: 46160 | K72: 46160 | L72: 8281.75 | M72: =Tabela22465789[[#This Row],[VENDA]]+Tabela22465789[[#This Row],[MÃO DE OBRA]]-Tabela22465789[[#This Row],[VALOR PAGO]] -> 0
C73: 22157 | E73: 46097 | F73: MATOS IND | G73: HENRIQUE | H73: =H72 -> 8281.75 | J73: 46178 | K73: 46178 | L73: 8281.75 | M73: =Tabela22465789[[#This Row],[VENDA]]+Tabela22465789[[#This Row],[MÃO DE OBRA]]-Tabela22465789[[#This Row],[VALOR PAGO]] -> 0
B74: SMART | C74: 22262 | D74: 4040 | E74: 46101 | F74: LC COMPONENTES | G74: MARCELO | I74: =714*8.91 -> 6361.74 | J74: 46122 | K74: 46122 | L74: 6361.74 | M74: =Tabela22465789[[#This Row],[VENDA]]+Tabela22465789[[#This Row],[MÃO DE OBRA]]-Tabela22465789[[#This Row],[VALOR PAGO]] -> 0
B75: STK | C75: 22243 | D75: 3370 | E75: 46101 | F75: GLAUCIA | G75: SILVANO | H75: 1025.48 | J75: 46115 | M75: =Tabela22465789[[#This Row],[VENDA]]+Tabela22465789[[#This Row],[MÃO DE OBRA]]-Tabela22465789[[#This Row],[VALOR PAGO]] -> 1025.48
B76: STK | C76: 22243 | D76: 3370 | E76: 46101 | F76: GLAUCIA | G76: SILVANO | H76: 1025.48 | J76: 46122 | M76: =Tabela22465789[[#This Row],[VENDA]]+Tabela22465789[[#This Row],[MÃO DE OBRA]]-Tabela22465789[[#This Row],[VALOR PAGO]] -> 1025.48
B77: STK | C77: 22243 | D77: 3370 | E77: 46101 | F77: GLAUCIA | G77: SILVANO | H77: 1025.48 | J77: 46129 | M77: =Tabela22465789[[#This Row],[VENDA]]+Tabela22465789[[#This Row],[MÃO DE OBRA]]-Tabela22465789[[#This Row],[VALOR PAGO]] -> 1025.48
B78: STK | C78: 22243 | D78: 3370 | E78: 46101 | F78: GLAUCIA | G78: SILVANO | H78: 1025.48 | J78: 46136 | M78: =Tabela22465789[[#This Row],[VENDA]]+Tabela22465789[[#This Row],[MÃO DE OBRA]]-Tabela22465789[[#This Row],[VALOR PAGO]] -> 1025.48
B79: STK | C79: 22243 | D79: 3370 | E79: 46101 | F79: GLAUCIA | G79: SILVANO | H79: 1025.48 | J79: 46143 | M79: =Tabela22465789[[#This Row],[VENDA]]+Tabela22465789[[#This Row],[MÃO DE OBRA]]-Tabela22465789[[#This Row],[VALOR PAGO]] -> 1025.48
B80: STK | C80: 22263 | D80: 4018 | E80: 46101 | F80: VIA BELLA | G80: MARCIANO | H80: 2214.82 | J80: 46131 | K80: 46132 | L80: 2214.82 | M80: =Tabela22465789[[#This Row],[VENDA]]+Tabela22465789[[#This Row],[MÃO DE OBRA]]-Tabela22465789[[#This Row],[VALOR PAGO]] -> 0
B81: STK | C81: 22263 | D81: 4018 | E81: 46101 | F81: VIA BELLA | G81: MARCIANO | H81: 2214.81 | J81: 46146 | K81: 46132 | L81: 2247.59 | M81: =Tabela22465789[[#This Row],[VENDA]]+Tabela22465789[[#This Row],[MÃO DE OBRA]]-Tabela22465789[[#This Row],[VALOR PAGO]] -> -32.78
B82: SMART | C82: 22292 | D82: 4042 | E82: 46104 | F82: LC COMPONENTES | G82: MARCELO | I82: 694.98 | J82: 46125 | K82: 46125 | L82: 694.98 | M82: =Tabela22465789[[#This Row],[VENDA]]+Tabela22465789[[#This Row],[MÃO DE OBRA]]-Tabela22465789[[#This Row],[VALOR PAGO]] -> 0
B83: SMART | C83: 22293 | D83: 4043 | E83: 46104 | F83: SOARES | G83: MARCELO | I83: 138 | J83: 46132 | K83: 46136 | L83: 138 | M83: =Tabela22465789[[#This Row],[VENDA]]+Tabela22465789[[#This Row],[MÃO DE OBRA]]-Tabela22465789[[#This Row],[VALOR PAGO]] -> 0
B84: SMART | C84: 22311 | D84: 4095 | E84: 46105 | F84: SOARES | G84: MARCELO | I84: 1128.49 | J84: 46133 | K84: 46108 | L84: 1128.5 | M84: =Tabela22465789[[#This Row],[VENDA]]+Tabela22465789[[#This Row],[MÃO DE OBRA]]-Tabela22465789[[#This Row],[VALOR PAGO]] -> -0.01
B85: SMART | C85: 22311 | D85: 4095 | E85: 46105 | F85: SOARES | G85: MARCELO | I85: 1128.49 | J85: 46140 | K85: 46139 | L85: 1128.5 | M85: =Tabela22465789[[#This Row],[VENDA]]+Tabela22465789[[#This Row],[MÃO DE OBRA]]-Tabela22465789[[#This Row],[VALOR PAGO]] -> -0.01
B86: SMART | C86: 22311 | D86: 4095 | E86: 46105 | F86: SOARES | G86: MARCELO | I86: 1128.48 | J86: 46147 | K86: 46139 | L86: 1128.51 | M86: =Tabela22465789[[#This Row],[VENDA]]+Tabela22465789[[#This Row],[MÃO DE OBRA]]-Tabela22465789[[#This Row],[VALOR PAGO]] -> -0.03
B87: STK | C87: 22345 | D87: 4199 | E87: 46107 | F87: NOSSA SRA DE FAT | G87: MARCIANO | H87: 828 | J87: 46152 | K87: 46107 | L87: 828 | M87: =Tabela22465789[[#This Row],[VENDA]]+Tabela22465789[[#This Row],[MÃO DE OBRA]]-Tabela22465789[[#This Row],[VALOR PAGO]] -> 0
B88: STK | C88: 22381 | D88: 4184 | E88: 46108 | F88: GLAUCIA | G88: SILVANO | H88: 573.84 | J88: 46122 | M88: =Tabela22465789[[#This Row],[VENDA]]+Tabela22465789[[#This Row],[MÃO DE OBRA]]-Tabela22465789[[#This Row],[VALOR PAGO]] -> 573.84
B89: STK | C89: 22381 | D89: 4184 | E89: 46108 | F89: GLAUCIA | G89: SILVANO | H89: 573.84 | J89: 46129 | M89: =Tabela22465789[[#This Row],[VENDA]]+Tabela22465789[[#This Row],[MÃO DE OBRA]]-Tabela22465789[[#This Row],[VALOR PAGO]] -> 573.84
B90: STK | C90: 22381 | D90: 4184 | E90: 46108 | F90: GLAUCIA | G90: SILVANO | H90: 573.84 | J90: 46136 | M90: =Tabela22465789[[#This Row],[VENDA]]+Tabela22465789[[#This Row],[MÃO DE OBRA]]-Tabela22465789[[#This Row],[VALOR PAGO]] -> 573.84
B91: STK | C91: 22381 | D91: 4184 | E91: 46108 | F91: GLAUCIA | G91: SILVANO | H91: 573.84 | J91: 46143 | M91: =Tabela22465789[[#This Row],[VENDA]]+Tabela22465789[[#This Row],[MÃO DE OBRA]]-Tabela22465789[[#This Row],[VALOR PAGO]] -> 573.84
B92: STK | C92: 22381 | D92: 4184 | E92: 46108 | F92: GLAUCIA | G92: SILVANO | H92: 573.84 | J92: 46150 | M92: =Tabela22465789[[#This Row],[VENDA]]+Tabela22465789[[#This Row],[MÃO DE OBRA]]-Tabela22465789[[#This Row],[VALOR PAGO]] -> 573.84
B93: SMART | C93: 22385 | D93: 4200 | E93: 46108 | F93: LC COMPONENTES | G93: MARCELO | I93: 821.21 | J93: 46129 | K93: 46129 | L93: 821.21 | M93: =Tabela22465789[[#This Row],[VENDA]]+Tabela22465789[[#This Row],[MÃO DE OBRA]]-Tabela22465789[[#This Row],[VALOR PAGO]] -> 0
B94: STK | C94: 22371 | D94: 4207 | E94: 46108 | F94: MARIOTTA | G94: SILVANO | H94: 1892.4 | J94: 46122 | K94: 46125 | L94: 1892.4 | M94: =Tabela22465789[[#This Row],[VENDA]]+Tabela22465789[[#This Row],[MÃO DE OBRA]]-Tabela22465789[[#This Row],[VALOR PAGO]] -> 0
B95: STK | C95: 22371 | D95: 4207 | E95: 46108 | F95: MARIOTTA | G95: SILVANO | H95: 1892.4 | J95: 46129 | K95: 46129 | L95: 1892.4 | M95: =Tabela22465789[[#This Row],[VENDA]]+Tabela22465789[[#This Row],[MÃO DE OBRA]]-Tabela22465789[[#This Row],[VALOR PAGO]] -> 0
B96: STK | C96: 22371 | D96: 4207 | E96: 46108 | F96: MARIOTTA | G96: SILVANO | H96: 1892.4 | J96: 46136 | K96: 46136 | L96: 1892.4 | M96: =Tabela22465789[[#This Row],[VENDA]]+Tabela22465789[[#This Row],[MÃO DE OBRA]]-Tabela22465789[[#This Row],[VALOR PAGO]] -> 0
B97: STK | C97: 22379 | D97: 4208 | E97: 46108 | F97: MARIOTTA | G97: SILVANO | H97: =400*7.07/3 -> 942.66667 | J97: 46125 | K97: 46125 | L97: 942.66 | M97: =Tabela22465789[[#This Row],[VENDA]]+Tabela22465789[[#This Row],[MÃO DE OBRA]]-Tabela22465789[[#This Row],[VALOR PAGO]] -> 0.0066666667
B98: STK | C98: 22379 | D98: 4208 | E98: 46108 | F98: MARIOTTA | G98: SILVANO | H98: =400*7.07/3 -> 942.66667 | J98: 46132 | K98: 46132 | L98: 942.66 | M98: =Tabela22465789[[#This Row],[VENDA]]+Tabela22465789[[#This Row],[MÃO DE OBRA]]-Tabela22465789[[#This Row],[VALOR PAGO]] -> 0.0066666667
B99: STK | C99: 22379 | D99: 4208 | E99: 46108 | F99: MARIOTTA | G99: SILVANO | H99: =400*7.07/3 -> 942.66667 | J99: 46139 | K99: 46139 | L99: 942.66 | M99: =Tabela22465789[[#This Row],[VENDA]]+Tabela22465789[[#This Row],[MÃO DE OBRA]]-Tabela22465789[[#This Row],[VALOR PAGO]] -> 0.0066666667
B100: STK | C100: 22368 | D100: 4205 | E100: 46108 | F100: MARIOTTA | G100: SILVANO | H100: =1000*14.97/3 -> 4990 | J100: 46122 | K100: 46122 | L100: 4990 | M100: =Tabela22465789[[#This Row],[VENDA]]+Tabela22465789[[#This Row],[MÃO DE OBRA]]-Tabela22465789[[#This Row],[VALOR PAGO]] -> 0
B101: STK | C101: 22368 | D101: 4205 | E101: 46108 | F101: MARIOTTA | G101: SILVANO | H101: =1000*14.97/3 -> 4990 | J101: 46129 | K101: 46129 | L101: 4990 | M101: =Tabela22465789[[#This Row],[VENDA]]+Tabela22465789[[#This Row],[MÃO DE OBRA]]-Tabela22465789[[#This Row],[VALOR PAGO]] -> 0
B102: STK | C102: 22368 | D102: 4205 | E102: 46108 | F102: MARIOTTA | G102: SILVANO | H102: =1000*14.97/3 -> 4990 | J102: 46136 | K102: 46136 | L102: 4990 | M102: =Tabela22465789[[#This Row],[VENDA]]+Tabela22465789[[#This Row],[MÃO DE OBRA]]-Tabela22465789[[#This Row],[VALOR PAGO]] -> 0
B103: SMART | C103: 22432 | D103: 4193 | E103: 46112 | F103: SOARES | G103: MARCELO | H103: 1583.89 | J103: 46140 | K103: 46139 | L103: 1583.9 | M103: =Tabela22465789[[#This Row],[VENDA]]+Tabela22465789[[#This Row],[MÃO DE OBRA]]-Tabela22465789[[#This Row],[VALOR PAGO]] -> -0.01
B104: SMART | C104: 22432 | D104: 4193 | E104: 46112 | F104: SOARES | G104: MARCELO | H104: 1583.89 | J104: 46147 | K104: 46139 | L104: 1583.9 | M104: =Tabela22465789[[#This Row],[VENDA]]+Tabela22465789[[#This Row],[MÃO DE OBRA]]-Tabela22465789[[#This Row],[VALOR PAGO]] -> -0.01
B105: SMART | C105: 22432 | D105: 4193 | E105: 46112 | F105: SOARES | G105: MARCELO | H105: 1583.89 | J105: 46154 | K105: 46139 | L105: 1583.9 | M105: =Tabela22465789[[#This Row],[VENDA]]+Tabela22465789[[#This Row],[MÃO DE OBRA]]-Tabela22465789[[#This Row],[VALOR PAGO]] -> -0.01
A106: 27 | M106: =Tabela22465789[[#This Row],[VENDA]]+Tabela22465789[[#This Row],[MÃO DE OBRA]]-Tabela22465789[[#This Row],[VALOR PAGO]] -> 0
M107: =Tabela22465789[[#This Row],[VENDA]]+Tabela22465789[[#This Row],[MÃO DE OBRA]]-Tabela22465789[[#This Row],[VALOR PAGO]] -> 0
B109: TOTAL VENDA: | D109: =Tabela22465789[[#Totals],[VENDA]] -> 0 | H109: =SUM(H21:H108) -> 343846.58 | I109: =SUM(Tabela22465789[MÃO DE OBRA]) -> 16486.26
B110: TOTAL MÃO DE OBRA: | D110: =Tabela22465789[[#Totals],[MÃO DE OBRA]] -> 0
B111: TOTAL: | C111: =SUM(D109+D110) -> 0 | F111: TOTAL RECEBIDO: | H111: =SUM(Tabela22465789[VALOR PAGO]) -> 348618.36 | J111: TOTAL À RECEBER: | L111: =SUM(Tabela22465789[VALOR EM ABERTO]) -> 11714.48

Sheet Abril 2026
B2: FRETES
B4: MÊS | C4: SMART | H4: STK
C5: 2023 | D5: 2024 | E5: 2025 | F5: 2026 | G5: 2027 | H5: 2025 | I5: 2026 | J5: 2027 | K5: 2028 | L5: 2029 | M5: 2030
B6: JANEIRO | C6: 126073.37 | D6: 270562.53 | E6: 49887.66 | F6: 0 | G6: 0 | H6: 0 | I6: 0 | J6: 0 | K6: 0 | L6: 0 | M6: 0
B7: FEVEREIRO | C7: 166235.96 | D7: 324984.97 | E7: 15513.83 | F7: 0 | G7: 0 | H7: 0 | I7: 0 | J7: 0 | K7: 0 | L7: 0 | M7: 0
B8: MARÇO | C8: 119814.85 | D8: 256001.57 | E8: 32410.22 | F8: 0 | G8: 0 | H8: 0 | I8: 0 | J8: 0 | K8: 0 | L8: 0 | M8: 0
B9: ABRIL | C9: 112668.22 | D9: 136419.94 | E9: 23117.53 | F9: 0 | G9: 0 | H9: 0 | I9: 0 | J9: 0 | K9: 0 | L9: 0 | M9: 0
B10: MAIO | C10: 39597.94 | D10: 57014.4 | E10: 11710.4 | F10: 0 | G10: 0 | H10: 0 | I10: 0 | J10: 0 | K10: 0 | L10: 0 | M10: 0
B11: JUNHO | C11: 77419.24 | D11: 259261.92 | E11: 32986.86 | F11: 0 | G11: 0 | H11: 0 | I11: 0 | J11: 0 | K11: 0 | L11: 0 | M11: 0
B12: JULHO | C12: 74963.62 | D12: 191964.91 | E12: 8086.81 | F12: 0 | G12: 0 | H12: 0 | I12: 0 | J12: 0 | K12: 0 | L12: 0 | M12: 0
B13: AGOSTO | C13: 152485.66 | D13: 273158.85 | E13: 22122.22 | F13: 0 | G13: 0 | H13: 0 | I13: 0 | J13: 0 | K13: 0 | L13: 0 | M13: 0
B14: SETEMBRO | C14: 171282.48 | D14: 63159.51 | E14: 36466.42 | F14: 0 | G14: 0 | H14: 0 | I14: 0 | J14: 0 | K14: 0 | L14: 0 | M14: 0
B15: OUTUBRO | C15: 168433.06 | D15: 53077.38 | E15: 99828 | F15: 0 | G15: 0 | I15: 0 | J15: 0 | K15: 0 | L15: 0 | M15: 0
B16: NOVEMBRO | C16: 155757.68 | D16: 15517.44 | E16: 0 | F16: 0 | G16: 0 | H16: 0 | I16: 0 | J16: 0 | K16: 0 | L16: 0 | M16: 0
B17: DEZEMBRO | C17: 163379.08 | D17: 9580.01 | E17: 0 | F17: 0 | G17: 0 | H17: 0 | I17: 0 | J17: 0 | K17: 0 | L17: 0 | M17: 0
B18: TOTAL | C18: =SUM(C6:C17) -> 1528111.2 | D18: =SUM(D6:D17) -> 1910703.4 | E18: =SUM(E6:E17) -> 332129.95 | F18: =SUM(F6:F17) -> 0 | G18: 0 | H18: =SUM(H6:H17) -> 0 | I18: 0 | J18: =SUM(J6:J17) -> 0 | K18: 0 | L18: =SUM(L6:L17) -> 0 | M18: 0
B19: TOTAL CONSOLIDADO 2026: | D19: =SUM(I18+F18) -> 0
B20: EMPRESA | C20: NOTA FISCAL | D20: PEDIDO | E20: DATA DE EMISSÃO | F20: DESTINATÁRIO | G20: REPRESENTANTE | H20: VENDA | I20: MÃO DE OBRA | J20: VENCIMENTO | K20: DATA DE PAGAMENTO | L20: VALOR PAGO | M20: VALOR EM ABERTO | N20: Coluna1
B21: STK | C21: 826 | D21: 784 | E21: 46114 | F21: MARIOTTA | G21: SILVANO | H21: 5867.2 | J21: 46142 | K21: 46141 | L21: 5867.2 | M21: =Tabela2246578910[[#This Row],[VENDA]]+Tabela2246578910[[#This Row],[MÃO DE OBRA]]-Tabela2246578910[[#This Row],[VALOR PAGO]] -> 0
B22: STK | C22: 826 | D22: 784 | E22: 46114 | F22: MARIOTTA | G22: SILVANO | H22: 5867.2 | J22: 46149 | K22: 46150 | L22: 5867.2 | M22: =Tabela2246578910[[#This Row],[VENDA]]+Tabela2246578910[[#This Row],[MÃO DE OBRA]]-Tabela2246578910[[#This Row],[VALOR PAGO]] -> 0
B23: STK | C23: 826 | D23: 784 | E23: 46114 | F23: MARIOTTA | G23: SILVANO | H23: 5867.2 | J23: 46156 | K23: 46157 | L23: 5867.2 | M23: =Tabela2246578910[[#This Row],[VENDA]]+Tabela2246578910[[#This Row],[MÃO DE OBRA]]-Tabela2246578910[[#This Row],[VALOR PAGO]] -> 0
B24: STK | C24: 829 | D24: 756 | E24: 46118 | F24: VR CALÇADOS | G24: CLEMILSON | H24: 2633.5 | J24: 46125 | K24: 46126 | L24: 2633.5 | M24: =Tabela2246578910[[#This Row],[VENDA]]+Tabela2246578910[[#This Row],[MÃO DE OBRA]]-Tabela2246578910[[#This Row],[VALOR PAGO]] -> 0
B25: STK | C25: 829 | D25: 756 | E25: 46118 | F25: VR CALÇADOS | G25: CLEMILSON | H25: 2632 | J25: 46132 | K25: 46126 | L25: 2632 | M25: =Tabela2246578910[[#This Row],[VENDA]]+Tabela2246578910[[#This Row],[MÃO DE OBRA]]-Tabela2246578910[[#This Row],[VALOR PAGO]] -> 0
B26: STK | C26: 829 | D26: 756 | E26: 46118 | F26: VR CALÇADOS | G26: CLEMILSON | H26: 2632 | J26: 46139 | K26: 46126 | L26: 2632 | M26: =Tabela2246578910[[#This Row],[VENDA]]+Tabela2246578910[[#This Row],[MÃO DE OBRA]]-Tabela2246578910[[#This Row],[VALOR PAGO]] -> 0
B27: STK | C27: 834 | D27: 795 | E27: 46119 | F27: MARIOTTA | G27: SILVANO | H27: 2828 | J27: 46133 | K27: 46134 | L27: 2828 | M27: =Tabela2246578910[[#This Row],[VENDA]]+Tabela2246578910[[#This Row],[MÃO DE OBRA]]-Tabela2246578910[[#This Row],[VALOR PAGO]] -> 0
B28: STK | C28: 834 | D28: 795 | E28: 46119 | F28: MARIOTTA | G28: SILVANO | H28: 2828 | J28: 46140 | K28: 46140 | L28: 2828 | M28: =Tabela2246578910[[#This Row],[VENDA]]+Tabela2246578910[[#This Row],[MÃO DE OBRA]]-Tabela2246578910[[#This Row],[VALOR PAGO]] -> 0
B29: SMART | C29: 22542 | D29: - | E29: 46120 | F29: P&G | G29: - | H29: 534.8 | J29: A VISTA | K29: 46120 | L29: 534.8 | M29: =Tabela2246578910[[#This Row],[VENDA]]+Tabela2246578910[[#This Row],[MÃO DE OBRA]]-Tabela2246578910[[#This Row],[VALOR PAGO]] -> 0 | N29: Venda estoque
B30: SMART | C30: 22556 | D30: 4280 | E30: 46120 | F30: SOARES | G30: MARCELO | I30: 366.85 | J30: 46148 | K30: 46139 | L30: 366.85 | M30: =Tabela2246578910[[#This Row],[VENDA]]+Tabela2246578910[[#This Row],[MÃO DE OBRA]]-Tabela2246578910[[#This Row],[VALOR PAGO]] -> 0
B31: SMART | C31: 22556 | D31: 4280 | E31: 46120 | F31: SOARES | G31: MARCELO | I31: 366.85 | J31: 46155 | K31: 46139 | L31: 366.85 | M31: =Tabela2246578910[[#This Row],[VENDA]]+Tabela2246578910[[#This Row],[MÃO DE OBRA]]-Tabela2246578910[[#This Row],[VALOR PAGO]] -> 0
B32: SMART | C32: 22556 | D32: 4280 | E32: 46120 | F32: SOARES | G32: MARCELO | I32: 366.84 | J32: 46162 | K32: 46162 | L32: 366.86 | M32: =Tabela2246578910[[#This Row],[VENDA]]+Tabela2246578910[[#This Row],[MÃO DE OBRA]]-Tabela2246578910[[#This Row],[VALOR PAGO]] -> -0.02
B33: STK | C33: 22591 | D33: 4318 | E33: 46122 | F33: MARIOTTA | G33: SILVANO | H33: 4990 | J33: 46129 | K33: 46129 | L33: 4990 | M33: =Tabela2246578910[[#This Row],[VENDA]]+Tabela2246578910[[#This Row],[MÃO DE OBRA]]-Tabela2246578910[[#This Row],[VALOR PAGO]] -> 0
B34: STK | C34: 22591 | D34: 4318 | E34: 46122 | F34: MARIOTTA | G34: SILVANO | H34: 4990 | J34: 46136 | K34: 46136 | L34: 4990 | M34: =Tabela2246578910[[#This Row],[VENDA]]+Tabela2246578910[[#This Row],[MÃO DE OBRA]]-Tabela2246578910[[#This Row],[VALOR PAGO]] -> 0
B35: STK | C35: 22591 | D35: 4318 | E35: 46122 | F35: MARIOTTA | G35: SILVANO | H35: 4990 | J35: 46143 | K35: 46146 | L35: 4990 | M35: =Tabela2246578910[[#This Row],[VENDA]]+Tabela2246578910[[#This Row],[MÃO DE OBRA]]-Tabela2246578910[[#This Row],[VALOR PAGO]] -> 0
B36: SMART | C36: 22615 | D36: 4349 | E36: 46122 | F36: SOARES | G36: MARCELO | I36: 626.17 | J36: 46150 | K36: 46139 | L36: 626.18 | M36: =Tabela2246578910[[#This Row],[VENDA]]+Tabela2246578910[[#This Row],[MÃO DE OBRA]]-Tabela2246578910[[#This Row],[VALOR PAGO]] -> -0.01
B37: SMART | C37: 22615 | D37: 4349 | E37: 46122 | F37: SOARES | G37: MARCELO | I37: 626.17 | J37: 46157 | K37: 46139 | L37: 626.18 | M37: =Tabela2246578910[[#This Row],[VENDA]]+Tabela2246578910[[#This Row],[MÃO DE OBRA]]-Tabela2246578910[[#This Row],[VALOR PAGO]] -> -0.01
B38: SMART | C38: 22615 | D38: 4349 | E38: 46122 | F38: SOARES | G38: MARCELO | I38: 626.18 | J38: 46164 | K38: 46162 | L38: 626.17 | M38: =Tabela2246578910[[#This Row],[VENDA]]+Tabela2246578910[[#This Row],[MÃO DE OBRA]]-Tabela2246578910[[#This Row],[VALOR PAGO]] -> 0.01
B39: SMART | C39: 22617 | D39: 4336 | E39: 46122 | F39: LC COMP | G39: MARCELO | I39: =(78.5+39+38)*7.11 -> 1105.605 | J39: 46143 | K39: 46141 | L39: 1105.61 | M39: =Tabela2246578910[[#This Row],[VENDA]]+Tabela2246578910[[#This Row],[MÃO DE OBRA]]-Tabela2246578910[[#This Row],[VALOR PAGO]] -> -0.005
B40: SMART | C40: 22642 | D40: 4349 | E40: 46126 | F40: SOARES | G40: MARCELO | I40: 366.27 | J40: 46154 | K40: 46139 | L40: 366.28 | M40: =Tabela2246578910[[#This Row],[VENDA]]+Tabela2246578910[[#This Row],[MÃO DE OBRA]]-Tabela2246578910[[#This Row],[VALOR PAGO]] -> -0.01
B41: SMART | C41: 22642 | D41: 4349 | E41: 46126 | F41: SOARES | G41: MARCELO | I41: 366.27 | J41: 46161 | K41: 46162 | L41: 366.28 | M41: =Tabela2246578910[[#This Row],[VENDA]]+Tabela2246578910[[#This Row],[MÃO DE OBRA]]-Tabela2246578910[[#This Row],[VALOR PAGO]] -> -0.01
B42: SMART | C42: 22642 | D42: 4349 | E42: 46126 | F42: SOARES | G42: MARCELO | I42: 366.28 | J42: 46168 | K42: 46178 | L42: 366.27 | M42: =Tabela2246578910[[#This Row],[VENDA]]+Tabela2246578910[[#This Row],[MÃO DE OBRA]]-Tabela2246578910[[#This Row],[VALOR PAGO]] -> 0.01
B43: SMART | C43: 22643 | D43: 4352 | E43: 46126 | F43: LC COMP | G43: MARCELO | I43: =114.4*7.11 -> 813.384 | J43: 46147 | K43: 46147 | L43: 813.38 | M43: =Tabela2246578910[[#This Row],[VENDA]]+Tabela2246578910[[#This Row],[MÃO DE OBRA]]-Tabela2246578910[[#This Row],[VALOR PAGO]] -> 0.004
B44: STK | C44: 851 | D44: 947 | E44: 46127 | F44: MARIOTTA | G44: SILVANO | H44: =8337.6/3 -> 2779.2 | J44: 46155 | K44: 46155 | L44: 2779.2 | M44: =Tabela2246578910[[#This Row],[VENDA]]+Tabela2246578910[[#This Row],[MÃO DE OBRA]]-Tabela2246578910[[#This Row],[VALOR PAGO]] -> 0
B45: STK | C45: 851 | D45: 947 | E45: 46127 | F45: MARIOTTA | G45: SILVANO | H45: =8337.6/3 -> 2779.2 | J45: 46162 | K45: 46161 | L45: 2779.2 | M45: =Tabela2246578910[[#This Row],[VENDA]]+Tabela2246578910[[#This Row],[MÃO DE OBRA]]-Tabela2246578910[[#This Row],[VALOR PAGO]] -> 0
B46: STK | C46: 851 | D46: 947 | E46: 46127 | F46: MARIOTTA | G46: SILVANO | H46: =8337.6/3 -> 2779.2 | J46: 46169 | K46: 46167 | L46: 2779.2 | M46: =Tabela2246578910[[#This Row],[VENDA]]+Tabela2246578910[[#This Row],[MÃO DE OBRA]]-Tabela2246578910[[#This Row],[VALOR PAGO]] -> 0
B47: SMART | C47: 22711 | D47: 4349 | E47: 46128 | F47: SOARES | G47: MARCELO | I47: 272.55 | J47: 46147 | K47: 46162 | L47: 272.55 | M47: =Tabela2246578910[[#This Row],[VENDA]]+Tabela2246578910[[#This Row],[MÃO DE OBRA]]-Tabela2246578910[[#This Row],[VALOR PAGO]] -> 0
B48: SMART | C48: 22712 | D48: 4445 | E48: 46129 | F48: SOARES | G48: MARCELO | I48: 456.55 | J48: 46157 | K48: 46139 | L48: 456.55 | M48: =Tabela2246578910[[#This Row],[VENDA]]+Tabela2246578910[[#This Row],[MÃO DE OBRA]]-Tabela2246578910[[#This Row],[VALOR PAGO]] -> 0
B49: SMART | C49: 22712 | D49: 4445 | E49: 46129 | F49: SOARES | G49: MARCELO | I49: 456.55 | J49: 46164 | K49: 46163 | L49: 456.55 | M49: =Tabela2246578910[[#This Row],[VENDA]]+Tabela2246578910[[#This Row],[MÃO DE OBRA]]-Tabela2246578910[[#This Row],[VALOR PAGO]] -> 0
B50: SMART | C50: 22712 | D50: 4445 | E50: 46129 | F50: SOARES | G50: MARCELO | I50: 456.54 | J50: 46171 | K50: 46178 | L50: 456.56 | M50: =Tabela2246578910[[#This Row],[VENDA]]+Tabela2246578910[[#This Row],[MÃO DE OBRA]]-Tabela2246578910[[#This Row],[VALOR PAGO]] -> -0.02
B51: STK | C51: 22713 | D51: 4469 | E51: 46129 | F51: NH TEX | G51: DIRETO | H51: 1324.47 | J51: 46159 | K51: 46160 | L51: 1324.47 | M51: =Tabela2246578910[[#This Row],[VENDA]]+Tabela2246578910[[#This Row],[MÃO DE OBRA]]-Tabela2246578910[[#This Row],[VALOR PAGO]] -> 0
B52: STK | C52: 22713 | D52: 4469 | E52: 46129 | F52: NH TEX | G52: DIRETO | H52: 1324.47 | J52: 46169 | K52: 46170 | L52: 1324.47 | M52: =Tabela2246578910[[#This Row],[VENDA]]+Tabela2246578910[[#This Row],[MÃO DE OBRA]]-Tabela2246578910[[#This Row],[VALOR PAGO]] -> 0
B53: STK | C53: 22713 | D53: 4469 | E53: 46129 | F53: NH TEX | G53: DIRETO | H53: 1324.47 | J53: 46179 | K53: 46181 | L53: 1324.47 | M53: =Tabela2246578910[[#This Row],[VENDA]]+Tabela2246578910[[#This Row],[MÃO DE OBRA]]-Tabela2246578910[[#This Row],[VALOR PAGO]] -> 0
B54: STK | C54: 22713 | D54: 4469 | E54: 46129 | F54: NH TEX | G54: DIRETO | H54: 1324.47 | J54: 46189 | K54: 46189 | L54: 1324.47 | M54: =Tabela2246578910[[#This Row],[VENDA]]+Tabela2246578910[[#This Row],[MÃO DE OBRA]]-Tabela2246578910[[#This Row],[VALOR PAGO]] -> 0
B55: SMART | C55: 22738 | D55: 4445 | E55: 46129 | F55: SOARES | G55: MARCELO | I55: 403.65 | J55: 46157 | K55: 46162 | L55: 403.65 | M55: =Tabela2246578910[[#This Row],[VENDA]]+Tabela2246578910[[#This Row],[MÃO DE OBRA]]-Tabela2246578910[[#This Row],[VALOR PAGO]] -> 0
B56: STK | C56: 858 | D56: 822 | E56: 46129 | F56: MARIOTTA | G56: SILVANO | H56: =7.07*1000/3 -> 2356.6667 | J56: 46143 | K56: 46146 | L56: 2356.66 | M56: =Tabela2246578910[[#This Row],[VENDA]]+Tabela2246578910[[#This Row],[MÃO DE OBRA]]-Tabela2246578910[[#This Row],[VALOR PAGO]] -> 0.0066666667
B57: STK | C57: 858 | D57: 822 | E57: 46129 | F57: MARIOTTA | G57: SILVANO | H57: =7.07*1000/3 -> 2356.6667 | J57: 46150 | K57: 46150 | L57: 2356.66 | M57: =Tabela2246578910[[#This Row],[VENDA]]+Tabela2246578910[[#This Row],[MÃO DE OBRA]]-Tabela2246578910[[#This Row],[VALOR PAGO]] -> 0.0066666667
B58: STK | C58: 858 | D58: 822 | E58: 46129 | F58: MARIOTTA | G58: SILVANO | H58: =7.07*1000/3 -> 2356.6667 | J58: 46157 | K58: 46156 | L58: 2356.66 | M58: =Tabela2246578910[[#This Row],[VENDA]]+Tabela2246578910[[#This Row],[MÃO DE OBRA]]-Tabela2246578910[[#This Row],[VALOR PAGO]] -> 0.0066666667
B59: STK | C59: 22745 | D59: 4491 | E59: 46129 | F59: VIA BELLA | G59: MARCIANO | H59: 7102.1 | J59: 46143 | K59: 46146 | L59: 7102.1 | M59: =Tabela2246578910[[#This Row],[VENDA]]+Tabela2246578910[[#This Row],[MÃO DE OBRA]]-Tabela2246578910[[#This Row],[VALOR PAGO]] -> 0
B60: STK | C60: 865 | D60: 820 | E60: 46132 | F60: VR CALÇADOS | G60: CLEMILSON | H60: 1755 | J60: 46143 | K60: 46154 | L60: 1755 | M60: =Tabela2246578910[[#This Row],[VENDA]]+Tabela2246578910[[#This Row],[MÃO DE OBRA]]-Tabela2246578910[[#This Row],[VALOR PAGO]] -> 0
B61: STK | C61: 865 | D61: 820 | E61: 46132 | F61: VR CALÇADOS | G61: CLEMILSON | H61: 1755 | J61: 46150 | K61: 46154 | L61: 1755 | M61: =Tabela2246578910[[#This Row],[VENDA]]+Tabela2246578910[[#This Row],[MÃO DE OBRA]]-Tabela2246578910[[#This Row],[VALOR PAGO]] -> 0
B62: STK | C62: 865 | D62: 820 | E62: 46132 | F62: VR CALÇADOS | G62: CLEMILSON | H62: 1755 | J62: 46157 | K62: 46154 | L62: 1755 | M62: =Tabela2246578910[[#This Row],[VENDA]]+Tabela2246578910[[#This Row],[MÃO DE OBRA]]-Tabela2246578910[[#This Row],[VALOR PAGO]] -> 0
B63: SMART | C63: 22832 | D63: 4548 | E63: 46136 | F63: SOARES | G63: MARCELO | I63: 410.55 | J63: 46164 | K63: 46162 | L63: 410.55 | M63: =Tabela2246578910[[#This Row],[VENDA]]+Tabela2246578910[[#This Row],[MÃO DE OBRA]]-Tabela2246578910[[#This Row],[VALOR PAGO]] -> 0
B64: STK | C64: 22842 | D64: 4593 | E64: 46139 | F64: ROSA 'DALVA | G64: HENRIQUE | H64: 8553.6 | J64: A VISTA | K64: 46139 | L64: 8553.6 | M64: =Tabela2246578910[[#This Row],[VENDA]]+Tabela2246578910[[#This Row],[MÃO DE OBRA]]-Tabela2246578910[[#This Row],[VALOR PAGO]] -> 0
B65: SMART | C65: 22845 | D65: 4558 | E65: 46139 | F65: SOARES | G65: MARCELO | I65: 407.1 | J65: 46167 | K65: 46162 | L65: 407.1 | M65: =Tabela2246578910[[#This Row],[VENDA]]+Tabela2246578910[[#This Row],[MÃO DE OBRA]]-Tabela2246578910[[#This Row],[VALOR PAGO]] -> 0
B66: SMART | C66: 22845 | D66: 4558 | E66: 46139 | F66: SOARES | G66: MARCELO | I66: 407.1 | J66: 46174 | K66: 46178 | L66: 407.1 | M66: =Tabela2246578910[[#This Row],[VENDA]]+Tabela2246578910[[#This Row],[MÃO DE OBRA]]-Tabela2246578910[[#This Row],[VALOR PAGO]] -> 0
B67: SMART | C67: 22845 | D67: 4558 | E67: 46139 | F67: SOARES | G67: MARCELO | I67: 407.1 | J67: 46181 | K67: 46188 | L67: 407.1 | M67: =Tabela2246578910[[#This Row],[VENDA]]+Tabela2246578910[[#This Row],[MÃO DE OBRA]]-Tabela2246578910[[#This Row],[VALOR PAGO]] -> 0
B68: SMART | C68: 22867 | D68: 4557 | E68: 46139 | F68: LC COMP | G68: MARCELO | H68: 5279.175 | J68: 46160 | K68: 46160 | L68: 5279.18 | M68: =Tabela2246578910[[#This Row],[VENDA]]+Tabela2246578910[[#This Row],[MÃO DE OBRA]]-Tabela2246578910[[#This Row],[VALOR PAGO]] -> -0.005
B69: STK | C69: 885 | D69: 846 | E69: 46141 | F69: MARIOTTA | G69: SILVANO | H69: 1702.8 | J69: 46154 | K69: 46154 | L69: 1702.8 | M69: =Tabela2246578910[[#This Row],[VENDA]]+Tabela2246578910[[#This Row],[MÃO DE OBRA]]-Tabela2246578910[[#This Row],[VALOR PAGO]] -> 0
B70: STK | C70: 885 | D70: 846 | E70: 46141 | F70: MARIOTTA | G70: SILVANO | H70: 1702.8 | J70: 46161 | K70: 46161 | L70: 1702.8 | M70: =Tabela2246578910[[#This Row],[VENDA]]+Tabela2246578910[[#This Row],[MÃO DE OBRA]]-Tabela2246578910[[#This Row],[VALOR PAGO]] -> 0
B71: STK | C71: 885 | D71: 846 | E71: 46141 | F71: MARIOTTA | G71: SILVANO | H71: 1702.8 | J71: 46168 | K71: 46168 | L71: 1702.8 | M71: =Tabela2246578910[[#This Row],[VENDA]]+Tabela2246578910[[#This Row],[MÃO DE OBRA]]-Tabela2246578910[[#This Row],[VALOR PAGO]] -> 0
B72: STK | C72: 22910 | D72: 4659 | E72: 46142 | F72: SELTEN | G72: FERNANDO | H72: 1880 | J72: 46157 | K72: 46157 | L72: 1880 | M72: =Tabela2246578910[[#This Row],[VENDA]]+Tabela2246578910[[#This Row],[MÃO DE OBRA]]-Tabela2246578910[[#This Row],[VALOR PAGO]] -> 0
B73: STK | C73: 22910 | D73: 4659 | E73: 46142 | F73: SELTEN | G73: FERNANDO | H73: 1880 | J73: 46172 | K73: 46174 | L73: 1880 | M73: =Tabela2246578910[[#This Row],[VENDA]]+Tabela2246578910[[#This Row],[MÃO DE OBRA]]-Tabela2246578910[[#This Row],[VALOR PAGO]] -> 0
B74: STK | C74: 22910 | D74: 4659 | E74: 46142 | F74: SELTEN | G74: FERNANDO | H74: 1128 | J74: 46187 | K74: 46188 | L74: 1128 | M74: =Tabela2246578910[[#This Row],[VENDA]]+Tabela2246578910[[#This Row],[MÃO DE OBRA]]-Tabela2246578910[[#This Row],[VALOR PAGO]] -> 0
M75: =Tabela2246578910[[#This Row],[VENDA]]+Tabela2246578910[[#This Row],[MÃO DE OBRA]]-Tabela2246578910[[#This Row],[VALOR PAGO]] -> 0
M76: =Tabela2246578910[[#This Row],[VENDA]]+Tabela2246578910[[#This Row],[MÃO DE OBRA]]-Tabela2246578910[[#This Row],[VALOR PAGO]] -> 0
N77: Referente 160m de devolução da NF22.910 - NF DEVOLUÇÃO: 000.015
B78: TOTAL VENDA: | D78: =Tabela2246578910[[#Totals],[VENDA]] -> 0 | H78: =SUM(H21:H77) -> 103561.66 | I78: =SUM(Tabela2246578910[MÃO DE OBRA]) -> 9674.559
B79: TOTAL MÃO DE OBRA: | D79: =Tabela2246578910[[#Totals],[MÃO DE OBRA]] -> 0
B80: TOTAL: | C80: =SUM(D78+D79) -> 0 | F80: TOTAL RECEBIDO: | H80: =SUM(Tabela2246578910[VALOR PAGO]) -> 113236.26 | J80: TOTAL À RECEBER: | L80: =SUM(Tabela2246578910[VALOR EM ABERTO]) -> -0.046

Sheet Maio 2026
B2: FRETES
B4: MÊS | C4: SMART | H4: STK
C5: 2023 | D5: 2024 | E5: 2025 | F5: 2026 | G5: 2027 | H5: 2025 | I5: 2026 | J5: 2027 | K5: 2028 | L5: 2029 | M5: 2030
B6: JANEIRO | C6: 126073.37 | D6: 270562.53 | E6: 49887.66 | F6: =Tabela224657[[#Totals],[VENDA]]+Tabela224657[[#Totals],[MÃO DE OBRA]] -> 50516.042 | G6: 0 | H6: 0 | I6: 0 | J6: 0 | K6: 0 | L6: 0 | M6: 0
B7: FEVEREIRO | C7: 166235.96 | D7: 324984.97 | E7: 15513.83 | F7: =Tabela2246578[[#Totals],[VENDA]]+Tabela2246578[[#Totals],[MÃO DE OBRA]] -> 65390.11 | G7: 0 | H7: 0 | I7: 0 | J7: 0 | K7: 0 | L7: 0 | M7: 0
B8: MARÇO | C8: 119814.85 | D8: 256001.57 | E8: 32410.22 | F8: ='Março 2026'!H109+'Março 2026'!I109 -> 360332.84 | G8: 0 | H8: 0 | I8: 0 | J8: 0 | K8: 0 | L8: 0 | M8: 0
B9: ABRIL | C9: 112668.22 | D9: 136419.94 | E9: 23117.53 | F9: ='Abril 2026'!H78+'Abril 2026'!I78 -> 113236.21 | G9: 0 | H9: 0 | I9: 0 | J9: 0 | K9: 0 | L9: 0 | M9: 0
B10: MAIO | C10: 39597.94 | D10: 57014.4 | E10: 11710.4 | F10: =H82+I82 -> 107479.18 | G10: 0 | H10: 0 | I10: 0 | J10: 0 | K10: 0 | L10: 0 | M10: 0
B11: JUNHO | C11: 77419.24 | D11: 259261.92 | E11: 32986.86 | F11: 0 | G11: 0 | H11: 0 | I11: 0 | J11: 0 | K11: 0 | L11: 0 | M11: 0
B12: JULHO | C12: 74963.62 | D12: 191964.91 | E12: 8086.81 | F12: 0 | G12: 0 | H12: 0 | I12: 0 | J12: 0 | K12: 0 | L12: 0 | M12: 0
B13: AGOSTO | C13: 152485.66 | D13: 273158.85 | E13: 22122.22 | F13: 0 | G13: 0 | H13: 0 | I13: 0 | J13: 0 | K13: 0 | L13: 0 | M13: 0
B14: SETEMBRO | C14: 171282.48 | D14: 63159.51 | E14: 36466.42 | F14: 0 | G14: 0 | H14: 0 | I14: 0 | J14: 0 | K14: 0 | L14: 0 | M14: 0
B15: OUTUBRO | C15: 168433.06 | D15: 53077.38 | E15: 99828 | F15: 0 | G15: 0 | I15: 0 | J15: 0 | K15: 0 | L15: 0 | M15: 0
B16: NOVEMBRO | C16: 155757.68 | D16: 15517.44 | E16: =Tabela2246[[#Totals],[VENDA]]+Tabela2246[[#Totals],[MÃO DE OBRA]] -> 381690.36 | F16: 0 | G16: 0 | H16: 0 | I16: 0 | J16: 0 | K16: 0 | L16: 0 | M16: 0
B17: DEZEMBRO | C17: 163379.08 | D17: 9580.01 | E17: =Tabela22465[[#Totals],[VENDA]]+Tabela22465[[#Totals],[MÃO DE OBRA]] -> 148680.26 | F17: 0 | G17: 0 | H17: 0 | I17: 0 | J17: 0 | K17: 0 | L17: 0 | M17: 0
B18: TOTAL | C18: =SUM(C6:C17) -> 1528111.2 | D18: =SUM(D6:D17) -> 1910703.4 | E18: =SUM(E6:E17) -> 862500.57 | F18: =SUM(F6:F17) -> 696954.39 | G18: 0 | H18: =SUM(H6:H17) -> 0 | I18: 0 | J18: =SUM(J6:J17) -> 0 | K18: 0 | L18: =SUM(L6:L17) -> 0 | M18: 0
B19: TOTAL CONSOLIDADO 2026: | D19: =SUM(I18+F18) -> 696954.39
B20: EMPRESA | C20: NOTA FISCAL | D20: PEDIDO | E20: DATA DE EMISSÃO | F20: DESTINATÁRIO | G20: REPRESENTANTE | H20: VENDA | I20: MÃO DE OBRA | J20: VENCIMENTO | K20: DATA DE PAGAMENTO | L20: VALOR PAGO | M20: VALOR EM ABERTO | N20: Coluna1
E21: 46146 | F21: JC ACESSORIOS | H21: 4590.5 | J21: 46160 | K21: 46146 | L21: =2295.25+2295.25 -> 4590.5 | M21: =Tabela224657891011[[#This Row],[VENDA]]+Tabela224657891011[[#This Row],[MÃO DE OBRA]]-Tabela224657891011[[#This Row],[VALOR PAGO]] -> 0 | N21: Pago 50% 04/05 e saldo 18/05
B22: SMART | C22: 22964 | D22: 4669 | E22: 46146 | F22: SOARES | G22: MARCELO | I22: 407.1 | J22: 46174 | K22: 46178 | L22: 407.1 | M22: =Tabela224657891011[[#This Row],[VENDA]]+Tabela224657891011[[#This Row],[MÃO DE OBRA]]-Tabela224657891011[[#This Row],[VALOR PAGO]] -> 0
B23: SMART | C23: 22964 | D23: 4669 | E23: 46146 | F23: SOARES | G23: MARCELO | I23: 407.1 | J23: 46181 | K23: 46188 | L23: 407.1 | M23: =Tabela224657891011[[#This Row],[VENDA]]+Tabela224657891011[[#This Row],[MÃO DE OBRA]]-Tabela224657891011[[#This Row],[VALOR PAGO]] -> 0
B24: STK | C24: 900 | D24: 871 | E24: 46148 | F24: MARIOTTA | G24: SILVANO | H24: 1602.53 | J24: 46162 | K24: 46162 | L24: 1602.53 | M24: =Tabela224657891011[[#This Row],[VENDA]]+Tabela224657891011[[#This Row],[MÃO DE OBRA]]-Tabela224657891011[[#This Row],[VALOR PAGO]] -> 0
B25: STK | C25: 900 | D25: 871 | E25: 46148 | F25: MARIOTTA | G25: SILVANO | H25: 1602.53 | J25: 46169 | K25: 46167 | L25: 1602.53 | M25: =Tabela224657891011[[#This Row],[VENDA]]+Tabela224657891011[[#This Row],[MÃO DE OBRA]]-Tabela224657891011[[#This Row],[VALOR PAGO]] -> 0
B26: STK | C26: 900 | D26: 871 | E26: 46148 | F26: MARIOTTA | G26: SILVANO | H26: 1602.54 | J26: 46176 | K26: 46175 | L26: 1602.53 | M26: =Tabela224657891011[[#This Row],[VENDA]]+Tabela224657891011[[#This Row],[MÃO DE OBRA]]-Tabela224657891011[[#This Row],[VALOR PAGO]] -> 0.01
B27: SMART | C27: 23021 | D27: 4681 | E27: 46148 | F27: SOARES | G27: MARCELO | I27: 526.12 | J27: 46183 | K27: 46178 | L27: 526.12 | M27: =Tabela224657891011[[#This Row],[VENDA]]+Tabela224657891011[[#This Row],[MÃO DE OBRA]]-Tabela224657891011[[#This Row],[VALOR PAGO]] -> 0
B28: SMART | C28: 23022 | D28: 4680 | E28: 46148 | F28: SOARES | G28: MARCELO | I28: 403.64 | J28: 46183 | K28: 46178 | L28: 403.66 | M28: =Tabela224657891011[[#This Row],[VENDA]]+Tabela224657891011[[#This Row],[MÃO DE OBRA]]-Tabela224657891011[[#This Row],[VALOR PAGO]] -> -0.02
B29: SMART | C29: 23072 | D29: 4717 | E29: 46150 | F29: SOARES | G29: MARCELO | I29: 1001.65 | J29: 46178 | K29: 46188 | L29: 1001.65 | M29: =Tabela224657891011[[#This Row],[VENDA]]+Tabela224657891011[[#This Row],[MÃO DE OBRA]]-Tabela224657891011[[#This Row],[VALOR PAGO]] -> 0
B30: SMART | C30: 23072 | D30: 4717 | E30: 46150 | F30: SOARES | G30: MARCELO | I30: 1001.645 | J30: 46185 | K30: 46188 | L30: 1001.65 | M30: =Tabela224657891011[[#This Row],[VENDA]]+Tabela224657891011[[#This Row],[MÃO DE OBRA]]-Tabela224657891011[[#This Row],[VALOR PAGO]] -> -0.005
B31: SMART | C31: 23072 | D31: 4717 | E31: 46150 | F31: SOARES | G31: MARCELO | I31: 1001.64 | J31: 46192 | K31: 46191 | L31: 1001.66 | M31: =Tabela224657891011[[#This Row],[VENDA]]+Tabela224657891011[[#This Row],[MÃO DE OBRA]]-Tabela224657891011[[#This Row],[VALOR PAGO]] -> -0.02
B32: STK | C32: 23068 | D32: 4781 | E32: 46150 | F32: CRIAÇÕES ROGER | G32: MARCIANO | I32: 109.75 | J32: A VISTA | K32: 46161 | L32: 109.75 | M32: =Tabela224657891011[[#This Row],[VENDA]]+Tabela224657891011[[#This Row],[MÃO DE OBRA]]-Tabela224657891011[[#This Row],[VALOR PAGO]] -> 0
B33: STK | C33: 23133 | D33: 4837 | E33: 46155 | F33: MARIOTTA | G33: SILVANO | H33: 2073.86 | J33: 46176 | K33: 46176 | L33: 2073.86 | M33: =Tabela224657891011[[#This Row],[VENDA]]+Tabela224657891011[[#This Row],[MÃO DE OBRA]]-Tabela224657891011[[#This Row],[VALOR PAGO]] -> 0
B34: STK | C34: 23133 | D34: 4837 | E34: 46155 | F34: MARIOTTA | G34: SILVANO | H34: 2073.87 | J34: 46183 | K34: 46183 | L34: 2073.87 | M34: =Tabela224657891011[[#This Row],[VENDA]]+Tabela224657891011[[#This Row],[MÃO DE OBRA]]-Tabela224657891011[[#This Row],[VALOR PAGO]] -> 0
B35: STK | C35: 23133 | D35: 4837 | E35: 46155 | F35: MARIOTTA | G35: SILVANO | H35: 2073.87 | J35: 46190 | K35: 46190 | L35: 2073 | M35: =Tabela224657891011[[#This Row],[VENDA]]+Tabela224657891011[[#This Row],[MÃO DE OBRA]]-Tabela224657891011[[#This Row],[VALOR PAGO]] -> 0.87
B36: STK | C36: 23134 | D36: 4838 | E36: 46155 | F36: MARIOTTA | G36: SILVANO | H36: 2073.86 | J36: 46185 | K36: 46185 | L36: 2073.86 | M36: =Tabela224657891011[[#This Row],[VENDA]]+Tabela224657891011[[#This Row],[MÃO DE OBRA]]-Tabela224657891011[[#This Row],[VALOR PAGO]] -> 0
B37: STK | C37: 23134 | D37: 4838 | E37: 46155 | F37: MARIOTTA | G37: SILVANO | H37: 2073.87 | J37: 46192 | K37: 46199 | L37: 2073.87 | M37: =Tabela224657891011[[#This Row],[VENDA]]+Tabela224657891011[[#This Row],[MÃO DE OBRA]]-Tabela224657891011[[#This Row],[VALOR PAGO]] -> 0
B38: STK | C38: 23134 | D38: 4838 | E38: 46155 | F38: MARIOTTA | G38: SILVANO | H38: 2073.87 | J38: 46199 | K38: 46199 | L38: 2073.87 | M38: =Tabela224657891011[[#This Row],[VENDA]]+Tabela224657891011[[#This Row],[MÃO DE OBRA]]-Tabela224657891011[[#This Row],[VALOR PAGO]] -> 0
B39: STK | C39: 23135 | D39: 4839 | E39: 46155 | F39: MARIOTTA | G39: SILVANO | H39: 2170.49 | J39: 46197 | K39: 46197 | L39: 2170.49 | M39: =Tabela224657891011[[#This Row],[VENDA]]+Tabela224657891011[[#This Row],[MÃO DE OBRA]]-Tabela224657891011[[#This Row],[VALOR PAGO]] -> 0
B40: STK | C40: 23135 | D40: 4839 | E40: 46155 | F40: MARIOTTA | G40: SILVANO | H40: 2171.49 | J40: 46204 | M40: =Tabela224657891011[[#This Row],[VENDA]]+Tabela224657891011[[#This Row],[MÃO DE OBRA]]-Tabela224657891011[[#This Row],[VALOR PAGO]] -> 2171.49
B41: STK | C41: 23135 | D41: 4839 | E41: 46155 | F41: MARIOTTA | G41: SILVANO | H41: 2172.49 | J41: 46211 | M41: =Tabela224657891011[[#This Row],[VENDA]]+Tabela224657891011[[#This Row],[MÃO DE OBRA]]-Tabela224657891011[[#This Row],[VALOR PAGO]] -> 2172.49
B42: SMART | C42: 23203 | D42: 4812 | E42: 46156 | F42: SOARES | G42: MARCELO | I42: 112.06 | J42: 46191 | K42: 46188 | L42: 112.19 | M42: =Tabela224657891011[[#This Row],[VENDA]]+Tabela224657891011[[#This Row],[MÃO DE OBRA]]-Tabela224657891011[[#This Row],[VALOR PAGO]] -> -0.13
B43: SMART | C43: 23202 | D43: 4840 | E43: 46156 | F43: SOARES | G43: MARCELO | I43: 457.7 | J43: 46184 | K43: 46188 | L43: 457.7 | M43: =Tabela224657891011[[#This Row],[VENDA]]+Tabela224657891011[[#This Row],[MÃO DE OBRA]]-Tabela224657891011[[#This Row],[VALOR PAGO]] -> 0
B44: SMART | C44: 23202 | D44: 4840 | E44: 46156 | F44: SOARES | G44: MARCELO | I44: 457.7 | J44: 46191 | K44: 46191 | L44: 457.7 | M44: =Tabela224657891011[[#This Row],[VENDA]]+Tabela224657891011[[#This Row],[MÃO DE OBRA]]-Tabela224657891011[[#This Row],[VALOR PAGO]] -> 0
B45: SMART | C45: 23202 | D45: 4840 | E45: 46156 | F45: SOARES | G45: MARCELO | I45: 457.7 | J45: 46198 | K45: 46195 | L45: 457.7 | M45: =Tabela224657891011[[#This Row],[VENDA]]+Tabela224657891011[[#This Row],[MÃO DE OBRA]]-Tabela224657891011[[#This Row],[VALOR PAGO]] -> 0
B46: SMART | C46: 23240 | D46: 4840 | E46: 46157 | F46: SOARES | G46: MARCELO | I46: 883.2 | J46: 46185 | K46: 46188 | L46: 883.2 | M46: =Tabela224657891011[[#This Row],[VENDA]]+Tabela224657891011[[#This Row],[MÃO DE OBRA]]-Tabela224657891011[[#This Row],[VALOR PAGO]] -> 0
B47: SMART | C47: 23240 | D47: 4840 | E47: 46157 | F47: SOARES | G47: MARCELO | I47: 883.2 | J47: 46192 | K47: 46191 | L47: 883.2 | M47: =Tabela224657891011[[#This Row],[VENDA]]+Tabela224657891011[[#This Row],[MÃO DE OBRA]]-Tabela224657891011[[#This Row],[VALOR PAGO]] -> 0
B48: SMART | C48: 23240 | D48: 4840 | E48: 46157 | F48: SOARES | G48: MARCELO | I48: 883.19 | J48: 46199 | K48: 46196 | L48: 883.21 | M48: =Tabela224657891011[[#This Row],[VENDA]]+Tabela224657891011[[#This Row],[MÃO DE OBRA]]-Tabela224657891011[[#This Row],[VALOR PAGO]] -> -0.02
B49: STK | C49: 23234 | D49: 4872 | E49: 46157 | F49: SOARES | G49: MARCELO | H49: 12510 | J49: 46185 | K49: 46191 | L49: 12510 | M49: =Tabela224657891011[[#This Row],[VENDA]]+Tabela224657891011[[#This Row],[MÃO DE OBRA]]-Tabela224657891011[[#This Row],[VALOR PAGO]] -> 0
B50: STK | C50: 23234 | D50: 4872 | E50: 46157 | F50: SOARES | G50: MARCELO | H50: 12510 | J50: 46192 | K50: 46195 | L50: 12510 | M50: =Tabela224657891011[[#This Row],[VENDA]]+Tabela224657891011[[#This Row],[MÃO DE OBRA]]-Tabela224657891011[[#This Row],[VALOR PAGO]] -> 0
B51: STK | C51: 23234 | D51: 4872 | E51: 46157 | F51: SOARES | G51: MARCELO | H51: 12510 | J51: 46199 | K51: 46197 | L51: 12510 | M51: =Tabela224657891011[[#This Row],[VENDA]]+Tabela224657891011[[#This Row],[MÃO DE OBRA]]-Tabela224657891011[[#This Row],[VALOR PAGO]] -> 0
B52: STK | C52: 23260 | D52: 4879 | E52: 46160 | F52: MARIOTTA | G52: SILVANO | H52: 2262.4 | J52: 46174 | K52: 46170 | L52: 2262.4 | M52: =Tabela224657891011[[#This Row],[VENDA]]+Tabela224657891011[[#This Row],[MÃO DE OBRA]]-Tabela224657891011[[#This Row],[VALOR PAGO]] -> 0
B53: STK | C53: 23260 | D53: 4879 | E53: 46160 | F53: MARIOTTA | G53: SILVANO | H53: 2262.4 | J53: 46181 | K53: 46181 | L53: 2262.4 | M53: =Tabela224657891011[[#This Row],[VENDA]]+Tabela224657891011[[#This Row],[MÃO DE OBRA]]-Tabela224657891011[[#This Row],[VALOR PAGO]] -> 0
B54: STK | C54: 23260 | D54: 4879 | E54: 46160 | F54: MARIOTTA | G54: SILVANO | H54: 2262.4 | J54: 46188 | K54: 46188 | L54: 2262.4 | M54: =Tabela224657891011[[#This Row],[VENDA]]+Tabela224657891011[[#This Row],[MÃO DE OBRA]]-Tabela224657891011[[#This Row],[VALOR PAGO]] -> 0
B55: SMART | C55: 23263 | D55: 4829 | E55: 46160 | F55: LC COMPONENTES | G55: MARCELO | I55: 1407.78 | J55: 46181 | K55: 46181 | L55: 1407.78 | M55: =Tabela224657891011[[#This Row],[VENDA]]+Tabela224657891011[[#This Row],[MÃO DE OBRA]]-Tabela224657891011[[#This Row],[VALOR PAGO]] -> 0
B56: SMART | C56: 23303 | D56: 4894 | E56: 46162 | F56: SOARES | G56: MARCELO | I56: 598.42 | J56: 46197 | K56: 46195 | L56: 598.43 | M56: =Tabela224657891011[[#This Row],[VENDA]]+Tabela224657891011[[#This Row],[MÃO DE OBRA]]-Tabela224657891011[[#This Row],[VALOR PAGO]] -> -0.01
B57: STK | C57: 23316 | D57: 4939 | E57: 46163 | F57: MARIOTTA | G57: SILVANO | H57: 2994 | J57: 46177 | K57: 46178 | L57: 2994 | M57: =Tabela224657891011[[#This Row],[VENDA]]+Tabela224657891011[[#This Row],[MÃO DE OBRA]]-Tabela224657891011[[#This Row],[VALOR PAGO]] -> 0
B58: STK | C58: 23316 | D58: 4939 | E58: 46163 | F58: MARIOTTA | G58: SILVANO | H58: 2994 | J58: 46184 | K58: 46184 | L58: 2994 | M58: =Tabela224657891011[[#This Row],[VENDA]]+Tabela224657891011[[#This Row],[MÃO DE OBRA]]-Tabela224657891011[[#This Row],[VALOR PAGO]] -> 0
B59: STK | C59: 23316 | D59: 4939 | E59: 46163 | F59: MARIOTTA | G59: SILVANO | H59: 2994 | J59: 46191 | K59: 46191 | L59: 2994 | M59: =Tabela224657891011[[#This Row],[VENDA]]+Tabela224657891011[[#This Row],[MÃO DE OBRA]]-Tabela224657891011[[#This Row],[VALOR PAGO]] -> 0
B60: SMART | C60: 23326 | D60: 4933 | E60: 46163 | F60: SOARES | G60: MARCELO | I60: 361.1 | J60: 46191 | K60: 46191 | L60: 361.1 | M60: =Tabela224657891011[[#This Row],[VENDA]]+Tabela224657891011[[#This Row],[MÃO DE OBRA]]-Tabela224657891011[[#This Row],[VALOR PAGO]] -> 0
B61: SMART | C61: 23326 | D61: 4933 | E61: 46163 | F61: SOARES | G61: MARCELO | I61: 361.1 | J61: 46198 | K61: 46196 | L61: 361.1 | M61: =Tabela224657891011[[#This Row],[VENDA]]+Tabela224657891011[[#This Row],[MÃO DE OBRA]]-Tabela224657891011[[#This Row],[VALOR PAGO]] -> 0
B62: SMART | C62: 23326 | D62: 4933 | E62: 46163 | F62: SOARES | G62: MARCELO | I62: 361.09 | J62: 46205 | K62: 46197 | L62: 361.11 | M62: =Tabela224657891011[[#This Row],[VENDA]]+Tabela224657891011[[#This Row],[MÃO DE OBRA]]-Tabela224657891011[[#This Row],[VALOR PAGO]] -> -0.02
B63: SMART | C63: 23325 | D63: 4912 | E63: 46163 | F63: SOARES | G63: MARCELO | I63: 355.72 | J63: 46198 | K63: 46199 | L63: 355.73 | M63: =Tabela224657891011[[#This Row],[VENDA]]+Tabela224657891011[[#This Row],[MÃO DE OBRA]]-Tabela224657891011[[#This Row],[VALOR PAGO]] -> -0.01
B64: SMART | C64: 23341 | D64: 4933 | E64: 46164 | F64: SOARES | G64: MARCELO | I64: 407.9 | J64: 46199 | K64: 46195 | L64: 407.11 | M64: =Tabela224657891011[[#This Row],[VENDA]]+Tabela224657891011[[#This Row],[MÃO DE OBRA]]-Tabela224657891011[[#This Row],[VALOR PAGO]] -> 0.79
B65: STK | C65: 23372 | D65: 5002 | E65: 46167 | F65: MARIOTTA | G65: SILVANO | H65: 2450.93 | J65: 46197 | K65: 46197 | L65: 2450.93 | M65: =Tabela224657891011[[#This Row],[VENDA]]+Tabela224657891011[[#This Row],[MÃO DE OBRA]]-Tabela224657891011[[#This Row],[VALOR PAGO]] -> 0
B66: STK | C66: 23372 | D66: 5002 | E66: 46167 | F66: MARIOTTA | G66: SILVANO | H66: 2450.93 | J66: 46204 | K66: 46204 | L66: 2450.93 | M66: =Tabela224657891011[[#This Row],[VENDA]]+Tabela224657891011[[#This Row],[MÃO DE OBRA]]-Tabela224657891011[[#This Row],[VALOR PAGO]] -> 0
B67: STK | C67: 23372 | D67: 5002 | E67: 46167 | F67: MARIOTTA | G67: SILVANO | H67: 2450.94 | J67: 46211 | M67: =Tabela224657891011[[#This Row],[VENDA]]+Tabela224657891011[[#This Row],[MÃO DE OBRA]]-Tabela224657891011[[#This Row],[VALOR PAGO]] -> 2450.94
B68: SMART | C68: 23376 | D68: 4913 | E68: 46167 | F68: LC COMPONENTES | G68: MARCELO | I68: 1773.09 | J68: 46188 | K68: 46188 | L68: 1773.09 | M68: =Tabela224657891011[[#This Row],[VENDA]]+Tabela224657891011[[#This Row],[MÃO DE OBRA]]-Tabela224657891011[[#This Row],[VALOR PAGO]] -> 0
B69: SMART | C69: 23377 | D69: 4933 | E69: 46167 | F69: SOARES | G69: MARCELO | I69: 265.65 | J69: 46202 | K69: 46195 | L69: 265.65 | M69: =Tabela224657891011[[#This Row],[VENDA]]+Tabela224657891011[[#This Row],[MÃO DE OBRA]]-Tabela224657891011[[#This Row],[VALOR PAGO]] -> 0
B70: SMART | C70: 23422 | D70: 5031 | E70: 46169 | F70: SOARES | G70: MARCELO | I70: 410.55 | J70: 46204 | K70: 46197 | L70: 410.55 | M70: =Tabela224657891011[[#This Row],[VENDA]]+Tabela224657891011[[#This Row],[MÃO DE OBRA]]-Tabela224657891011[[#This Row],[VALOR PAGO]] -> 0
B71: SMART | C71: 23423 | D71: 4983 | E71: 46169 | F71: SOARES | G71: MARCELO | I71: 807.87 | J71: 46197 | K71: 46195 | L71: 807.88 | M71: =Tabela224657891011[[#This Row],[VENDA]]+Tabela224657891011[[#This Row],[MÃO DE OBRA]]-Tabela224657891011[[#This Row],[VALOR PAGO]] -> -0.01
B72: SMART | C72: 23423 | D72: 4983 | E72: 46169 | F72: SOARES | G72: MARCELO | I72: 807.87 | J72: 46204 | K72: 46197 | L72: 807.88 | M72: =Tabela224657891011[[#This Row],[VENDA]]+Tabela224657891011[[#This Row],[MÃO DE OBRA]]-Tabela224657891011[[#This Row],[VALOR PAGO]] -> -0.01
B73: SMART | C73: 23423 | D73: 4983 | E73: 46169 | F73: SOARES | G73: MARCELO | I73: 807.88 | J73: 46211 | K73: 46205 | L73: 807.87 | M73: =Tabela224657891011[[#This Row],[VENDA]]+Tabela224657891011[[#This Row],[MÃO DE OBRA]]-Tabela224657891011[[#This Row],[VALOR PAGO]] -> 0.01
B74: STK | C74: 23466 | D74: 5070 | E74: 46171 | F74: SELTEN | G74: FERNANDO | H74: 752 | J74: 46231 | M74: =Tabela224657891011[[#This Row],[VENDA]]+Tabela224657891011[[#This Row],[MÃO DE OBRA]]-Tabela224657891011[[#This Row],[VALOR PAGO]] -> 752
M75: =Tabela224657891011[[#This Row],[VENDA]]+Tabela224657891011[[#This Row],[MÃO DE OBRA]]-Tabela224657891011[[#This Row],[VALOR PAGO]] -> 0
M76: =Tabela224657891011[[#This Row],[VENDA]]+Tabela224657891011[[#This Row],[MÃO DE OBRA]]-Tabela224657891011[[#This Row],[VALOR PAGO]] -> 0
M77: =Tabela224657891011[[#This Row],[VENDA]]+Tabela224657891011[[#This Row],[MÃO DE OBRA]]-Tabela224657891011[[#This Row],[VALOR PAGO]] -> 0
M78: =Tabela224657891011[[#This Row],[VENDA]]+Tabela224657891011[[#This Row],[MÃO DE OBRA]]-Tabela224657891011[[#This Row],[VALOR PAGO]] -> 0
M79: =Tabela224657891011[[#This Row],[VENDA]]+Tabela224657891011[[#This Row],[MÃO DE OBRA]]-Tabela224657891011[[#This Row],[VALOR PAGO]] -> 0
M80: =Tabela224657891011[[#This Row],[VENDA]]+Tabela224657891011[[#This Row],[MÃO DE OBRA]]-Tabela224657891011[[#This Row],[VALOR PAGO]] -> 0
B82: TOTAL VENDA: | D82: =Tabela224657891011[[#Totals],[VENDA]] -> 0 | H82: =SUM(H21:H81) -> 89759.77 | I82: =SUM(Tabela224657891011[MÃO DE OBRA]) -> 17719.415
B83: TOTAL MÃO DE OBRA: | D83: =Tabela224657891011[[#Totals],[MÃO DE OBRA]] -> 0
B84: TOTAL: | C84: =SUM(D82+D83) -> 0 | F84: TOTAL RECEBIDO: | H84: =Tabela224657891011[[#Totals],[VALOR PAGO]] -> 0 | J84: TOTAL À RECEBER: | L84: =Tabela224657891011[[#Totals],[VALOR EM ABERTO]] -> 0

Sheet Junho 2026
B2: FRETES
B4: MÊS | C4: SMART | H4: STK
C5: 2023 | D5: 2024 | E5: 2025 | F5: 2026 | G5: 2027 | H5: 2025 | I5: 2026 | J5: 2027 | K5: 2028 | L5: 2029 | M5: 2030
B6: JANEIRO | C6: 126073.37 | D6: 270562.53 | E6: 49887.66 | F6: =Tabela224657[[#Totals],[VENDA]]+Tabela224657[[#Totals],[MÃO DE OBRA]] -> 50516.042 | G6: 0 | H6: 0 | I6: 0 | J6: 0 | K6: 0 | L6: 0 | M6: 0
B7: FEVEREIRO | C7: 166235.96 | D7: 324984.97 | E7: 15513.83 | F7: =Tabela2246578[[#Totals],[VENDA]]+Tabela2246578[[#Totals],[MÃO DE OBRA]] -> 65390.11 | G7: 0 | H7: 0 | I7: 0 | J7: 0 | K7: 0 | L7: 0 | M7: 0
B8: MARÇO | C8: 119814.85 | D8: 256001.57 | E8: 32410.22 | F8: ='Março 2026'!H109+'Março 2026'!I109 -> 360332.84 | G8: 0 | H8: 0 | I8: 0 | J8: 0 | K8: 0 | L8: 0 | M8: 0
B9: ABRIL | C9: 112668.22 | D9: 136419.94 | E9: 23117.53 | F9: ='Abril 2026'!H78+'Abril 2026'!I78 -> 113236.21 | G9: 0 | H9: 0 | I9: 0 | J9: 0 | K9: 0 | L9: 0 | M9: 0
B10: MAIO | C10: 39597.94 | D10: 57014.4 | E10: 11710.4 | F10: =H91+I91 -> 478840.34 | G10: 0 | H10: 0 | I10: 0 | J10: 0 | K10: 0 | L10: 0 | M10: 0
B11: JUNHO | C11: 77419.24 | D11: 259261.92 | E11: 32986.86 | F11: 0 | G11: 0 | H11: 0 | I11: 0 | J11: 0 | K11: 0 | L11: 0 | M11: 0
B12: JULHO | C12: 74963.62 | D12: 191964.91 | E12: 8086.81 | F12: 0 | G12: 0 | H12: 0 | I12: 0 | J12: 0 | K12: 0 | L12: 0 | M12: 0
B13: AGOSTO | C13: 152485.66 | D13: 273158.85 | E13: 22122.22 | F13: 0 | G13: 0 | H13: 0 | I13: 0 | J13: 0 | K13: 0 | L13: 0 | M13: 0
B14: SETEMBRO | C14: 171282.48 | D14: 63159.51 | E14: 36466.42 | F14: 0 | G14: 0 | H14: 0 | I14: 0 | J14: 0 | K14: 0 | L14: 0 | M14: 0
B15: OUTUBRO | C15: 168433.06 | D15: 53077.38 | E15: 99828 | F15: 0 | G15: 0 | I15: 0 | J15: 0 | K15: 0 | L15: 0 | M15: 0
B16: NOVEMBRO | C16: 155757.68 | D16: 15517.44 | E16: =Tabela2246[[#Totals],[VENDA]]+Tabela2246[[#Totals],[MÃO DE OBRA]] -> 381690.36 | F16: 0 | G16: 0 | H16: 0 | I16: 0 | J16: 0 | K16: 0 | L16: 0 | M16: 0
B17: DEZEMBRO | C17: 163379.08 | D17: 9580.01 | E17: =Tabela22465[[#Totals],[VENDA]]+Tabela22465[[#Totals],[MÃO DE OBRA]] -> 148680.26 | F17: 0 | G17: 0 | H17: 0 | I17: 0 | J17: 0 | K17: 0 | L17: 0 | M17: 0
B18: TOTAL | C18: =SUM(C6:C17) -> 1528111.2 | D18: =SUM(D6:D17) -> 1910703.4 | E18: =SUM(E6:E17) -> 862500.57 | F18: =SUM(F6:F17) -> 1068315.5 | G18: 0 | H18: =SUM(H6:H17) -> 0 | I18: 0 | J18: =SUM(J6:J17) -> 0 | K18: 0 | L18: =SUM(L6:L17) -> 0 | M18: 0
B19: TOTAL CONSOLIDADO 2026: | D19: =SUM(I18+F18) -> 1068315.5
B20: EMPRESA | C20: NOTA FISCAL | D20: PEDIDO | E20: DATA DE EMISSÃO | F20: DESTINATÁRIO | G20: REPRESENTANTE | H20: VENDA | I20: MÃO DE OBRA | J20: VENCIMENTO | K20: DATA DE PAGAMENTO | L20: VALOR PAGO | M20: VALOR EM ABERTO | N20: Coluna1
B21: STK | C21: 917 | D21: 895 | E21: 46178 | F21: MARIOTTA | G21: SILVANO | H21: 2784 | J21: 46220 | M21: =Tabela22465789101112[[#This Row],[VENDA]]+Tabela22465789101112[[#This Row],[MÃO DE OBRA]]-Tabela22465789101112[[#This Row],[VALOR PAGO]] -> 2784
B22: SMART | C22: 23578 | D22: 5141 | E22: 46181 | F22: SOARES | G22: MARCELO | I22: 270.82 | J22: 46209 | K22: 46205 | L22: 270.83 | M22: =Tabela22465789101112[[#This Row],[VENDA]]+Tabela22465789101112[[#This Row],[MÃO DE OBRA]]-Tabela22465789101112[[#This Row],[VALOR PAGO]] -> -0.01
B23: SMART | C23: 23579 | D23: 5166 | E23: 46181 | F23: SOARES | G23: MARCELO | I23: 506 | J23: 46209 | K23: 46205 | L23: 506 | M23: =Tabela22465789101112[[#This Row],[VENDA]]+Tabela22465789101112[[#This Row],[MÃO DE OBRA]]-Tabela22465789101112[[#This Row],[VALOR PAGO]] -> 0
B24: SMART | C24: 23579 | D24: 5166 | E24: 46181 | F24: SOARES | G24: MARCELO | I24: 506 | J24: 46216 | K24: 46205 | L24: 506 | M24: =Tabela22465789101112[[#This Row],[VENDA]]+Tabela22465789101112[[#This Row],[MÃO DE OBRA]]-Tabela22465789101112[[#This Row],[VALOR PAGO]] -> 0
B25: SMART | C25: 23579 | D25: 5166 | E25: 46181 | F25: SOARES | G25: MARCELO | I25: 505.99 | J25: 46223 | K25: 46205 | L25: 506.01 | M25: =Tabela22465789101112[[#This Row],[VENDA]]+Tabela22465789101112[[#This Row],[MÃO DE OBRA]]-Tabela22465789101112[[#This Row],[VALOR PAGO]] -> -0.02
B26: SMART | C26: 23597 | D26: 5166 | E26: 46182 | F26: SOARES | G26: MARCELO | I26: 407.1 | J26: 46217 | K26: 46205 | L26: 407.1 | M26: =Tabela22465789101112[[#This Row],[VENDA]]+Tabela22465789101112[[#This Row],[MÃO DE OBRA]]-Tabela22465789101112[[#This Row],[VALOR PAGO]] -> 0
B27: STK | C27: 23605 | D27: 5205 | E27: 46183 | F27: NHTEX | G27: HENRIQUE | H27: 795 | J27: 46183 | K27: 46183 | M27: =Tabela22465789101112[[#This Row],[VENDA]]+Tabela22465789101112[[#This Row],[MÃO DE OBRA]]-Tabela22465789101112[[#This Row],[VALOR PAGO]] -> 795
B28: SMART | C28: 23628 | D28: 5053 | E28: 46183 | F28: SOARES | G28: MARCELO | I28: 150.1 | J28: 46218 | K28: 46205 | L28: 150.1 | M28: =Tabela22465789101112[[#This Row],[VENDA]]+Tabela22465789101112[[#This Row],[MÃO DE OBRA]]-Tabela22465789101112[[#This Row],[VALOR PAGO]] -> 0
B29: STK | C29: 23750 | D29: 5200 | E29: 46189 | F29: SELTEN | G29: FERNANDO | H29: 877.33 | J29: 46204 | M29: =Tabela22465789101112[[#This Row],[VENDA]]+Tabela22465789101112[[#This Row],[MÃO DE OBRA]]-Tabela22465789101112[[#This Row],[VALOR PAGO]] -> 877.33
B30: STK | C30: 23750 | D30: 5200 | E30: 46189 | F30: SELTEN | G30: FERNANDO | H30: 877.33 | J30: 46219 | M30: =Tabela22465789101112[[#This Row],[VENDA]]+Tabela22465789101112[[#This Row],[MÃO DE OBRA]]-Tabela22465789101112[[#This Row],[VALOR PAGO]] -> 877.33
B31: STK | C31: 23750 | D31: 5200 | E31: 46189 | F31: SELTEN | G31: FERNANDO | H31: 877.34 | J31: 46234 | M31: =Tabela22465789101112[[#This Row],[VENDA]]+Tabela22465789101112[[#This Row],[MÃO DE OBRA]]-Tabela22465789101112[[#This Row],[VALOR PAGO]] -> 877.34
B32: STK | C32: 23737 | D32: 5321 | E32: 46189 | F32: NHTEX | G32: HENRIQUE | H32: 397.5 | J32: 46196 | M32: =Tabela22465789101112[[#This Row],[VENDA]]+Tabela22465789101112[[#This Row],[MÃO DE OBRA]]-Tabela22465789101112[[#This Row],[VALOR PAGO]] -> 397.5
B33: STK | C33: 23773 | D33: 5398 | E33: 46190 | F33: MARIOTTA | G33: SILVANO | H33: 1275 | J33: 46211 | M33: =Tabela22465789101112[[#This Row],[VENDA]]+Tabela22465789101112[[#This Row],[MÃO DE OBRA]]-Tabela22465789101112[[#This Row],[VALOR PAGO]] -> 1275
B34: STK | C34: 23773 | D34: 5398 | E34: 46190 | F34: MARIOTTA | G34: SILVANO | H34: 1275 | J34: 46218 | M34: =Tabela22465789101112[[#This Row],[VENDA]]+Tabela22465789101112[[#This Row],[MÃO DE OBRA]]-Tabela22465789101112[[#This Row],[VALOR PAGO]] -> 1275
B35: SMART | C35: 23809 | D35: 5278 | E35: 46191 | F35: SOARES | G35: MARCELO | I35: 1236.24 | J35: 46219 | K35: 46205 | L35: 1236.26 | M35: =Tabela22465789101112[[#This Row],[VENDA]]+Tabela22465789101112[[#This Row],[MÃO DE OBRA]]-Tabela22465789101112[[#This Row],[VALOR PAGO]] -> -0.02
B36: SMART | C36: 23809 | D36: 5278 | E36: 46191 | F36: SOARES | G36: MARCELO | I36: 1236.24 | J36: 46226 | K36: 46205 | L36: 1236.26 | M36: =Tabela22465789101112[[#This Row],[VENDA]]+Tabela22465789101112[[#This Row],[MÃO DE OBRA]]-Tabela22465789101112[[#This Row],[VALOR PAGO]] -> -0.02
B37: SMART | C37: 23809 | D37: 5278 | E37: 46191 | F37: SOARES | G37: MARCELO | I37: 1236.25 | J37: 46233 | M37: =Tabela22465789101112[[#This Row],[VENDA]]+Tabela22465789101112[[#This Row],[MÃO DE OBRA]]-Tabela22465789101112[[#This Row],[VALOR PAGO]] -> 1236.25
B38: STK | C38: 23838 | D38: 5383 | E38: 46192 | F38: MARIOTTA | G38: SILVANO | H38: 2610 | J38: 46237 | M38: =Tabela22465789101112[[#This Row],[VENDA]]+Tabela22465789101112[[#This Row],[MÃO DE OBRA]]-Tabela22465789101112[[#This Row],[VALOR PAGO]] -> 2610
B39: STK | C39: 934 | D39: 908 | E39: 46195 | F39: COMÉRCIO SANTOS | G39: MARCIANO | H39: 11172 | J39: 46216 | M39: ='Julho 2026'!M35 -> 7502.2
B40: STK | C40: 934 | D40: 908 | E40: 46195 | F40: COMÉRCIO SANTOS | G40: MARCIANO | H40: 11172 | J40: 46223 | M40: =Tabela22465789101112[[#This Row],[VENDA]]+Tabela22465789101112[[#This Row],[MÃO DE OBRA]]-Tabela22465789101112[[#This Row],[VALOR PAGO]] -> 11172
B41: STK | C41: 934 | D41: 908 | E41: 46195 | F41: COMÉRCIO SANTOS | G41: MARCIANO | H41: 11172 | J41: 46230 | M41: =Tabela22465789101112[[#This Row],[VENDA]]+Tabela22465789101112[[#This Row],[MÃO DE OBRA]]-Tabela22465789101112[[#This Row],[VALOR PAGO]] -> 11172
B42: STK | C42: 934 | D42: 908 | E42: 46195 | F42: COMÉRCIO SANTOS | G42: MARCIANO | H42: 11172 | J42: 46237 | M42: =Tabela22465789101112[[#This Row],[VENDA]]+Tabela22465789101112[[#This Row],[MÃO DE OBRA]]-Tabela22465789101112[[#This Row],[VALOR PAGO]] -> 11172
B43: STK | C43: 934 | D43: 908 | E43: 46195 | F43: COMÉRCIO SANTOS | G43: MARCIANO | H43: 11172 | J43: 46244 | M43: =Tabela22465789101112[[#This Row],[VENDA]]+Tabela22465789101112[[#This Row],[MÃO DE OBRA]]-Tabela22465789101112[[#This Row],[VALOR PAGO]] -> 11172
B44: STK | C44: 934 | D44: 908 | E44: 46195 | F44: COMÉRCIO SANTOS | G44: MARCIANO | H44: 11172 | J44: 46251 | M44: =Tabela22465789101112[[#This Row],[VENDA]]+Tabela22465789101112[[#This Row],[MÃO DE OBRA]]-Tabela22465789101112[[#This Row],[VALOR PAGO]] -> 11172
B45: STK | C45: 935 | D45: 909 | E45: 46195 | F45: RM CALCADOS | G45: MARCIANO | H45: 9418.4 | J45: 46216 | M45: =Tabela22465789101112[[#This Row],[VENDA]]+Tabela22465789101112[[#This Row],[MÃO DE OBRA]]-Tabela22465789101112[[#This Row],[VALOR PAGO]] -> 9418.4
B46: STK | C46: 935 | D46: 909 | E46: 46195 | F46: RM CALCADOS | G46: MARCIANO | H46: 9416 | J46: 46223 | M46: =Tabela22465789101112[[#This Row],[VENDA]]+Tabela22465789101112[[#This Row],[MÃO DE OBRA]]-Tabela22465789101112[[#This Row],[VALOR PAGO]] -> 9416
B47: STK | C47: 935 | D47: 909 | E47: 46195 | F47: RM CALCADOS | G47: MARCIANO | H47: 9416 | J47: 46230 | M47: =Tabela22465789101112[[#This Row],[VENDA]]+Tabela22465789101112[[#This Row],[MÃO DE OBRA]]-Tabela22465789101112[[#This Row],[VALOR PAGO]] -> 9416
B48: STK | C48: 935 | D48: 909 | E48: 46195 | F48: RM CALCADOS | G48: MARCIANO | H48: 9416 | J48: 46237 | M48: =Tabela22465789101112[[#This Row],[VENDA]]+Tabela22465789101112[[#This Row],[MÃO DE OBRA]]-Tabela22465789101112[[#This Row],[VALOR PAGO]] -> 9416
B49: STK | C49: 935 | D49: 909 | E49: 46195 | F49: RM CALCADOS | G49: MARCIANO | H49: 9416 | J49: 46244 | M49: =Tabela22465789101112[[#This Row],[VENDA]]+Tabela22465789101112[[#This Row],[MÃO DE OBRA]]-Tabela22465789101112[[#This Row],[VALOR PAGO]] -> 9416
B50: STK | C50: 935 | D50: 909 | E50: 46195 | F50: RM CALCADOS | G50: MARCIANO | H50: 9416 | J50: 46251 | M50: =Tabela22465789101112[[#This Row],[VENDA]]+Tabela22465789101112[[#This Row],[MÃO DE OBRA]]-Tabela22465789101112[[#This Row],[VALOR PAGO]] -> 9416
B51: STK | C51: 936 | D51: 910 | E51: 46195 | F51: ADMX | G51: MARCIANO | H51: 11691.22 | J51: 46216 | M51: =Tabela22465789101112[[#This Row],[VENDA]]+Tabela22465789101112[[#This Row],[MÃO DE OBRA]]-Tabela22465789101112[[#This Row],[VALOR PAGO]] -> 11691.22
... B56: STK | C56: 936 | D56: 910 | E56: 46195 | F56: ADMX | G56: MARCIANO | H56: 11689 | J56: 46251 | M56: =Tabela22465789101112[[#This Row],[VENDA]]+Tabela22465789101112[[#This Row],[MÃO DE OBRA]]-Tabela22465789101112[[#This Row],[VALOR PAGO]] -> 11689
B57: SMART | C57: 23872 | D57: 5336 | E57: 46195 | F57: SOARES | G57: MARCELO | I57: 573.07 | J57: 46223 | K57: 46205 | L57: 573.07 | M57: =Tabela22465789101112[[#This Row],[VENDA]]+Tabela22465789101112[[#This Row],[MÃO DE OBRA]]-Tabela22465789101112[[#This Row],[VALOR PAGO]] -> 0
B58: SMART | C58: 23872 | D58: 5336 | E58: 46195 | F58: SOARES | G58: MARCELO | I58: 573.07 | J58: 46230 | K58: 46205 | L58: 459.55 | M58: =Tabela22465789101112[[#This Row],[VENDA]]+Tabela22465789101112[[#This Row],[MÃO DE OBRA]]-Tabela22465789101112[[#This Row],[VALOR PAGO]] -> 113.52
B59: SMART | C59: 23872 | D59: 5336 | E59: 46195 | F59: SOARES | G59: MARCELO | I59: 573.06 | J59: 46237 | M59: =Tabela22465789101112[[#This Row],[VENDA]]+Tabela22465789101112[[#This Row],[MÃO DE OBRA]]-Tabela22465789101112[[#This Row],[VALOR PAGO]] -> 573.06
B60: STK | C60: 939 | D60: 917 | E60: 46196 | F60: ADMX | G60: MARCIANO | H60: 8144.5 | J60: 46220 | M60: =Tabela22465789101112[[#This Row],[VENDA]]+Tabela22465789101112[[#This Row],[MÃO DE OBRA]]-Tabela22465789101112[[#This Row],[VALOR PAGO]] -> 8144.5
B61: STK | C61: 939 | D61: 917 | E61: 46196 | F61: ADMX | G61: MARCIANO | H61: 8143 | J61: 46224 | M61: =Tabela22465789101112[[#This Row],[VENDA]]+Tabela22465789101112[[#This Row],[MÃO DE OBRA]]-Tabela22465789101112[[#This Row],[VALOR PAGO]] -> 8143
B62: STK | C62: 939 | D62: 917 | E62: 46196 | F62: ADMX | G62: MARCIANO | H62: 8143 | J62: 46231 | M62: =Tabela22465789101112[[#This Row],[VENDA]]+Tabela22465789101112[[#This Row],[MÃO DE OBRA]]-Tabela22465789101112[[#This Row],[VALOR PAGO]] -> 8143
B63: STK | C63: 939 | D63: 917 | E63: 46196 | F63: ADMX | G63: MARCIANO | H63: 8143 | J63: 46238 | M63: =Tabela22465789101112[[#This Row],[VENDA]]+Tabela22465789101112[[#This Row],[MÃO DE OBRA]]-Tabela22465789101112[[#This Row],[VALOR PAGO]] -> 8143
B64: STK | C64: 939 | D64: 917 | E64: 46196 | F64: ADMX | G64: MARCIANO | H64: 8143 | J64: 46245 | M64: =Tabela22465789101112[[#This Row],[VENDA]]+Tabela22465789101112[[#This Row],[MÃO DE OBRA]]-Tabela22465789101112[[#This Row],[VALOR PAGO]] -> 8143
B65: STK | C65: 939 | D65: 917 | E65: 46196 | F65: ADMX | G65: MARCIANO | H65: 8143 | J65: 46252 | M65: =Tabela22465789101112[[#This Row],[VENDA]]+Tabela22465789101112[[#This Row],[MÃO DE OBRA]]-Tabela22465789101112[[#This Row],[VALOR PAGO]] -> 8143
B66: STK | C66: 940 | D66: 918 | E66: 46196 | F66: ADMX | G66: MARCIANO | H66: 18261.25 | J66: 46211 | M66: =Tabela22465789101112[[#This Row],[VENDA]]+Tabela22465789101112[[#This Row],[MÃO DE OBRA]]-Tabela22465789101112[[#This Row],[VALOR PAGO]] -> 18261.25
B67: STK | C67: 940 | D67: 918 | E67: 46196 | F67: ADMX | G67: MARCIANO | H67: 18260 | J67: 46226 | M67: =Tabela22465789101112[[#This Row],[VENDA]]+Tabela22465789101112[[#This Row],[MÃO DE OBRA]]-Tabela22465789101112[[#This Row],[VALOR PAGO]] -> 18260
B68: STK | C68: 940 | D68: 918 | E68: 46196 | F68: ADMX | G68: MARCIANO | H68: 18260 | J68: 46241 | M68: =Tabela22465789101112[[#This Row],[VENDA]]+Tabela22465789101112[[#This Row],[MÃO DE OBRA]]-Tabela22465789101112[[#This Row],[VALOR PAGO]] -> 18260
B69: STK | C69: 940 | D69: 918 | E69: 46196 | F69: ADMX | G69: MARCIANO | H69: 18260 | J69: 46256 | M69: =Tabela22465789101112[[#This Row],[VENDA]]+Tabela22465789101112[[#This Row],[MÃO DE OBRA]]-Tabela22465789101112[[#This Row],[VALOR PAGO]] -> 18260
B70: STK | C70: 940 | D70: 918 | E70: 46196 | F70: ADMX | G70: MARCIANO | H70: 18260 | J70: 46271 | M70: =Tabela22465789101112[[#This Row],[VENDA]]+Tabela22465789101112[[#This Row],[MÃO DE OBRA]]-Tabela22465789101112[[#This Row],[VALOR PAGO]] -> 18260
B71: STK | C71: 940 | D71: 918 | E71: 46196 | F71: ADMX | G71: MARCIANO | H71: 18260 | J71: 46286 | M71: =Tabela22465789101112[[#This Row],[VENDA]]+Tabela22465789101112[[#This Row],[MÃO DE OBRA]]-Tabela22465789101112[[#This Row],[VALOR PAGO]] -> 18260
... B76: STK | C76: 941 | D76: 915 | E76: 46196 | F76: ADMX | G76: MARCIANO | H76: 21949 | J76: 46331 | M76: =Tabela22465789101112[[#This Row],[VENDA]]+Tabela22465789101112[[#This Row],[MÃO DE OBRA]]-Tabela22465789101112[[#This Row],[VALOR PAGO]] -> 21949
B77: SMART | C77: 23902 | D77: 5331 | E77: 46196 | F77: LC COMPONENTES | G77: MARCELO | I77: 1020.2 | J77: 46217 | K77: 46217 | L77: 1020.2 | M77: =Tabela22465789101112[[#This Row],[VENDA]]+Tabela22465789101112[[#This Row],[MÃO DE OBRA]]-Tabela22465789101112[[#This Row],[VALOR PAGO]] -> 0
B78: SMART | C78: 23898 | D78: 5305 | E78: 46196 | F78: LC COMPONENTES | G78: MARCELO | I78: 1746.36 | J78: 46217 | K78: 46217 | L78: 1746.36 | M78: =Tabela22465789101112[[#This Row],[VENDA]]+Tabela22465789101112[[#This Row],[MÃO DE OBRA]]-Tabela22465789101112[[#This Row],[VALOR PAGO]] -> 0
B79: SMART | C79: 23965 | D79: 5394 | E79: 46198 | F79: SOARES | G79: MARCELO | I79: 229.42 | J79: 46226 | K79: 46205 | L79: 229.43 | M79: =Tabela22465789101112[[#This Row],[VENDA]]+Tabela22465789101112[[#This Row],[MÃO DE OBRA]]-Tabela22465789101112[[#This Row],[VALOR PAGO]] -> -0.01
B80: SMART | C80: 23965 | D80: 5394 | E80: 46198 | F80: SOARES | G80: MARCELO | I80: 229.42 | J80: 46233 | M80: =Tabela22465789101112[[#This Row],[VENDA]]+Tabela22465789101112[[#This Row],[MÃO DE OBRA]]-Tabela22465789101112[[#This Row],[VALOR PAGO]] -> 229.42
B81: SMART | C81: 23965 | D81: 5394 | E81: 46198 | F81: SOARES | G81: MARCELO | I81: 229.43 | J81: 46240 | M81: =Tabela22465789101112[[#This Row],[VENDA]]+Tabela22465789101112[[#This Row],[MÃO DE OBRA]]-Tabela22465789101112[[#This Row],[VALOR PAGO]] -> 229.43
B82: SMART | C82: 23940 | D82: 5301 | E82: 46198 | F82: LC COMPONENTES | G82: MARCELO | I82: 1386.45 | J82: 46219 | K82: 46219 | L82: 1386.45 | M82: =Tabela22465789101112[[#This Row],[VENDA]]+Tabela22465789101112[[#This Row],[MÃO DE OBRA]]-Tabela22465789101112[[#This Row],[VALOR PAGO]] -> 0
M83: =Tabela22465789101112[[#This Row],[VENDA]]+Tabela22465789101112[[#This Row],[MÃO DE OBRA]]-Tabela22465789101112[[#This Row],[VALOR PAGO]] -> 0
M84: =Tabela22465789101112[[#This Row],[VENDA]]+Tabela22465789101112[[#This Row],[MÃO DE OBRA]]-Tabela22465789101112[[#This Row],[VALOR PAGO]] -> 0
M85: =Tabela22465789101112[[#This Row],[VENDA]]+Tabela22465789101112[[#This Row],[MÃO DE OBRA]]-Tabela22465789101112[[#This Row],[VALOR PAGO]] -> 0
M86: =Tabela22465789101112[[#This Row],[VENDA]]+Tabela22465789101112[[#This Row],[MÃO DE OBRA]]-Tabela22465789101112[[#This Row],[VALOR PAGO]] -> 0
M87: =Tabela22465789101112[[#This Row],[VENDA]]+Tabela22465789101112[[#This Row],[MÃO DE OBRA]]-Tabela22465789101112[[#This Row],[VALOR PAGO]] -> 0
M88: =Tabela22465789101112[[#This Row],[VENDA]]+Tabela22465789101112[[#This Row],[MÃO DE OBRA]]-Tabela22465789101112[[#This Row],[VALOR PAGO]] -> 0
M89: =Tabela22465789101112[[#This Row],[VENDA]]+Tabela22465789101112[[#This Row],[MÃO DE OBRA]]-Tabela22465789101112[[#This Row],[VALOR PAGO]] -> 0
B91: TOTAL VENDA: | D91: =Tabela22465789101112[[#Totals],[VENDA]] -> 0 | H91: =SUM(H21:H90) -> 466225.12 | I91: =SUM(Tabela22465789101112[MÃO DE OBRA]) -> 12615.22
B92: TOTAL MÃO DE OBRA: | D92: =Tabela22465789101112[[#Totals],[MÃO DE OBRA]] -> 0
B93: TOTAL: | C93: =SUM(D91+D92) -> 0 | F93: TOTAL RECEBIDO: | H93: =Tabela22465789101112[[#Totals],[VALOR PAGO]] -> 0 | J93: TOTAL À RECEBER: | L93: =Tabela22465789101112[[#Totals],[VALOR EM ABERTO]] -> 0

Sheet Julho 2026
B2: FRETES
B4: MÊS | C4: SMART | H4: STK
C5: 2023 | D5: 2024 | E5: 2025 | F5: 2026 | G5: 2027 | H5: 2025 | I5: 2026 | J5: 2027 | K5: 2028 | L5: 2029 | M5: 2030
B6: JANEIRO | C6: 126073.37 | D6: 270562.53 | E6: 49887.66 | F6: =Tabela224657[[#Totals],[VENDA]]+Tabela224657[[#Totals],[MÃO DE OBRA]] -> 50516.042 | G6: 0 | H6: 0 | I6: 0 | J6: 0 | K6: 0 | L6: 0 | M6: 0
B7: FEVEREIRO | C7: 166235.96 | D7: 324984.97 | E7: 15513.83 | F7: =Tabela2246578[[#Totals],[VENDA]]+Tabela2246578[[#Totals],[MÃO DE OBRA]] -> 65390.11 | G7: 0 | H7: 0 | I7: 0 | J7: 0 | K7: 0 | L7: 0 | M7: 0
B8: MARÇO | C8: 119814.85 | D8: 256001.57 | E8: 32410.22 | F8: ='Março 2026'!H109+'Março 2026'!I109 -> 360332.84 | G8: 0 | H8: 0 | I8: 0 | J8: 0 | K8: 0 | L8: 0 | M8: 0
B9: ABRIL | C9: 112668.22 | D9: 136419.94 | E9: 23117.53 | F9: ='Abril 2026'!H78+'Abril 2026'!I78 -> 113236.21 | G9: 0 | H9: 0 | I9: 0 | J9: 0 | K9: 0 | L9: 0 | M9: 0
B10: MAIO | C10: 39597.94 | D10: 57014.4 | E10: 11710.4 | F10: =H99+I99 -> 354642.22 | G10: 0 | H10: 0 | I10: 0 | J10: 0 | K10: 0 | L10: 0 | M10: 0
B11: JUNHO | C11: 77419.24 | D11: 259261.92 | E11: 32986.86 | F11: 0 | G11: 0 | H11: 0 | I11: 0 | J11: 0 | K11: 0 | L11: 0 | M11: 0
B12: JULHO | C12: 74963.62 | D12: 191964.91 | E12: 8086.81 | F12: 0 | G12: 0 | H12: 0 | I12: 0 | J12: 0 | K12: 0 | L12: 0 | M12: 0
B13: AGOSTO | C13: 152485.66 | D13: 273158.85 | E13: 22122.22 | F13: 0 | G13: 0 | H13: 0 | I13: 0 | J13: 0 | K13: 0 | L13: 0 | M13: 0
B14: SETEMBRO | C14: 171282.48 | D14: 63159.51 | E14: 36466.42 | F14: 0 | G14: 0 | H14: 0 | I14: 0 | J14: 0 | K14: 0 | L14: 0 | M14: 0
B15: OUTUBRO | C15: 168433.06 | D15: 53077.38 | E15: 99828 | F15: 0 | G15: 0 | I15: 0 | J15: 0 | K15: 0 | L15: 0 | M15: 0
B16: NOVEMBRO | C16: 155757.68 | D16: 15517.44 | E16: =Tabela2246[[#Totals],[VENDA]]+Tabela2246[[#Totals],[MÃO DE OBRA]] -> 381690.36 | F16: 0 | G16: 0 | H16: 0 | I16: 0 | J16: 0 | K16: 0 | L16: 0 | M16: 0
B17: DEZEMBRO | C17: 163379.08 | D17: 9580.01 | E17: =Tabela22465[[#Totals],[VENDA]]+Tabela22465[[#Totals],[MÃO DE OBRA]] -> 148680.26 | F17: 0 | G17: 0 | H17: 0 | I17: 0 | J17: 0 | K17: 0 | L17: 0 | M17: 0
B18: TOTAL | C18: =SUM(C6:C17) -> 1528111.2 | D18: =SUM(D6:D17) -> 1910703.4 | E18: =SUM(E6:E17) -> 862500.57 | F18: =SUM(F6:F17) -> 944117.43 | G18: 0 | H18: =SUM(H6:H17) -> 0 | I18: 0 | J18: =SUM(J6:J17) -> 0 | K18: 0 | L18: =SUM(L6:L17) -> 0 | M18: 0
B19: TOTAL CONSOLIDADO 2026: | D19: =SUM(I18+F18) -> 944117.43
B20: EMPRESA | C20: NOTA FISCAL | D20: PEDIDO | E20: DATA DE EMISSÃO | F20: DESTINATÁRIO | G20: REPRESENTANTE | H20: VENDA | I20: MÃO DE OBRA | J20: VENCIMENTO | K20: DATA DE PAGAMENTO | L20: VALOR PAGO | M20: VALOR EM ABERTO | N20: Coluna1
B21: SMART | C21: 24103 | D21: 5438 | E21: 46205 | F21: LC COMPONENTES | G21: MARCELO | I21: 4602.01 | J21: 46226
B22: SMART | C22: 24105 | D22: 5513 | E22: 46205 | F22: LC COMPONENTES | G22: MARCELO | I22: 7087.9 | J22: 46226 | M22: =Tabela2246578910111213[[#This Row],[VENDA]]+Tabela2246578910111213[[#This Row],[MÃO DE OBRA]]-Tabela2246578910111213[[#This Row],[VALOR PAGO]] -> 7087.9
B23: SMART | C23: 24106 | D23: 5526 | E23: 46205 | F23: SOARES | G23: MARCELO | I23: 407.1 | J23: 46205 | M23: =Tabela2246578910111213[[#This Row],[VENDA]]+Tabela2246578910111213[[#This Row],[MÃO DE OBRA]]-Tabela2246578910111213[[#This Row],[VALOR PAGO]] -> 407.1
B24: STK | C24: 21143 | D24: 5648 | E24: 46206 | F24: MARIOTTA | G24: SILVANO | H24: 15623.73 | J24: 46221 | M24: =Tabela2246578910111213[[#This Row],[VENDA]]+Tabela2246578910111213[[#This Row],[MÃO DE OBRA]]-Tabela2246578910111213[[#This Row],[VALOR PAGO]] -> 15623.73
B25: STK | C25: 21143 | D25: 5648 | E25: 46206 | F25: MARIOTTA | G25: SILVANO | H25: 15623.73 | J25: 46236 | M25: =Tabela2246578910111213[[#This Row],[VENDA]]+Tabela2246578910111213[[#This Row],[MÃO DE OBRA]]-Tabela2246578910111213[[#This Row],[VALOR PAGO]] -> 15623.73
B26: STK | C26: 21143 | D26: 5648 | E26: 46206 | F26: MARIOTTA | G26: SILVANO | H26: 15623.73 | J26: 46251 | M26: =Tabela2246578910111213[[#This Row],[VENDA]]+Tabela2246578910111213[[#This Row],[MÃO DE OBRA]]-Tabela2246578910111213[[#This Row],[VALOR PAGO]] -> 15623.73
B27: STK | C27: 21143 | D27: 5648 | E27: 46206 | F27: MARIOTTA | G27: SILVANO | H27: 15623.73 | J27: 46266 | M27: =Tabela2246578910111213[[#This Row],[VENDA]]+Tabela2246578910111213[[#This Row],[MÃO DE OBRA]]-Tabela2246578910111213[[#This Row],[VALOR PAGO]] -> 15623.73
B28: STK | C28: 24183 | D28: 5381 | E28: 46209 | F28: MARIOTTA | G28: SILVANO | H28: 5536 | J28: 46254 | M28: =Tabela2246578910111213[[#This Row],[VENDA]]+Tabela2246578910111213[[#This Row],[MÃO DE OBRA]]-Tabela2246578910111213[[#This Row],[VALOR PAGO]] -> 5536
B29: SMART | C29: 24225 | D29: 5526 | E29: 46210 | F29: SOARES | G29: MARCELO | I29: 1972.82 | J29: 46238 | M29: =Tabela2246578910111213[[#This Row],[VENDA]]+Tabela2246578910111213[[#This Row],[MÃO DE OBRA]]-Tabela2246578910111213[[#This Row],[VALOR PAGO]] -> 1972.82
B30: SMART | C30: 24225 | D30: 5526 | E30: 46210 | F30: SOARES | G30: MARCELO | I30: 1972.82 | J30: 46245 | M30: =Tabela2246578910111213[[#This Row],[VENDA]]+Tabela2246578910111213[[#This Row],[MÃO DE OBRA]]-Tabela2246578910111213[[#This Row],[VALOR PAGO]] -> 1972.82
B31: SMART | C31: 24225 | D31: 5526 | E31: 46210 | F31: SOARES | G31: MARCELO | I31: 1972.82 | J31: 46252 | M31: =Tabela2246578910111213[[#This Row],[VENDA]]+Tabela2246578910111213[[#This Row],[MÃO DE OBRA]]-Tabela2246578910111213[[#This Row],[VALOR PAGO]] -> 1972.82
B32: SMART | C32: 24226 | D32: 5600 | E32: 46210 | F32: SOARES | G32: MARCELO | I32: 577.87 | J32: 46238 | M32: =Tabela2246578910111213[[#This Row],[VENDA]]+Tabela2246578910111213[[#This Row],[MÃO DE OBRA]]-Tabela2246578910111213[[#This Row],[VALOR PAGO]] -> 577.87
B33: SMART | C33: 24226 | D33: 5600 | E33: 46210 | F33: SOARES | G33: MARCELO | I33: 577.87 | J33: 46245 | M33: =Tabela2246578910111213[[#This Row],[VENDA]]+Tabela2246578910111213[[#This Row],[MÃO DE OBRA]]-Tabela2246578910111213[[#This Row],[VALOR PAGO]] -> 577.87
B34: SMART | C34: 24226 | D34: 5600 | E34: 46210 | F34: SOARES | G34: MARCELO | I34: 577.88 | J34: 46252 | M34: =Tabela2246578910111213[[#This Row],[VENDA]]+Tabela2246578910111213[[#This Row],[MÃO DE OBRA]]-Tabela2246578910111213[[#This Row],[VALOR PAGO]] -> 577.88
B35: STK | C35: 960 | D35: 936 | E35: 46212 | F35: RM CALCADOS | G35: MARCIANO | H35: 7502.2 | J35: 46233 | M35: =Tabela2246578910111213[[#This Row],[VENDA]]+Tabela2246578910111213[[#This Row],[MÃO DE OBRA]]-Tabela2246578910111213[[#This Row],[VALOR PAGO]] -> 7502.2
B36: STK | C36: 960 | D36: 936 | E36: 46212 | F36: RM CALCADOS | G36: MARCIANO | H36: 7501 | J36: 46240 | M36: =Tabela2246578910111213[[#This Row],[VENDA]]+Tabela2246578910111213[[#This Row],[MÃO DE OBRA]]-Tabela2246578910111213[[#This Row],[VALOR PAGO]] -> 7501
B37: STK | C37: 960 | D37: 936 | E37: 46212 | F37: RM CALCADOS | G37: MARCIANO | H37: 7501 | J37: 46247 | M37: =Tabela2246578910111213[[#This Row],[VENDA]]+Tabela2246578910111213[[#This Row],[MÃO DE OBRA]]-Tabela2246578910111213[[#This Row],[VALOR PAGO]] -> 7501
B38: STK | C38: 960 | D38: 936 | E38: 46212 | F38: RM CALCADOS | G38: MARCIANO | H38: 7501 | J38: 46254 | M38: =Tabela2246578910111213[[#This Row],[VENDA]]+Tabela2246578910111213[[#This Row],[MÃO DE OBRA]]-Tabela2246578910111213[[#This Row],[VALOR PAGO]] -> 7501
B39: STK | C39: 960 | D39: 936 | E39: 46212 | F39: RM CALCADOS | G39: MARCIANO | H39: 7501 | J39: 46261 | M39: =Tabela2246578910111213[[#This Row],[VENDA]]+Tabela2246578910111213[[#This Row],[MÃO DE OBRA]]-Tabela2246578910111213[[#This Row],[VALOR PAGO]] -> 7501
B40: STK | C40: 960 | D40: 936 | E40: 46212 | F40: RM CALCADOS | G40: MARCIANO | H40: 7501 | J40: 46268 | M40: =Tabela2246578910111213[[#This Row],[VENDA]]+Tabela2246578910111213[[#This Row],[MÃO DE OBRA]]-Tabela2246578910111213[[#This Row],[VALOR PAGO]] -> 7501
B41: STK | C41: 961 | D41: 937 | E41: 46212 | F41: ADMX | G41: MARCIANO | H41: 11970 | J41: 46233 | M41: =Tabela2246578910111213[[#This Row],[VENDA]]+Tabela2246578910111213[[#This Row],[MÃO DE OBRA]]-Tabela2246578910111213[[#This Row],[VALOR PAGO]] -> 11970
B42: STK | C42: 961 | D42: 937 | E42: 46212 | F42: ADMX | G42: MARCIANO | H42: 11970 | J42: 46240 | M42: =Tabela2246578910111213[[#This Row],[VENDA]]+Tabela2246578910111213[[#This Row],[MÃO DE OBRA]]-Tabela2246578910111213[[#This Row],[VALOR PAGO]] -> 11970
B43: STK | C43: 961 | D43: 937 | E43: 46212 | F43: ADMX | G43: MARCIANO | H43: 11970 | J43: 46247 | M43: =Tabela2246578910111213[[#This Row],[VENDA]]+Tabela2246578910111213[[#This Row],[MÃO DE OBRA]]-Tabela2246578910111213[[#This Row],[VALOR PAGO]] -> 11970
B44: STK | C44: 961 | D44: 937 | E44: 46212 | F44: ADMX | G44: MARCIANO | H44: 11970 | J44: 46254 | M44: =Tabela2246578910111213[[#This Row],[VENDA]]+Tabela2246578910111213[[#This Row],[MÃO DE OBRA]]-Tabela2246578910111213[[#This Row],[VALOR PAGO]] -> 11970
B45: STK | C45: 961 | D45: 937 | E45: 46212 | F45: ADMX | G45: MARCIANO | H45: 11970 | J45: 46261 | M45: =Tabela2246578910111213[[#This Row],[VENDA]]+Tabela2246578910111213[[#This Row],[MÃO DE OBRA]]-Tabela2246578910111213[[#This Row],[VALOR PAGO]] -> 11970
B46: STK | C46: 961 | D46: 937 | E46: 46212 | F46: ADMX | G46: MARCIANO | H46: 11970 | J46: 46268 | M46: =Tabela2246578910111213[[#This Row],[VENDA]]+Tabela2246578910111213[[#This Row],[MÃO DE OBRA]]-Tabela2246578910111213[[#This Row],[VALOR PAGO]] -> 11970
... B52: STK | C52: 962 | D52: 938 | E52: 46212 | F52: COMERCIO SANTOS | G52: MARCIANO | H52: 4293 | J52: 46268 | M52: =Tabela2246578910111213[[#This Row],[VENDA]]+Tabela2246578910111213[[#This Row],[MÃO DE OBRA]]-Tabela2246578910111213[[#This Row],[VALOR PAGO]] -> 4293
B53: STK | C53: 24315 | D53: 5727 | E53: 46213 | F53: LEANDRENSE | G53: MARCIANO | H53: =150*34.98 -> 5247 | J53: 46213 | K53: 46213 | L53: 5247 | M53: =Tabela2246578910111213[[#This Row],[VENDA]]+Tabela2246578910111213[[#This Row],[MÃO DE OBRA]]-Tabela2246578910111213[[#This Row],[VALOR PAGO]] -> 0
B54: SMART | C54: 24359 | D54: 5688 | E54: 46216 | F54: SOARES | G54: MARCELO | I54: 543.37 | J54: 46251 | M54: =Tabela2246578910111213[[#This Row],[VENDA]]+Tabela2246578910111213[[#This Row],[MÃO DE OBRA]]-Tabela2246578910111213[[#This Row],[VALOR PAGO]] -> 543.37
B55: SMART | C55: 24360 | D55: 5600 | E55: 46216 | F55: SOARES | G55: MARCELO | I55: 410.55 | J55: 46251 | M55: =Tabela2246578910111213[[#This Row],[VENDA]]+Tabela2246578910111213[[#This Row],[MÃO DE OBRA]]-Tabela2246578910111213[[#This Row],[VALOR PAGO]] -> 410.55
B56: SMART | C56: 24360 | D56: 5600 | E56: 46216 | F56: SOARES | G56: MARCELO | I56: 410.54 | J56: 46258 | M56: =Tabela2246578910111213[[#This Row],[VENDA]]+Tabela2246578910111213[[#This Row],[MÃO DE OBRA]]-Tabela2246578910111213[[#This Row],[VALOR PAGO]] -> 410.54
B57: SMART | C57: 24403 | D57: 5707 | E57: 46217 | F57: LC COMPONENTES | G57: MARCELO | I57: 7105.72 | J57: 46238 | M57: =Tabela2246578910111213[[#This Row],[VENDA]]+Tabela2246578910111213[[#This Row],[MÃO DE OBRA]]-Tabela2246578910111213[[#This Row],[VALOR PAGO]] -> 7105.72
B58: SMART | C58: 24405 | D58: 5757 | E58: 46217 | F58: SOARES | G58: MARCELO | I58: 418.55 | J58: 46252 | M58: =Tabela2246578910111213[[#This Row],[VENDA]]+Tabela2246578910111213[[#This Row],[MÃO DE OBRA]]-Tabela2246578910111213[[#This Row],[VALOR PAGO]] -> 418.55
B59: STK | C59: 966 | D59: 946 | E59: 46218 | F59: RM CALCADOS | G59: MARCIANO | I59: 9323.84 | J59: 46239 | M59: =Tabela2246578910111213[[#This Row],[VENDA]]+Tabela2246578910111213[[#This Row],[MÃO DE OBRA]]-Tabela2246578910111213[[#This Row],[VALOR PAGO]] -> 9323.84
B60: STK | C60: 966 | D60: 946 | E60: 46218 | F60: RM CALCADOS | G60: MARCIANO | I60: 9320 | J60: 46246 | M60: =Tabela2246578910111213[[#This Row],[VENDA]]+Tabela2246578910111213[[#This Row],[MÃO DE OBRA]]-Tabela2246578910111213[[#This Row],[VALOR PAGO]] -> 9320
B61: STK | C61: 966 | D61: 946 | E61: 46218 | F61: RM CALCADOS | G61: MARCIANO | I61: 9320 | J61: 46253 | M61: =Tabela2246578910111213[[#This Row],[VENDA]]+Tabela2246578910111213[[#This Row],[MÃO DE OBRA]]-Tabela2246578910111213[[#This Row],[VALOR PAGO]] -> 9320
B62: STK | C62: 966 | D62: 946 | E62: 46218 | F62: RM CALCADOS | G62: MARCIANO | I62: 9320 | J62: 46260 | M62: =Tabela2246578910111213[[#This Row],[VENDA]]+Tabela2246578910111213[[#This Row],[MÃO DE OBRA]]-Tabela2246578910111213[[#This Row],[VALOR PAGO]] -> 9320
B63: STK | C63: 966 | D63: 946 | E63: 46218 | F63: RM CALCADOS | G63: MARCIANO | I63: 9320 | J63: 46267 | M63: =Tabela2246578910111213[[#This Row],[VENDA]]+Tabela2246578910111213[[#This Row],[MÃO DE OBRA]]-Tabela2246578910111213[[#This Row],[VALOR PAGO]] -> 9320
B64: STK | C64: 966 | D64: 946 | E64: 46218 | F64: RM CALCADOS | G64: MARCIANO | I64: 9320 | J64: 46274 | M64: =Tabela2246578910111213[[#This Row],[VENDA]]+Tabela2246578910111213[[#This Row],[MÃO DE OBRA]]-Tabela2246578910111213[[#This Row],[VALOR PAGO]] -> 9320
B65: STK | C65: 967 | D65: 950 | E65: 46219 | F65: MARIOTTA | G65: HENRIQUE | H65: 6777 | J65: 46239 | M65: =Tabela2246578910111213[[#This Row],[VENDA]]+Tabela2246578910111213[[#This Row],[MÃO DE OBRA]]-Tabela2246578910111213[[#This Row],[VALOR PAGO]] -> 6777
B66: STK | C66: 967 | D66: 950 | E66: 46219 | F66: MARIOTTA | G66: HENRIQUE | H66: 6777 | J66: 46249
B67: STK | C67: 967 | D67: 950 | E67: 46219 | F67: MARIOTTA | G67: HENRIQUE | H67: 6777 | J67: 46259
B68: STK | C68: 967 | D68: 950 | E68: 46219 | F68: MARIOTTA | G68: HENRIQUE | H68: 6777 | J68: 46269
B69: STK | C69: 967 | D69: 950 | E69: 46219 | F69: MARIOTTA | G69: HENRIQUE | H69: 6777 | J69: 46279
B70: STK | C70: 967 | D70: 950 | E70: 46219 | F70: MARIOTTA | G70: HENRIQUE | H70: 6777 | J70: 46289
B71: STK | C71: 967 | D71: 950 | E71: 46219 | F71: MARIOTTA | G71: HENRIQUE | H71: 6777 | J71: 46299
B72: STK | C72: 967 | D72: 950 | E72: 46219 | F72: MARIOTTA | G72: HENRIQUE | H72: 6777 | J72: 46309
M91: =Tabela2246578910111213[[#This Row],[VENDA]]+Tabela2246578910111213[[#This Row],[MÃO DE OBRA]]-Tabela2246578910111213[[#This Row],[VALOR PAGO]] -> 0
M92: =Tabela2246578910111213[[#This Row],[VENDA]]+Tabela2246578910111213[[#This Row],[MÃO DE OBRA]]-Tabela2246578910111213[[#This Row],[VALOR PAGO]] -> 0
M93: =Tabela2246578910111213[[#This Row],[VENDA]]+Tabela2246578910111213[[#This Row],[MÃO DE OBRA]]-Tabela2246578910111213[[#This Row],[VALOR PAGO]] -> 0
M94: =Tabela2246578910111213[[#This Row],[VENDA]]+Tabela2246578910111213[[#This Row],[MÃO DE OBRA]]-Tabela2246578910111213[[#This Row],[VALOR PAGO]] -> 0
M95: =Tabela2246578910111213[[#This Row],[VENDA]]+Tabela2246578910111213[[#This Row],[MÃO DE OBRA]]-Tabela2246578910111213[[#This Row],[VALOR PAGO]] -> 0
M96: =Tabela2246578910111213[[#This Row],[VENDA]]+Tabela2246578910111213[[#This Row],[MÃO DE OBRA]]-Tabela2246578910111213[[#This Row],[VALOR PAGO]] -> 0
M97: =Tabela2246578910111213[[#This Row],[VENDA]]+Tabela2246578910111213[[#This Row],[MÃO DE OBRA]]-Tabela2246578910111213[[#This Row],[VALOR PAGO]] -> 0
B99: TOTAL VENDA: | D99: =Tabela2246578910111213[[#Totals],[VENDA]] -> 0 | H99: =SUM(H21:H98) -> 270080.56 | I99: =SUM(Tabela2246578910111213[MÃO DE OBRA]) -> 84561.66
B100: TOTAL MÃO DE OBRA: | D100: =Tabela2246578910111213[[#Totals],[MÃO DE OBRA]] -> 0
B101: TOTAL: | C101: =SUM(D99+D100) -> 0 | F101: TOTAL RECEBIDO: | H101: =Tabela2246578910111213[[#Totals],[VALOR PAGO]] -> 0 | J101: TOTAL À RECEBER: | L101: =Tabela2246578910111213[[#Totals],[VALOR EM ABERTO]] -> 0

Sheet Inadimplencia
A1: DESTINATÁRIO | B1: REPRESENTANTE | C1: VENDA | D1: MÃO DE OBRA | E1: VENCIMENTO | F1: DATA DE PAGAMENTO | G1: VALOR PAGO | H1: VALOR EM ABERTO
A2: RM CALÇADOS | B2: MARCIANO | C2: 18954 | D2: 0 | E2: 46119 | H2: =C2 -> 18954
A3: RM CALÇADOS | B3: MARCIANO | C3: 18954 | D3: 0 | E3: 46126 | H3: =C3 -> 18954
A4: RM CALÇADOS | B4: MARCIANO | C4: 18954 | D4: 0 | E4: 46133 | H4: =C4 -> 18954
A5: GLAUCIA | B5: SILVANO | C5: 9515.57 | E5: 46114 | F5: 46135 | G5: 1291.53 | H5: 8224.04
A6: GLAUCIA | B6: SILVANO | C6: 9515.56 | E6: 46144 | H6: 9515.56
A7: NOSSA SRA DE FAT | B7: MARCIANO | C7: 662.4 | E7: 46136 | H7: 662.4
A8: YPORA | B8: MARCIANO | C8: 8783 | E8: 46120 | H8: 8783
A9: YPORA | B9: MARCIANO | C9: 8783 | E9: 46127 | H9: 8783
A10: YPORA | B10: MARCIANO | C10: 8783 | E10: 46134 | H10: 8783
A11: YPORA | B11: MARCIANO | C11: 8783 | E11: 46141 | H11: 8783
A12: SANTOS | B12: MARCIANO | C12: 6100 | E12: 46113 | H12: 6100
A13: SANTOS | B13: MARCIANO | C13: 6096 | E13: 46120 | H13: 6096
A14: SANTOS | B14: MARCIANO | C14: 6096 | E14: 46127 | H14: 6096
A15: SANTOS | B15: MARCIANO | C15: 6096 | E15: 46134 | H15: 6096
A16: SANTOS | B16: MARCIANO | C16: 6096 | E16: 46141 | H16: 6096
A17: ITAIPE | B17: MARCIANO | C17: 9041 | E17: 46120 | H17: 9041
... A36: MARIOTTA | B36: SILVANO | C36: 2356.6667 | E36: 46143 | H36: 2356.6667
A37: VIA BELLA | B37: MARCIANO | C37: 7098.15 | E37: 46143 | H37: 7098.15 | I37: pix já em poder no Diego para transferir
A38: VR CALÇADOS | B38: CLEMILSON | C38: 1755 | E38: 46143 | H38: 1755
H39: =SUM(H2:H38) -> 232827.58
E40: FERREIRA | H40: 189690
E41: GLAUCIA | H41: 25162.36
E42: MARIOTTA | H42: 7346.67

Sheet RESUMO FERREIRA
B1: FRETES
B2: NOTA FISCAL | C2: PEDIDO | D2: DATA DE EMISSÃO | E2: DESTINATÁRIO | F2: REPRESENTANTE | G2: VENDA | H2: VENCIMENTO
B3: 760 | C3: 711 | D3: 46092 | E3: SANTOS | F3: MARCIANO | G3: 6100 | H3: 46113
B4: 761 | C4: 712 | D4: 46092 | E4: ITAIPE | F4: MARCIANO | G4: 9045 | H4: 46113
B5: 762 | C5: 713 | D5: 46092 | E5: FELIPE NANUQUE | F5: MARCIANO | G5: 7767.5 | H5: 46113
B6: 525 | C6: 1019 | D6: 46360 | E6: RM CALÇADOS | F6: MARCIANO | G6: 18954 | H6: 46119
B7: 759 | C7: 709 | D7: 46092 | E7: YPORA | F7: MARCIANO | G7: 8783 | H7: 46120
B8: 760 | C8: 711 | D8: 46092 | E8: SANTOS | F8: MARCIANO | G8: 6096 | H8: 46120
B9: 761 | C9: 712 | D9: 46092 | E9: ITAIPE | F9: MARCIANO | G9: 9041 | H9: 46120
B10: 762 | C10: 713 | D10: 46092 | E10: FELIPE NANUQUE | F10: MARCIANO | G10: 7762 | H10: 46120
B11: 525 | C11: 1019 | D11: 46360 | E11: RM CALÇADOS | F11: MARCIANO | G11: 18954 | H11: 46126
B12: 759 | C12: 709 | D12: 46092 | E12: YPORA | F12: MARCIANO | G12: 8783 | H12: 46127
B13: 760 | C13: 711 | D13: 46092 | E13: SANTOS | F13: MARCIANO | G13: 6096 | H13: 46127
B14: 761 | C14: 712 | D14: 46092 | E14: ITAIPE | F14: MARCIANO | G14: 9041 | H14: 46127
... B28: 762 | C28: 713 | D28: 46092 | E28: FELIPE NANUQUE | F28: MARCIANO | G28: 7762 | H28: 46148
G29: =SUM(G3:G28) -> 238184.5
F30: Vencidas | G30: =SUM(G3:G16) -> 143138.5
F31: A vencer | G31: =SUM(G17:G28) -> 95046
B34: PEDIDOS EM PRODUÇÃO
B35: 1.000 ml | C35: Amalfi | E35: =1000*26.95 -> 26950 | F35: Integral
B40: PEDIDOS PARA FATURAR ATÉ 17/04
B41: 812 E 4410 | C41: Napa Linha Dakar | E41: 31936 | F41: Integral
B42: 4408 | C42: Amalfi Off White | E42: 5376.52 | F42: Integral
E43: =SUM(E41:E42) -> 37312.52
B47: BOLETOS
E48: 175568.87
B51: TOTAL | E51: =G29+E35+E43+E48 -> 478015.89

Sheet Silvano
A1: NF | B1: PEDIDO | C1: EMISSÃO | D1: CLIENTE | E1: REP | F1: VALOR | G1: VECTO
A2: 21723 | B2: 3637 | C2: 46072 | D2: GLAUCIA | E2: SILVANO | F2: 2809.31 | G2: 46093
A3: 21853 | B3: 3714 | C3: 46079 | D3: GLAUCIA | E3: SILVANO | F3: 2899.16 | G3: 46093
A4: 21938 | B4: 3818 | C4: 46084 | D4: GLAUCIA | E4: SILVANO | F4: 9515.57 | G4: 46114
A5: 22243 | B5: 3370 | C5: 46101 | D5: GLAUCIA | E5: SILVANO | F5: 1025.48 | G5: 46115
A6: 22243 | B6: 3370 | C6: 46101 | D6: GLAUCIA | E6: SILVANO | F6: 1025.48 | G6: 46122
A7: 22243 | B7: 3370 | C7: 46101 | D7: GLAUCIA | E7: SILVANO | F7: 1025.48 | G7: 46129
A8: 22243 | B8: 3370 | C8: 46101 | D8: GLAUCIA | E8: SILVANO | F8: 1025.48 | G8: 46136
A9: 22381 | B9: 4184 | C9: 46108 | D9: GLAUCIA | E9: SILVANO | F9: 573.84 | G9: 46122
A10: 22381 | B10: 4184 | C10: 46108 | D10: GLAUCIA | E10: SILVANO | F10: 573.84 | G10: 46129
A11: 22381 | B11: 4184 | C11: 46108 | D11: GLAUCIA | E11: SILVANO | F11: 573.84 | G11: 46136
F12: =SUM(F2:F11) -> 21047.48
D13: Pagou | F13: 2000
D14: Saldo atrasado | F14: =F12-F13 -> 19047.48
A19: NOTA FISCAL | B19: PEDIDO | C19: DATA DE EMISSÃO | D19: DESTINATÁRIO | E19: REPRESENTANTE | F19: VENDA | G19: VENCIMENTO
A20: 22371 | B20: 4207 | C20: 46108 | D20: MARIOTTA | E20: SILVANO | F20: 1892.4 | G20: 46136
A21: 22379 | B21: 4208 | C21: 46108 | D21: MARIOTTA | E21: SILVANO | F21: 942.66667 | G21: 46139
A22: 22368 | B22: 4205 | C22: 46108 | D22: MARIOTTA | E22: SILVANO | F22: 4990 | G22: 46136
A23: 834 | B23: 795 | C23: 46119 | D23: MARIOTTA | E23: SILVANO | F23: 2828 | G23: 46140
A24: 22591 | B24: 4318 | C24: 46122 | D24: MARIOTTA | E24: SILVANO | F24: 4990 | G24: 46136
D25: Saldo atrasado | F25: =SUM(F20:F24) -> 15643.067
A29: NOTA FISCAL | B29: PEDIDO | C29: DATA DE EMISSÃO | D29: DESTINATÁRIO | E29: REPRESENTANTE | F29: VENDA | G29: MÃO DE OBRA | H29: VENCIMENTO | I29: DATA DE PAGAMENTO | J29: VALOR PAGO | K29: VALOR EM ABERTO
A30: 21938 | B30: 3818 | C30: 46084 | D30: GLAUCIA | E30: SILVANO | F30: 9515.57 | H30: 46114 | I30: 46135 | J30: 1291.53 | K30: 8224.04
A31: 22243 | B31: 3370 | C31: 46101 | D31: GLAUCIA | E31: SILVANO | F31: 1025.48 | H31: 46115 | K31: 1025.48
A32: 22243 | B32: 3370 | C32: 46101 | D32: GLAUCIA | E32: SILVANO | F32: 1025.48 | H32: 46122 | K32: 1025.48
A33: 22243 | B33: 3370 | C33: 46101 | D33: GLAUCIA | E33: SILVANO | F33: 1025.48 | H33: 46129 | K33: 1025.48
A34: 22243 | B34: 3370 | C34: 46101 | D34: GLAUCIA | E34: SILVANO | F34: 1025.48 | H34: 46136 | K34: 1025.48
A35: 22381 | B35: 4184 | C35: 46108 | D35: GLAUCIA | E35: SILVANO | F35: 573.84 | H35: 46122 | K35: 573.84
A36: 22381 | B36: 4184 | C36: 46108 | D36: GLAUCIA | E36: SILVANO | F36: 573.84 | H36: 46129 | K36: 573.84
A37: 22381 | B37: 4184 | C37: 46108 | D37: GLAUCIA | E37: SILVANO | F37: 573.84 | H37: 46136 | K37: 573.84
K38: =SUM(K30:K37) -> 14047.48

Sheet Planilha1 (2)
A1: Dt.ent.item | B1: Dt.faturam | C1: Pedido | D1: Produto | E1: Desc.completa | F1: Grupo | G1: Descrição | H1: Nro.nota | I1: Nat.oper | J1: Qtd.item/Ft | K1: Qtd.solic.item | L1: Valor Fat+Valor IPI+Valor Frete | M1: Vlr.unit.líq | N1: Descr.Pos.item | O1: Cliente | P1: Razão social | Q1: Abreviação | R1: Cidade | S1: UF | T1: Sig.emp | U1: TITULO 1 - R$ | V1: Vecto | W1: TITULO 2 - R$ | X1: Vecto | Y1: TITULO 3 - R$ | Z1: Vecto | AA1: TITULO 4 - R$ | AB1: Vecto | AC1: TITULO 5 - R$ | AD1: Vecto | AE1: TITULO 6 - R$ | AF1: Vecto
A2: 45992 | B2: 45993 | C2: 475 | D2: 11922 | E2: NAPA METAL LYON PU 0,9MM - OURO LIGHT | F2: 39 | G2: STK LINE | H2: 515 | I2: 6102 | J2: 120 | K2: 120 | L2: 3234 | M2: 26.95 | N2: Faturado | O2: 1177 | P2: F & F IND.COM CALCADOS LTDA | Q2: CLEMILSON | R2: BIRIGUI | S2: SP | T2: SM3 | U2: 3234 | V2: 45993 | W2: 3234 | X2: 45993 | Y2: 3234 | Z2: 45993 | AA2: 3234 | AB2: 45993 | AC2: 3234 | AD2: 45993 | AE2: 3234 | AF2: 45993

Sheet Planilha1

Sheet BASE
A1: MÊS REF | B1: ANO | C1: EMPRESA | D1: NOTA FISCAL | E1: PEDIDO | F1: DATA EMISSÃO | G1: DESTINATÁRIO | H1: DESCRIÇÃO | I1: REPRESENTANTE | J1: VENDA | K1: MÃO DE OBRA | L1: TOTAL | M1: VENCIMENTO | N1: DATA DE PAGAMENTO 1 | O1: VALOR PAGO 1 | P1: VALOR EM ABERTO | Q1: DATA DE PAGAMENTO 2 | R1: VALOR EM ABERTO 2 | S1: DATA DE PAGAMENTO 3 | T1: VALOR EM ABERTO 3 | U1: DATA DE PAGAMENTO4 | V1: VALOR EM ABERTO 4 | W1: DATA DE PAGAMENTO 5 | X1: VALOR EM ABERTO 5 | Y1: STATUS | Z1: OBS | AA1: ORIGEM
A2: JANEIRO | B2: 2025 | C2: SMART | D2: 16412 | F2: 45665 | G2: SOARES | H2: Croco metal | J2: 0 | K2: 365.03 | L2: =J2+K2 -> 365.03 | M2: 45693 | N2: 45691 | O2: 365.03 | P2: =L2-O2 -> 0 | Y2: =IF(L2=0,"SEM VALOR",IF(P2<=0.01,"PAGO",IF(M2="","SEM VENCIMENTO",IF(M2<TODAY(),"VENCIDO","A VENCER")))) -> PAGO | AA2: Janeiro
A3: JANEIRO | B3: 2025 | C3: SMART | D3: 16437 | F3: 45667 | G3: SOARES | H3: Croco | J3: 0 | K3: 137.17 | L3: =J3+K3 -> 137.17 | M3: 45694 | N3: 45691 | O3: 137.17 | P3: =L3-O3 -> 0 | Y3: =IF(L3=0,"SEM VALOR",IF(P3<=0.01,"PAGO",IF(M3="","SEM VENCIMENTO",IF(M3<TODAY(),"VENCIDO","A VENCER")))) -> PAGO | AA3: Janeiro
A4: JANEIRO | B4: 2025 | C4: SMART | D4: 16437 | F4: 45667 | G4: SOARES | H4: Croco | J4: 0 | K4: 136 | L4: =J4+K4 -> 136 | M4: 45701 | N4: 45698 | O4: 136 | P4: =L4-O4 -> 0 | Y4: =IF(L4=0,"SEM VALOR",IF(P4<=0.01,"PAGO",IF(M4="","SEM VENCIMENTO",IF(M4<TODAY(),"VENCIDO","A VENCER")))) -> PAGO | AA4: Janeiro
A5: JANEIRO | B5: 2025 | C5: SMART | D5: 16437 | F5: 45667 | G5: SOARES | H5: Croco | J5: 0 | K5: 136 | L5: =J5+K5 -> 136 | M5: 45708 | N5: 45708 | O5: 136 | P5: =L5-O5 -> 0 | Y5: =IF(L5=0,"SEM VALOR",IF(P5<=0.01,"PAGO",IF(M5="","SEM VENCIMENTO",IF(M5<TODAY(),"VENCIDO","A VENCER")))) -> PAGO | AA5: Janeiro
A6: JANEIRO | B6: 2025 | C6: SMART | D6: 16488 | F6: 45671 | G6: SOARES | H6: Croco | J6: 0 | K6: 89.65 | L6: =J6+K6 -> 89.65 | M6: 45699 | N6: 45698 | O6: 89.65 | P6: =L6-O6 -> 0 | Y6: =IF(L6=0,"SEM VALOR",IF(P6<=0.01,"PAGO",IF(M6="","SEM VENCIMENTO",IF(M6<TODAY(),"VENCIDO","A VENCER")))) -> PAGO | AA6: Janeiro
A7: JANEIRO | B7: 2025 | C7: SMART | D7: 16488 | F7: 45671 | G7: SOARES | H7: Croco | J7: 0 | K7: 88 | L7: =J7+K7 -> 88 | M7: 45706 | N7: 45706 | O7: 88 | P7: =L7-O7 -> 0 | Y7: =IF(L7=0,"SEM VALOR",IF(P7<=0.01,"PAGO",IF(M7="","SEM VENCIMENTO",IF(M7<TODAY(),"VENCIDO","A VENCER")))) -> PAGO | AA7: Janeiro
A8: JANEIRO | B8: 2025 | C8: SMART | D8: 16488 | F8: 45671 | G8: SOARES | H8: Croco | J8: 0 | K8: 88 | L8: =J8+K8 -> 88 | M8: 45713 | N8: 45713 | O8: 88 | P8: =L8-O8 -> 0 | Y8: =IF(L8=0,"SEM VALOR",IF(P8<=0.01,"PAGO",IF(M8="","SEM VENCIMENTO",IF(M8<TODAY(),"VENCIDO","A VENCER")))) -> PAGO | AA8: Janeiro
A9: JANEIRO | B9: 2025 | C9: SMART | D9: 16540 | F9: 45674 | G9: SOARES | H9: Crocodile | J9: 0 | K9: 135.24 | L9: =J9+K9 -> 135.24 | M9: 45702 | N9: 45698 | O9: 135.24 | P9: =L9-O9 -> 0 | Y9: =IF(L9=0,"SEM VALOR",IF(P9<=0.01,"PAGO",IF(M9="","SEM VENCIMENTO",IF(M9<TODAY(),"VENCIDO","A VENCER")))) -> PAGO | AA9: Janeiro
A10: JANEIRO | B10: 2025 | C10: SMART | D10: 16542 | F10: 45674 | G10: SOARES | H10: Rafia glow | J10: 0 | K10: 267.38 | L10: =J10+K10 -> 267.38 | M10: 45702 | N10: 45698 | O10: 267.38 | P10: =L10-O10 -> 0 | Y10: =IF(L10=0,"SEM VALOR",IF(P10<=0.01,"PAGO",IF(M10="","SEM VENCIMENTO",IF(M10<TODAY(),"VENCIDO","A VENCER")))) -> PAGO | AA10: Janeiro
